Workbook

Sheet User Segmentation
A1: Generation | B1: Adoption Rate (U.S. 2024-25) | C1: Usage Frequency (Weekly+) | D1: Late Payment Incidence | E1: Regret After Use | J1: Revenue Source | K1: Typical Share
A2: Gen Z (18-28) | B2: 38% - 44% | C2: 0.4 | D2: 39% - 51% | E2: 27% - 64% | J2: Merchant fees | K2: 60–80%
A3: Millennials (29-44) | B3: 37% - 48% | C3: 0.28 | D3: 0.35 | E3: 30% - 57% | J3: Consumer interest | K3: 10–30%
A4: Gen X (45-60) | B4: 28% - 29% | C4: 0.1 | D4: 0.17 | E4: 22% - 37% | J4: Late fees | K4: 5–10%
A5: Baby Boomers (61-79) | B5: 13% - 21% | C5: 0.09 | D5: 0.11 | E5: 18% - 20% | J5: Interchange + other | K5: 5–15%
A15: Generation | B15: % BNPL Users
A16: Gen Z | B16: 44
A17: Millenials | B17: 48
A18: Gen X | B18: 31
A19: Baby Boomers | B19: 13
A21: Income Bracket | B21: % BNPL Users
A22: <50,000 | B22: 31
A23: 50,000-1,00,000 | B23: 32
A24: >1,00,000 | B24: 31
A27: Generation | B27: <50,000 | C27: 50,000-1,00,000 | D27: >1,00,000
A28: Gen Z | B28: 58 | C28: 32 | D28: 10
A29: Millenials | B29: 34 | C29: 41 | D29: 25
A30: Gen X | B30: 24 | C30: 39 | D30: 37
A31: Baby Boomers | B31: 42 | C31: 33 | D31: 25
A33: Generation | B33: Adjustment Factor
A34: Gen Z | B34: 1.6923077
A35: Millenial | B35: 1.7777778
A36: Gen X | B36: 1.2916667
A37: Baby Boomers | B37: 0.56521739
A39: Income Bracket | B39: <50,000 | C39: 50,000-1,00,000 | D39: >1,00,000
A40: Adjustment Factor | B40: 0.57407407 | C40: 1.1851852 | D40: 1.6315789
A43: What % of Gen uses BNPL services | H43: Column1 | I43: Column2
A44: Generation | B44: # Population (in M) | C44: Adoption Rate | D44: Weight | E44: Portfoliio Comp | F44: # of BNPL Users (in M) | H44: US Population (in M) | I44: 345
A45: Gen Z | B45: 71 | C45: 0.45 | D45: =GenSegment[[#This Row],[Adoption Rate ]]*GenSegment[[#This Row],['# Population (in M)]]/SUM(GenSegment['# Population (in M)]) -> 0.11576087 | E45: =GenSegment[[#This Row],[Weight]]/SUM(GenSegment[Weight]) -> 0.31188989 | F45: =$I$46*GenSegment[[#This Row],[Portfoliio Comp]] -> 16.140302 | H45: % of BNPL Users | I45: 0.15
A46: Millenial | B46: 74 | C46: 0.51 | D46: =GenSegment[[#This Row],[Adoption Rate ]]*GenSegment[[#This Row],['# Population (in M)]]/SUM(GenSegment['# Population (in M)]) -> 0.13673913 | E46: =GenSegment[[#This Row],[Weight]]/SUM(GenSegment[Weight]) -> 0.36841078 | F46: =$I$46*GenSegment[[#This Row],[Portfoliio Comp]] -> 19.065258 | H46: # of BNPL Users (in M) | I46: =I45*I44 -> 51.75
A47: Gen X | B47: 65.5 | C47: 0.32 | D47: =GenSegment[[#This Row],[Adoption Rate ]]*GenSegment[[#This Row],['# Population (in M)]]/SUM(GenSegment['# Population (in M)]) -> 0.075942029 | E47: =GenSegment[[#This Row],[Weight]]/SUM(GenSegment[Weight]) -> 0.20460758 | F47: =$I$46*GenSegment[[#This Row],[Portfoliio Comp]] -> 10.588442 | H47: # Total Loans (in M) | I47: 335.8
A48: Baby Boomer | B48: 65.5 | C48: 0.18 | D48: =GenSegment[[#This Row],[Adoption Rate ]]*GenSegment[[#This Row],['# Population (in M)]]/SUM(GenSegment['# Population (in M)]) -> 0.042717391 | E48: =GenSegment[[#This Row],[Weight]]/SUM(GenSegment[Weight]) -> 0.11509176 | F48: =$I$46*GenSegment[[#This Row],[Portfoliio Comp]] -> 5.9559986 | H48: Avg Loan per User | I48: =I47/I46 -> 6.4888889
H49: Avg MDR Rate | I49: =(5%+Dashboard!$K$25/10000) -> 0.05
H50: Avg Ticket Size | I50: ='Portfolio Metrics'!B4 -> 143.89084
H51: US Industry Revenue (in M) | I51: =SUMPRODUCT(ARPU_Table[[Deep Subprime]:[Super Prime]],Portfolio_Num[[Deep Subprime]:[Super Prime]]) -> 2416.8601
A52: What % of Income Bracket uses BNPL services
A53: Income Bracket | B53: Percentage of Population | C53: # Population (in M) | D53: Adoption Rate | E53: Weight | F53: Portfolio Comp | G53: # of BNPL Users (in M)
A54: <50,000 | B54: 0.54 | C54: =239.1*IncomeSegment[[#This Row],[Percentage of Population]] -> 129.114 | D54: 0.31 | E54: =IncomeSegment[[#This Row],[Adoption Rate]]*IncomeSegment[[#This Row],[Percentage of Population]] -> 0.1674 | F54: =IncomeSegment[[#This Row],[Weight]]/SUM(IncomeSegment[Weight]) -> 0.52182045 | G54: =$I$46*IncomeSegment[[#This Row],[Portfolio Comp]] -> 27.004208
A55: 50,000-1,00,000 | B55: 0.27 | C55: =239.1*IncomeSegment[[#This Row],[Percentage of Population]] -> 64.557 | D55: 0.35 | E55: =IncomeSegment[[#This Row],[Adoption Rate]]*IncomeSegment[[#This Row],[Percentage of Population]] -> 0.0945 | F55: =IncomeSegment[[#This Row],[Weight]]/SUM(IncomeSegment[Weight]) -> 0.29457606 | G55: =$I$46*IncomeSegment[[#This Row],[Portfolio Comp]] -> 15.244311
A56: >1,00,000 | B56: 0.19 | C56: =239.1*IncomeSegment[[#This Row],[Percentage of Population]] -> 45.429 | D56: 0.31 | E56: =IncomeSegment[[#This Row],[Adoption Rate]]*IncomeSegment[[#This Row],[Percentage of Population]] -> 0.0589 | F56: =IncomeSegment[[#This Row],[Weight]]/SUM(IncomeSegment[Weight]) -> 0.18360349 | G56: =$I$46*IncomeSegment[[#This Row],[Portfolio Comp]] -> 9.5014807
A58: % of Different Generations belonging to different Income Brackets
A59: Generation | B59: <50,000 | C59: 50,000-1,00,000 | D59: >1,00,000
A60: Gen Z | B60: 0.65 | C60: 0.3 | D60: 0.05
A61: Millenial | B61: 0.25 | C61: 0.5 | D61: 0.25
A62: Gen X | B62: 0.15 | C62: 0.55 | D62: 0.3
A63: Baby Boomer | B63: 0.3 | C63: 0.5 | D63: 0.2
A65: BNPL Portfolio Composition
A66: Generation | B66: <50,000 | C66: 50,000-1,00,000 | D66: >1,00,000
A67: Gen Z | B67: =$F45*B60 -> 10.491196 | C67: =$F45*C60 -> 4.8420905 | D67: =$F45*D60 -> 0.80701508
A68: Millenial | B68: =$F46*B61 -> 4.7663144 | C68: =$F46*C61 -> 9.5326289 | D68: =$F46*D61 -> 4.7663144
A69: Gen X | B69: =$F47*B62 -> 1.5882663 | C69: =$F47*C62 -> 5.8236431 | D69: =$F47*D62 -> 3.1765326
A70: Baby Boomer | B70: =$F48*B63 -> 1.7867996 | C70: =$F48*C63 -> 2.9779993 | D70: =$F48*D63 -> 1.1911997
A72: BNPL Portfolio Composition
A73: Generation | B73: <50,000 | C73: 50,000-1,00,000 | D73: >1,00,000
A74: Gen Z | B74: =B67*($G$54/SUM(Table1723[<50,000])) -> 15.204899 | C74: =C67*($G$55/SUM(Table1723[50,000-1,00,000])) -> 3.1848974 | D74: =D67*($G$56/SUM(Table1723[>1,00,000])) -> 0.7713299
A75: Millenial | B75: =B68*($G$54/SUM(Table1723[<50,000])) -> 6.9078234 | C75: =C68*($G$55/SUM(Table1723[50,000-1,00,000])) -> 6.270111 | D75: =D68*($G$56/SUM(Table1723[>1,00,000])) -> 4.555554
A76: Gen X | B76: =B69*($G$54/SUM(Table1723[<50,000])) -> 2.3018757 | C76: =C69*($G$55/SUM(Table1723[50,000-1,00,000])) -> 3.8305161 | D76: =D69*($G$56/SUM(Table1723[>1,00,000])) -> 3.0360704
A77: Baby Boomer | B77: =B70*($G$54/SUM(Table1723[<50,000])) -> 2.5896101 | C77: =C70*($G$55/SUM(Table1723[50,000-1,00,000])) -> 1.9587866 | D77: =D70*($G$56/SUM(Table1723[>1,00,000])) -> 1.1385264
A81: # BNPL Portfolio Composition (in M)
A82: Generation | B82: <50,000 | C82: 50,000-1,00,000 | D82: >1,00,000
A83: Gen Z | B83: =B74*($F45/SUM($B74:$D74)) -> 12.807789 | C83: =C74*($F45/SUM($B74:$D74)) -> 2.6827862 | D83: =D74*($F45/SUM($B74:$D74)) -> 0.64972679
A84: Millenial | B84: =B75*($F46/SUM($B75:$D75)) -> 7.4265948 | C84: =C75*($F46/SUM($B75:$D75)) -> 6.7409907 | D84: =D75*($F46/SUM($B75:$D75)) -> 4.8976721
A85: Gen X | B85: =B76*($F47/SUM($B76:$D76)) -> 2.6583822 | C85: =C76*($F47/SUM($B76:$D76)) -> 4.4237733 | D85: =D76*($F47/SUM($B76:$D76)) -> 3.5062865
A86: Baby Boomer | B86: =B77*($F48/SUM($B77:$D77)) -> 2.7121369 | C86: =C77*($F48/SUM($B77:$D77)) -> 2.0514662 | D86: =D77*($F48/SUM($B77:$D77)) -> 1.1923955
A88: % BNPL Portfolio Composition
A89: Generation | B89: <50,000 | C89: 50,000-1,00,000 | D89: >1,00,000
A90: Gen Z | B90: =B83/SUM(GenxIncome_Num[[<50,000]:[>1,00,000]]) -> 0.2474935 | C90: =C83/SUM(GenxIncome_Num[[<50,000]:[>1,00,000]]) -> 0.051841278 | D90: =D83/SUM(GenxIncome_Num[[<50,000]:[>1,00,000]]) -> 0.012555107
A91: Millenial | B91: =B84/SUM(GenxIncome_Num[[<50,000]:[>1,00,000]]) -> 0.14350908 | C91: =C84/SUM(GenxIncome_Num[[<50,000]:[>1,00,000]]) -> 0.13026069 | D91: =D84/SUM(GenxIncome_Num[[<50,000]:[>1,00,000]]) -> 0.094641007
A92: Gen X | B92: =B85/SUM(GenxIncome_Num[[<50,000]:[>1,00,000]]) -> 0.051369705 | C92: =C85/SUM(GenxIncome_Num[[<50,000]:[>1,00,000]]) -> 0.085483542 | D92: =D85/SUM(GenxIncome_Num[[<50,000]:[>1,00,000]]) -> 0.067754328
A93: Baby Boomer | B93: =B86/SUM(GenxIncome_Num[[<50,000]:[>1,00,000]]) -> 0.052408443 | C93: =C86/SUM(GenxIncome_Num[[<50,000]:[>1,00,000]]) -> 0.039641859 | D93: =D86/SUM(GenxIncome_Num[[<50,000]:[>1,00,000]]) -> 0.023041459

Sheet Default Rates
A1: Credit Category | B1: Credit Score
A2: Deep Subprime | B2: <580
A3: Subprime | B3: 580-619 | I3: Credit Category | J3: BNPL Loan Originations
A4: Near Prime | B4: 620-659 | I4: No Score | J4: 0.039
A5: Prime | B5: 660-719 | I5: Deep Subprime | J5: 0.45
A6: Super Prime | B6: >720 | I6: Subprime | J6: 0.16
I7: Near Prime | J7: 0.127
I8: Prime | J8: 0.132
A9: Credit Category | B9: # BNPL User Count | C9: BNPL Loan Originations | D9: BNPL Default Rates | I9: Super Prime | J9: 0.091
A10: No Score | B10: N/A | C10: 0.039 | D10: 0.041
A11: Deep Subprime | B11: =SUM(IncomexCredit_Num[Deep Subprime]) -> 11.97606 | C11: 0.45 | D11: 0.035
A12: Subprime | B12: =SUM(IncomexCredit_Num[Subprime]) -> 11.897983 | C12: 0.16 | D12: 0.011
A13: Near Prime | B13: =SUM(IncomexCredit_Num[Near Prime]) -> 9.1919163 | C13: 0.127 | D13: 0.008
A14: Prime | B14: =SUM(IncomexCredit_Num[Prime]) -> 10.241757 | C14: 0.132 | D14: 0.007
A15: Super Prime | B15: =SUM(IncomexCredit_Num[Super Prime]) -> 8.2522537 | C15: 0.091 | D15: 0.008
A17: What % of an Income Bracket lies in what Credit Category?
A18: Income Bracket | B18: Deep Subprime | C18: Subprime | D18: Near Prime | E18: Prime | F18: Super Prime | I18: Income Bracket | J18: # of BNPL Users (in M)
A19: <50,000 | B19: 0.38 | C19: 0.32 | D19: 0.15 | E19: 0.11 | F19: 0.04 | I19: <50,000 | J19: {='User Segmentation'!G54:G56} -> 27.004208
A20: 50,000-1,00,000 | B20: 0.1 | C20: 0.17 | D20: 0.25 | E20: 0.29 | F20: 0.19 | I20: 50,000-1,00,000 | J20: 15.244311
A21: >1,00,000 | B21: 0.02 | C21: 0.07 | D21: 0.14 | E21: 0.3 | F21: 0.45 | I21: >1,00,000 | J21: 9.5014807
A23: Income Bracket | B23: Deep Subprime | C23: Subprime | D23: Near Prime | E23: Prime | F23: Super Prime
A24: <50,000 | B24: =B19*$J19 -> 10.261599 | C24: =C19*$J19 -> 8.6413466 | D24: =D19*$J19 -> 4.0506312 | E24: =E19*$J19 -> 2.9704629 | F24: =F19*$J19 -> 1.0801683
A25: 50,000-1,00,000 | B25: =B20*$J20 -> 1.5244311 | C25: =C20*$J20 -> 2.5915329 | D25: =D20*$J20 -> 3.8110778 | E25: =E20*$J20 -> 4.4208502 | F25: =F20*$J20 -> 2.8964191
A26: >1,00,000 | B26: =B21*$J21 -> 0.19002961 | C26: =C21*$J21 -> 0.66510365 | D26: =D21*$J21 -> 1.3302073 | E26: =E21*$J21 -> 2.8504442 | F26: =F21*$J21 -> 4.2756663
A28: Default Rates by Income Brackets
A29: Income Bracket | B29: Default Rate
A30: <50,000 | B30: =$B19*$D$11+$C19*$D$12+$D19*$D$13+$E19*$D$14+$F19*$D$15 -> 0.01911
A31: 50,000-1,00,000 | B31: =$B20*$D$11+$C20*$D$12+$D20*$D$13+$E20*$D$14+$F20*$D$15 -> 0.01092
A32: >1,00,000 | B32: =$B21*$D$11+$C21*$D$12+$D21*$D$13+$E21*$D$14+$F21*$D$15 -> 0.00829
A34: What % of a Generation lies in what Credit Category?
A35: Generation | B35: Deep Subprime | C35: Subprime | D35: Near Prime | E35: Prime | F35: Super Prime
A36: Gen Z | B36: ='User Segmentation'!$B60*'Default Rates'!B$19+'User Segmentation'!$C60*'Default Rates'!B$20+'User Segmentation'!$D60*'Default Rates'!B$21 -> 0.278 | C36: ='User Segmentation'!$B60*'Default Rates'!C$19+'User Segmentation'!$C60*'Default Rates'!C$20+'User Segmentation'!$D60*'Default Rates'!C$21+0.0292 -> 0.2917 | D36: ='User Segmentation'!$B60*'Default Rates'!D$19+'User Segmentation'!$C60*'Default Rates'!D$20+'User Segmentation'!$D60*'Default Rates'!D$21+0.05005 -> 0.22955 | E36: =('User Segmentation'!$B60*'Default Rates'!E$19+'User Segmentation'!$C60*'Default Rates'!E$20+'User Segmentation'!$D60*'Default Rates'!E$21)*0.75 -> 0.130125 | F36: =('User Segmentation'!$B60*'Default Rates'!F$19+'User Segmentation'!$C60*'Default Rates'!F$20+'User Segmentation'!$D60*'Default Rates'!F$21)*0.75 -> 0.079125
A37: Millenial | B37: ='User Segmentation'!$B61*'Default Rates'!B$19+'User Segmentation'!$C61*'Default Rates'!B$20+'User Segmentation'!$D61*'Default Rates'!B$21 -> 0.15 | C37: ='User Segmentation'!$B61*'Default Rates'!C$19+'User Segmentation'!$C61*'Default Rates'!C$20+'User Segmentation'!$D61*'Default Rates'!C$21 -> 0.1825 | D37: ='User Segmentation'!$B61*'Default Rates'!D$19+'User Segmentation'!$C61*'Default Rates'!D$20+'User Segmentation'!$D61*'Default Rates'!D$21 -> 0.1975 | E37: ='User Segmentation'!$B61*'Default Rates'!E$19+'User Segmentation'!$C61*'Default Rates'!E$20+'User Segmentation'!$D61*'Default Rates'!E$21 -> 0.2475 | F37: ='User Segmentation'!$B61*'Default Rates'!F$19+'User Segmentation'!$C61*'Default Rates'!F$20+'User Segmentation'!$D61*'Default Rates'!F$21 -> 0.2175
A38: Gen X | B38: ='User Segmentation'!$B62*'Default Rates'!B$19+'User Segmentation'!$C62*'Default Rates'!B$20+'User Segmentation'!$D62*'Default Rates'!B$21 -> 0.118 | C38: ='User Segmentation'!$B62*'Default Rates'!C$19+'User Segmentation'!$C62*'Default Rates'!C$20+'User Segmentation'!$D62*'Default Rates'!C$21 -> 0.1625 | D38: ='User Segmentation'!$B62*'Default Rates'!D$19+'User Segmentation'!$C62*'Default Rates'!D$20+'User Segmentation'!$D62*'Default Rates'!D$21 -> 0.202 | E38: ='User Segmentation'!$B62*'Default Rates'!E$19+'User Segmentation'!$C62*'Default Rates'!E$20+'User Segmentation'!$D62*'Default Rates'!E$21 -> 0.266 | F38: ='User Segmentation'!$B62*'Default Rates'!F$19+'User Segmentation'!$C62*'Default Rates'!F$20+'User Segmentation'!$D62*'Default Rates'!F$21 -> 0.2455
A39: Baby Boomer | B39: ='User Segmentation'!$B63*'Default Rates'!B$19+'User Segmentation'!$C63*'Default Rates'!B$20+'User Segmentation'!$D63*'Default Rates'!B$21 -> 0.168 | C39: ='User Segmentation'!$B63*'Default Rates'!C$19+'User Segmentation'!$C63*'Default Rates'!C$20+'User Segmentation'!$D63*'Default Rates'!C$21 -> 0.195 | D39: ='User Segmentation'!$B63*'Default Rates'!D$19+'User Segmentation'!$C63*'Default Rates'!D$20+'User Segmentation'!$D63*'Default Rates'!D$21 -> 0.198 | E39: ='User Segmentation'!$B63*'Default Rates'!E$19+'User Segmentation'!$C63*'Default Rates'!E$20+'User Segmentation'!$D63*'Default Rates'!E$21 -> 0.238 | F39: ='User Segmentation'!$B63*'Default Rates'!F$19+'User Segmentation'!$C63*'Default Rates'!F$20+'User Segmentation'!$D63*'Default Rates'!F$21 -> 0.197
A42: Default Rates by Generation
A43: Generation | B43: Default Rates
A44: Gen Z | B44: ='User Segmentation'!B60*'Default Rates'!B58+'User Segmentation'!C60*'Default Rates'!C58+'User Segmentation'!D60*'Default Rates'!D58 -> 0.01968632
A45: Millenial | B45: ='User Segmentation'!B61*'Default Rates'!B59+'User Segmentation'!C61*'Default Rates'!C59+'User Segmentation'!D61*'Default Rates'!D59 -> 0.012658075
A46: Gen X | B46: ='User Segmentation'!B62*'Default Rates'!B60+'User Segmentation'!C62*'Default Rates'!C60+'User Segmentation'!D62*'Default Rates'!D60 -> 0.0113595
A47: Baby Boomer | B47: ='User Segmentation'!B63*'Default Rates'!B61+'User Segmentation'!C63*'Default Rates'!C61+'User Segmentation'!D63*'Default Rates'!D61 -> 0.012851
A49: Generation Default Behaviour Multiplier
A50: Generation | B50: <50,000 | C50: 50,000-1,00,000 | D50: >1,00,000
A51: Gen Z | B51: 1.23 | C51: 1.2 | D51: 1.15
A52: Millenial | B52: 1.05 | C52: 1.02 | D52: 1
A53: Gen X | B53: 1 | C53: 1 | D53: 1
A54: Baby Boomer | B54: 1 | C54: 1 | D54: 1
A56: %Default Rates by User Segment
A57: Generation | B57: <50,000 | C57: 50,000-1,00,000 | D57: >1,00,000
A58: Gen Z | B58: =$B$30*B51 -> 0.0235053 | C58: =$B$31*C51 -> 0.013104 | D58: =$B$32*D51 -> 0.0095335
A59: Millenial | B59: =$B$30*B52 -> 0.0200655 | C59: =$B$31*C52 -> 0.0111384 | D59: =$B$32*D52 -> 0.00829
A60: Gen X | B60: =$B$30*B53 -> 0.01911 | C60: =$B$31*C53 -> 0.01092 | D60: =$B$32*D53 -> 0.00829
A61: Baby Boomer | B61: =$B$30*B54 -> 0.01911 | C61: =$B$31*C54 -> 0.01092 | D61: =$B$32*D54 -> 0.00829

Sheet Portfolio x PD x Loan Count
A1: Generation | B1: Income Bracket | C1: Deep Subprime | D1: Sub Prime | E1: Near Prime | F1: Prime | G1: Super Prime
A2: Gen Z | B2: <50,000 | C2: ='User Segmentation'!$B60*'Default Rates'!B19 -> 0.247 | D2: ='User Segmentation'!$B60*'Default Rates'!C19 -> 0.208 | E2: ='User Segmentation'!$B60*'Default Rates'!D19 -> 0.0975 | F2: ='User Segmentation'!$B60*'Default Rates'!E19 -> 0.0715 | G2: ='User Segmentation'!$B60*'Default Rates'!F19 -> 0.026
A3: Gen Z | B3: 50,000-1,00,000 | C3: ='User Segmentation'!$C60*'Default Rates'!B20 -> 0.03 | D3: ='User Segmentation'!$C60*'Default Rates'!C20 -> 0.051 | E3: ='User Segmentation'!$C60*'Default Rates'!D20 -> 0.075 | F3: ='User Segmentation'!$C60*'Default Rates'!E20 -> 0.087 | G3: ='User Segmentation'!$C60*'Default Rates'!F20 -> 0.057
A4: Gen Z | B4: >1,00,000 | C4: ='User Segmentation'!$D60*'Default Rates'!B21 -> 0.001 | D4: ='User Segmentation'!$D60*'Default Rates'!C21 -> 0.0035 | E4: ='User Segmentation'!$D60*'Default Rates'!D21 -> 0.007 | F4: ='User Segmentation'!$D60*'Default Rates'!E21 -> 0.015 | G4: ='User Segmentation'!$D60*'Default Rates'!F21 -> 0.0225
A5: Millenial | B5: <50,000 | C5: ='User Segmentation'!$B61*'Default Rates'!B19 -> 0.095 | D5: ='User Segmentation'!$B61*'Default Rates'!C19 -> 0.08 | E5: ='User Segmentation'!$B61*'Default Rates'!D19 -> 0.0375 | F5: ='User Segmentation'!$B61*'Default Rates'!E19 -> 0.0275 | G5: ='User Segmentation'!$B61*'Default Rates'!F19 -> 0.01
A6: Millenial | B6: 50,000-1,00,000 | C6: ='User Segmentation'!$C61*'Default Rates'!B20 -> 0.05 | D6: ='User Segmentation'!$C61*'Default Rates'!C20 -> 0.085 | E6: ='User Segmentation'!$C61*'Default Rates'!D20 -> 0.125 | F6: ='User Segmentation'!$C61*'Default Rates'!E20 -> 0.145 | G6: ='User Segmentation'!$C61*'Default Rates'!F20 -> 0.095
A7: Millenial | B7: >1,00,000 | C7: ='User Segmentation'!$D61*'Default Rates'!B21 -> 0.005 | D7: ='User Segmentation'!$D61*'Default Rates'!C21 -> 0.0175 | E7: ='User Segmentation'!$D61*'Default Rates'!D21 -> 0.035 | F7: ='User Segmentation'!$D61*'Default Rates'!E21 -> 0.075 | G7: ='User Segmentation'!$D61*'Default Rates'!F21 -> 0.1125
A8: Gen X | B8: <50,000 | C8: ='User Segmentation'!$B62*'Default Rates'!B19 -> 0.057 | D8: ='User Segmentation'!$B62*'Default Rates'!C19 -> 0.048 | E8: ='User Segmentation'!$B62*'Default Rates'!D19 -> 0.0225 | F8: ='User Segmentation'!$B62*'Default Rates'!E19 -> 0.0165 | G8: ='User Segmentation'!$B62*'Default Rates'!F19 -> 0.006
A9: Gen X | B9: 50,000-1,00,000 | C9: ='User Segmentation'!$C62*'Default Rates'!B20 -> 0.055 | D9: ='User Segmentation'!$C62*'Default Rates'!C20 -> 0.0935 | E9: ='User Segmentation'!$C62*'Default Rates'!D20 -> 0.1375 | F9: ='User Segmentation'!$C62*'Default Rates'!E20 -> 0.1595 | G9: ='User Segmentation'!$C62*'Default Rates'!F20 -> 0.1045 | J9: Generation | K9: # of BNPL Users (in M)
A10: Gen X | B10: >1,00,000 | C10: ='User Segmentation'!$D62*'Default Rates'!B21 -> 0.006 | D10: ='User Segmentation'!$D62*'Default Rates'!C21 -> 0.021 | E10: ='User Segmentation'!$D62*'Default Rates'!D21 -> 0.042 | F10: ='User Segmentation'!$D62*'Default Rates'!E21 -> 0.09 | G10: ='User Segmentation'!$D62*'Default Rates'!F21 -> 0.135 | J10: Gen Z | K10: =SUM('User Segmentation'!B83:D83) -> 16.140302
A11: Baby Boomer | B11: <50,000 | C11: ='User Segmentation'!$B$63*'Default Rates'!B19 -> 0.114 | D11: ='User Segmentation'!$B63*'Default Rates'!C19 -> 0.096 | E11: ='User Segmentation'!$B63*'Default Rates'!D19 -> 0.045 | F11: ='User Segmentation'!$B63*'Default Rates'!E19 -> 0.033 | G11: ='User Segmentation'!$B63*'Default Rates'!F19 -> 0.012 | J11: Millenial | K11: =SUM('User Segmentation'!B84:D84) -> 19.065258
A12: Baby Boomer | B12: 50,000-1,00,000 | C12: ='User Segmentation'!$C$63*'Default Rates'!B20 -> 0.05 | D12: ='User Segmentation'!$C$63*'Default Rates'!C20 -> 0.085 | E12: ='User Segmentation'!$C$63*'Default Rates'!D20 -> 0.125 | F12: ='User Segmentation'!$C$63*'Default Rates'!E20 -> 0.145 | G12: ='User Segmentation'!$C$63*'Default Rates'!F20 -> 0.095 | J12: Gen X | K12: =SUM('User Segmentation'!B85:D85) -> 10.588442
A13: Baby Boomer | B13: >1,00,000 | C13: ='User Segmentation'!$D$63*'Default Rates'!B21 -> 0.004 | D13: ='User Segmentation'!$D$63*'Default Rates'!C21 -> 0.014 | E13: ='User Segmentation'!$D$63*'Default Rates'!D21 -> 0.028 | F13: ='User Segmentation'!$D$63*'Default Rates'!E21 -> 0.06 | G13: ='User Segmentation'!$D$63*'Default Rates'!F21 -> 0.09 | J13: Baby Boomer | K13: =SUM('User Segmentation'!B86:D86) -> 5.9559986
A16: Generation | B16: Income Bracket | C16: Deep Subprime | D16: Sub Prime | E16: Near Prime | F16: Prime | G16: Super Prime | O16: Income Bracket | P16: Sum
A17: Gen Z | B17: <50,000 | C17: =C2*$K$10 -> 3.9866545 | D17: =D2*$K$10 -> 3.3571827 | E17: =E2*$K$10 -> 1.5736794 | F17: =F2*$K$10 -> 1.1540316 | G17: =G2*$K$10 -> 0.41964784 | O17: <50k | P17: =SUM(Table40[[#This Row],[Deep Subprime]:[Super Prime]],C20:G20,C23:G23,C26:G26) -> 18.632576
A18: Gen Z | B18: 50,000-1,00,000 | C18: =C3*$K$10 -> 0.48420905 | D18: =D3*$K$10 -> 0.82315538 | E18: =E3*$K$10 -> 1.2105226 | F18: =F3*$K$10 -> 1.4042062 | G18: =G3*$K$10 -> 0.91999719 | O18: 50k-100k | P18: =SUM(Table40[[#This Row],[Deep Subprime]:[Super Prime]],C21:G21,C24:G24,C27:G27) -> 23.176362
A19: Gen Z | B19: >1,00,000 | C19: =C4*$K$10 -> 0.016140302 | D19: =D4*$K$10 -> 0.056491056 | E19: =E4*$K$10 -> 0.11298211 | F19: =F4*$K$10 -> 0.24210452 | G19: =G4*$K$10 -> 0.36315679 | O19: >100k | P19: =SUM(Table40[[#This Row],[Deep Subprime]:[Super Prime]],C22:G22,C25:G25,C28:G28) -> 9.7422406
A20: Millenial | B20: <50,000 | C20: =C5*$K$11 -> 1.8111995 | D20: =D5*$K$11 -> 1.5252206 | E20: =E5*$K$11 -> 0.71494716 | F20: =F5*$K$11 -> 0.52429459 | G20: =G5*$K$11 -> 0.19065258
A21: Millenial | B21: 50,000-1,00,000 | C21: =C6*$K$11 -> 0.95326289 | D21: =D6*$K$11 -> 1.6205469 | E21: =E6*$K$11 -> 2.3831572 | F21: =F6*$K$11 -> 2.7644624 | G21: =G6*$K$11 -> 1.8111995
A22: Millenial | B22: >1,00,000 | C22: =C7*$K$11 -> 0.095326289 | D22: =D7*$K$11 -> 0.33364201 | E22: =E7*$K$11 -> 0.66728402 | F22: =F7*$K$11 -> 1.4298943 | G22: =G7*$K$11 -> 2.1448415 | O22: Generation | P22: Sum
A23: Gen X | B23: <50,000 | C23: =C8*$K$12 -> 0.60354119 | D23: =D8*$K$12 -> 0.50824522 | E23: =E8*$K$12 -> 0.23823995 | F23: =F8*$K$12 -> 0.17470929 | G23: =G8*$K$12 -> 0.063530652 | O23: Gen Z | P23: =SUM(C31:G33) -> 19.161126
A24: Gen X | B24: 50,000-1,00,000 | C24: =C9*$K$12 -> 0.58236431 | D24: =D9*$K$12 -> 0.99001933 | E24: =E9*$K$12 -> 1.4559108 | F24: =F9*$K$12 -> 1.6888565 | G24: =G9*$K$12 -> 1.1064922 | O24: Millenial | P24: =SUM(C34:G36) -> 17.733488
A25: Gen X | B25: >1,00,000 | C25: =C10*$K$12 -> 0.063530652 | D25: =D10*$K$12 -> 0.22235728 | E25: =E10*$K$12 -> 0.44471456 | F25: =F10*$K$12 -> 0.95295978 | G25: =G10*$K$12 -> 1.4294397 | O25: Gen X | P25: =SUM(C37:G39) -> 9.1684621
A26: Baby Boomer | B26: <50,000 | C26: =C11*$K$13 -> 0.67898384 | D26: =D11*$K$13 -> 0.57177587 | E26: =E11*$K$13 -> 0.26801994 | F26: =F11*$K$13 -> 0.19654795 | G26: =G11*$K$13 -> 0.071471984 | O26: Baby Boomer | P26: =SUM(C40:G42) -> 5.6869231
A27: Baby Boomer | B27: 50,000-1,00,000 | C27: =C12*$K$13 -> 0.29779993 | D27: =D12*$K$13 -> 0.50625988 | E27: =E12*$K$13 -> 0.74449983 | F27: =F12*$K$13 -> 0.8636198 | G27: =G12*$K$13 -> 0.56581987
A28: Baby Boomer | B28: >1,00,000 | C28: =C13*$K$13 -> 0.023823995 | D28: =D13*$K$13 -> 0.083383981 | E28: =E13*$K$13 -> 0.16676796 | F28: =F13*$K$13 -> 0.35735992 | G28: =G13*$K$13 -> 0.53603988
A30: Generation | B30: Income Bracket | C30: Deep Subprime | D30: Sub Prime | E30: Near Prime | F30: Prime | G30: Super Prime | O30: Income Bracket | P30: # of BNPL Users (in M)
A31: Gen Z | B31: <50,000 | C31: =C17*$P31/$P17 -> 5.7778616 | D31: =D17*$P$31/$P$17 -> 4.8655677 | E31: =E17*$P$31/$P$17 -> 2.2807349 | F31: =F17*$P$31/$P$17 -> 1.6725389 | G31: =G17*$P$31/$P$17 -> 0.60819596 | O31: <50,000 | P31: ='User Segmentation'!G54 -> 27.004208
A32: Gen Z | B32: 50,000-1,00,000 | C32: =C18*$P32/$P18 -> 0.31848974 | D32: =D18*$P32/$P18 -> 0.54143255 | E32: =E18*$P32/$P18 -> 0.79622434 | F32: =F18*$P32/$P18 -> 0.92362024 | G32: =G18*$P32/$P18 -> 0.6051305 | O32: 50,000-1,00,000 | P32: ='User Segmentation'!G55 -> 15.244311
A33: Gen Z | B33: >1,00,000 | C33: =C19*$P33/$P19 -> 0.015741426 | D33: =D19*$P33/$P19 -> 0.055094993 | E33: =E19*$P33/$P19 -> 0.11018999 | F33: =F19*$P33/$P19 -> 0.2361214 | G33: =G19*$P33/$P19 -> 0.3541821 | O33: >1,00,000 | P33: ='User Segmentation'!G56 -> 9.5014807
A34: Millenial | B34: <50,000 | C34: =C20*$P31/$P17 -> 2.6249729 | D34: =D20*$P31/$P17 -> 2.2105035 | E34: =E20*$P31/$P17 -> 1.0361735 | F34: =F20*$P31/$P17 -> 0.75986057 | G34: =G20*$P31/$P17 -> 0.27631294
A35: Millenial | B35: 50,000-1,00,000 | C35: =C21*$P32/$P18 -> 0.6270111 | D35: =D21*$P32/$P18 -> 1.0659189 | E35: =E21*$P32/$P18 -> 1.5675277 | F35: =F21*$P32/$P18 -> 1.8183322 | G35: =G21*$P32/$P18 -> 1.1913211
A36: Millenial | B36: >1,00,000 | C36: =C22*$P33/$P19 -> 0.092970491 | D36: =D22*$P33/$P19 -> 0.32539672 | E36: =E22*$P33/$P19 -> 0.65079343 | F36: =F22*$P33/$P19 -> 1.3945574 | G36: =G22*$P33/$P19 -> 2.091836
A37: Gen X | B37: <50,000 | C37: =C23*$P31/$P17 -> 0.87471275 | D37: =D23*$P31/$P17 -> 0.73660021 | E37: =E23*$P31/$P17 -> 0.34528135 | F37: =F23*$P31/$P17 -> 0.25320632 | G37: =G23*$P31/$P17 -> 0.092075026
A38: Gen X | B38: 50,000-1,00,000 | C38: =C24*$P32/$P18 -> 0.38305161 | D38: =D24*$P32/$P18 -> 0.65118774 | E38: =E24*$P32/$P18 -> 0.95762903 | F38: =F24*$P32/$P18 -> 1.1108497 | G38: =G24*$P32/$P18 -> 0.72779806
A39: Gen X | B39: >1,00,000 | C39: =C25*$P33/$P19 -> 0.061960619 | D39: =D25*$P33/$P19 -> 0.21686217 | E39: =E25*$P33/$P19 -> 0.43372434 | F39: =F25*$P33/$P19 -> 0.92940929 | G39: =G25*$P33/$P19 -> 1.3941139
A40: Baby Boomer | B40: <50,000 | C40: =C26*$P31/$P17 -> 0.98405184 | D40: =D26*$P31/$P17 -> 0.82867524 | E40: =E26*$P31/$P17 -> 0.38844152 | F40: =F26*$P31/$P17 -> 0.28485711 | G40: =G26*$P31/$P17 -> 0.1035844
A41: Baby Boomer | B41: 50,000-1,00,000 | C41: =C27*$P32/$P18 -> 0.19587866 | D41: =D27*$P32/$P18 -> 0.33299373 | E41: =E27*$P32/$P18 -> 0.48969666 | F41: =F27*$P32/$P18 -> 0.56804813 | G41: =G27*$P32/$P18 -> 0.37216946
A42: Baby Boomer | B42: >1,00,000 | C42: =C28*$P33/$P19 -> 0.023235232 | D42: =D28*$P33/$P19 -> 0.081323313 | E42: =E28*$P33/$P19 -> 0.16264663 | F42: =F28*$P33/$P19 -> 0.34852848 | G42: =G28*$P33/$P19 -> 0.52279273
A46: # BNPL Portfolio (in M)
A47: Generation | B47: Income Bracket | C47: Deep Subprime | D47: Sub Prime | E47: Near Prime | F47: Prime | G47: Super Prime | J47: Income Bracket | K47: # of BNPL Users (in M)
A48: Gen Z | B48: <50,000 | C48: =C31*$K$10/$P$23 -> 4.8669597 | D48: =D31*$K$10/$P$23 -> 4.0984924 | E48: =E31*$K$10/$P$23 -> 1.9211683 | F48: =F31*$K$10/$P$23 -> 1.4088568 | G48: =G31*$K$10/$P$23 -> 0.51231155 | J48: <50,000 | K48: =P31 -> 27.004208
A49: Gen Z | B49: 50,000-1,00,000 | C49: =C32*$K$10/$P$23 -> 0.26827862 | D49: =D32*$K$10/$P$23 -> 0.45607365 | E49: =E32*$K$10/$P$23 -> 0.67069654 | F49: =F32*$K$10/$P$23 -> 0.77800798 | G49: =G32*$K$10/$P$23 -> 0.50972937 | J49: 50,000-1,00,000 | K49: =P32 -> 15.244311
A50: Gen Z | B50: >1,00,000 | C50: =C33*$K$10/$P$23 -> 0.013259731 | D50: =D33*$K$10/$P$23 -> 0.046409057 | E50: =E33*$K$10/$P$23 -> 0.092818114 | F50: =F33*$K$10/$P$23 -> 0.19889596 | G50: =G33*$K$10/$P$23 -> 0.29834394 | J50: >1,00,000 | K50: =P33 -> 9.5014807
A51: Millenial | B51: <50,000 | C51: =C34*$K$11/$P$24 -> 2.822106 | D51: =D34*$K$11/$P$24 -> 2.3765103 | E51: =E34*$K$11/$P$24 -> 1.1139892 | F51: =F34*$K$11/$P$24 -> 0.81692543 | G51: =G34*$K$11/$P$24 -> 0.29706379
A52: Millenial | B52: 50,000-1,00,000 | C52: =C35*$K$11/$P$24 -> 0.67409907 | D52: =D35*$K$11/$P$24 -> 1.1459684 | E52: =E35*$K$11/$P$24 -> 1.6852477 | F52: =F35*$K$11/$P$24 -> 1.9548873 | G52: =G35*$K$11/$P$24 -> 1.2807882
A53: Millenial | B53: >1,00,000 | C53: =C36*$K$11/$P$24 -> 0.099952492 | D53: =D36*$K$11/$P$24 -> 0.34983372 | E53: =E36*$K$11/$P$24 -> 0.69966745 | F53: =F36*$K$11/$P$24 -> 1.4992874 | G53: =G36*$K$11/$P$24 -> 2.2489311 | J53: Credit Category | K53: # BNPL User Count
A54: Gen X | B54: <50,000 | C54: =C37*$K$12/$P$25 -> 1.0101853 | D54: =D37*$K$12/$P$25 -> 0.85068232 | E54: =E37*$K$12/$P$25 -> 0.39875734 | F54: =F37*$K$12/$P$25 -> 0.29242205 | G54: =G37*$K$12/$P$25 -> 0.10633529 | J54: No Score | K54: N/A
A55: Gen X | B55: 50,000-1,00,000 | C55: =C38*$K$12/$P$25 -> 0.44237733 | D55: =D38*$K$12/$P$25 -> 0.75204146 | E55: =E38*$K$12/$P$25 -> 1.1059433 | F55: =F38*$K$12/$P$25 -> 1.2828943 | G55: =G38*$K$12/$P$25 -> 0.84051692 | J55: Deep Subprime | K55: =SUM(IncomexCredit_Num[Deep Subprime]) -> 11.97606
A56: Gen X | B56: >1,00,000 | C56: =C39*$K$12/$P$25 -> 0.071556867 | D56: =D39*$K$12/$P$25 -> 0.25044904 | E56: =E39*$K$12/$P$25 -> 0.50089807 | F56: =F39*$K$12/$P$25 -> 1.073353 | G56: =G39*$K$12/$P$25 -> 1.6100295 | J56: Subprime | K56: =SUM(IncomexCredit_Num[Subprime]) -> 11.897983
A57: Baby Boomer | B57: <50,000 | C57: =C40*$K$13/$P$26 -> 1.030612 | D57: =D40*$K$13/$P$26 -> 0.86788382 | E57: =E40*$K$13/$P$26 -> 0.40682054 | F57: =F40*$K$13/$P$26 -> 0.29833506 | G57: =G40*$K$13/$P$26 -> 0.10848548 | J57: Near Prime | K57: =SUM(IncomexCredit_Num[Near Prime]) -> 9.1919163
A58: Baby Boomer | B58: 50,000-1,00,000 | C58: =C41*$K$13/$P$26 -> 0.20514662 | D58: =D41*$K$13/$P$26 -> 0.34874925 | E58: =E41*$K$13/$P$26 -> 0.51286655 | F58: =F41*$K$13/$P$26 -> 0.5949252 | G58: =G41*$K$13/$P$26 -> 0.38977858 | J58: Prime | K58: =SUM(IncomexCredit_Num[Prime]) -> 10.241757
A59: Baby Boomer | B59: >1,00,000 | C59: =C42*$K$13/$P$26 -> 0.024334602 | D59: =D42*$K$13/$P$26 -> 0.085171107 | E59: =E42*$K$13/$P$26 -> 0.17034221 | F59: =F42*$K$13/$P$26 -> 0.36501903 | G59: =G42*$K$13/$P$26 -> 0.54752855 | J59: Super Prime | K59: =SUM(IncomexCredit_Num[Super Prime]) -> 8.2522537
C61: =SUM(Table42[Deep Subprime]) -> 11.528868 | D61: =SUM(Table42[Sub Prime]) -> 11.628265 | E61: =SUM(Table42[Near Prime]) -> 9.2792153 | F61: =SUM(Table42[Prime]) -> 10.563809 | G61: =SUM(Table42[Super Prime]) -> 8.7498423
A62: # BNPL Portfolio (in M)
A63: Generation | B63: Income Bracket | C63: Deep Subprime | D63: Sub Prime | E63: Near Prime | F63: Prime | G63: Super Prime
A64: Gen Z | B64: <50,000 | C64: =C48*$K$55/C$61 -> 5.0557435 | D64: =D48*$K$56/D$61 -> 4.1935573 | E64: =E48*$K$57/E$61 -> 1.9030939 | F64: =F48*$K$58/F$61 -> 1.3659058 | G64: =G48*$K$59/G$61 -> 0.48317727
A65: Gen Z | B65: 50,000-1,00,000 | C65: =C49*$K$55/C$61 -> 0.27868483 | D65: =D49*$K$56/D$61 -> 0.46665231 | E65: =E49*$K$57/E$61 -> 0.66438661 | F65: =F49*$K$58/F$61 -> 0.75428935 | G65: =G49*$K$59/G$61 -> 0.48074193
A66: Gen Z | B66: >1,00,000 | C66: =C50*$K$55/C$61 -> 0.01377406 | D66: =D50*$K$56/D$61 -> 0.047485519 | E66: =E50*$K$57/E$61 -> 0.091944879 | F66: =F50*$K$58/F$61 -> 0.19283234 | G66: =G50*$K$59/G$61 -> 0.28137763
A67: Millenial | B67: <50,000 | C67: =C51*$K$55/C$61 -> 2.9315723 | D67: =D51*$K$56/D$61 -> 2.4316337 | E67: =E51*$K$57/E$61 -> 1.1035088 | F67: =F51*$K$58/F$61 -> 0.79202035 | G67: =G51*$K$59/G$61 -> 0.28017028
A68: Millenial | B68: 50,000-1,00,000 | C68: =C52*$K$55/C$61 -> 0.7002466 | D68: =D52*$K$56/D$61 -> 1.1725493 | E68: =E52*$K$57/E$61 -> 1.6693928 | F68: =F52*$K$58/F$61 -> 1.8952899 | G68: =G52*$K$59/G$61 -> 1.207952
A69: Millenial | B69: >1,00,000 | C69: =C53*$K$55/C$61 -> 0.10382953 | D69: =D53*$K$56/D$61 -> 0.35794815 | E69: =E53*$K$57/E$61 -> 0.69308496 | F69: =F53*$K$58/F$61 -> 1.4535796 | G69: =G53*$K$59/G$61 -> 2.1210382
A70: Gen X | B70: <50,000 | C70: =C54*$K$55/C$61 -> 1.0493692 | D70: =D54*$K$56/D$61 -> 0.87041397 | E70: =E54*$K$57/E$61 -> 0.39500582 | F70: =F54*$K$58/F$61 -> 0.28350716 | G70: =G54*$K$59/G$61 -> 0.10028818
A71: Gen X | B71: 50,000-1,00,000 | C71: =C55*$K$55/C$61 -> 0.45953663 | D71: =D55*$K$56/D$61 -> 0.76948512 | E71: =E55*$K$57/E$61 -> 1.0955386 | F71: =F55*$K$58/F$61 -> 1.2437835 | G71: =G55*$K$59/G$61 -> 0.79271816
A72: Gen X | B72: >1,00,000 | C72: =C56*$K$55/C$61 -> 0.074332475 | D72: =D56*$K$56/D$61 -> 0.25625822 | E72: =E56*$K$57/E$61 -> 0.49618561 | F72: =F56*$K$58/F$61 -> 1.0406304 | G72: =G56*$K$59/G$61 -> 1.5184699
A73: Baby Boomer | B73: <50,000 | C73: =C57*$K$55/C$61 -> 1.0705883 | D73: =D57*$K$56/D$61 -> 0.88801446 | E73: =E57*$K$57/E$61 -> 0.40299316 | F73: =F57*$K$58/F$61 -> 0.28923991 | G73: =G57*$K$59/G$61 -> 0.10231609
A74: Baby Boomer | B74: 50,000-1,00,000 | C74: =C58*$K$55/C$61 -> 0.21310402 | D74: =D58*$K$56/D$61 -> 0.35683852 | E74: =E58*$K$57/E$61 -> 0.50804149 | F74: =F58*$K$58/F$61 -> 0.57678809 | G74: =G58*$K$59/G$61 -> 0.36761254
A75: Baby Boomer | B75: >1,00,000 | C75: =C59*$K$55/C$61 -> 0.025278513 | D75: =D59*$K$56/D$61 -> 0.087146658 | E75: =E59*$K$57/E$61 -> 0.16873963 | F75: =F59*$K$58/F$61 -> 0.35389093 | G75: =G59*$K$59/G$61 -> 0.51639154
A77: % BNPL Portfolio
A78: Generation | B78: Income Bracket | C78: Deep Subprime | D78: Sub Prime | E78: Near Prime | F78: Prime | G78: Super Prime
A79: Gen Z | B79: <50,000 | C79: =C64/SUM(Portfolio_Num[[Deep Subprime]:[Super Prime]]) -> 0.098055593 | D79: =D64/SUM(Portfolio_Num[[Deep Subprime]:[Super Prime]]) -> 0.081333586 | E79: =E64/SUM(Portfolio_Num[[Deep Subprime]:[Super Prime]]) -> 0.036910299 | F79: =F64/SUM(Portfolio_Num[[Deep Subprime]:[Super Prime]]) -> 0.026491595 | G79: =G64/SUM(Portfolio_Num[[Deep Subprime]:[Super Prime]]) -> 0.0093711704
A80: Gen Z | B80: 50,000-1,00,000 | C80: =C65/SUM(Portfolio_Num[[Deep Subprime]:[Super Prime]]) -> 0.0054050619 | D80: =D65/SUM(Portfolio_Num[[Deep Subprime]:[Super Prime]]) -> 0.0090506707 | E80: =E65/SUM(Portfolio_Num[[Deep Subprime]:[Super Prime]]) -> 0.012885706 | F80: =F65/SUM(Portfolio_Num[[Deep Subprime]:[Super Prime]]) -> 0.01462936 | G80: =G65/SUM(Portfolio_Num[[Deep Subprime]:[Super Prime]]) -> 0.0093239373
A81: Gen Z | B81: >1,00,000 | C81: =C66/SUM(Portfolio_Num[[Deep Subprime]:[Super Prime]]) -> 0.00026714639 | D81: =D66/SUM(Portfolio_Num[[Deep Subprime]:[Super Prime]]) -> 0.00092097646 | E81: =E66/SUM(Portfolio_Num[[Deep Subprime]:[Super Prime]]) -> 0.0017832609 | F81: =F66/SUM(Portfolio_Num[[Deep Subprime]:[Super Prime]]) -> 0.0037399623 | G81: =G66/SUM(Portfolio_Num[[Deep Subprime]:[Super Prime]]) -> 0.0054572884
A82: Millenial | B82: <50,000 | C82: =C67/SUM(Portfolio_Num[[Deep Subprime]:[Super Prime]]) -> 0.056857524 | D82: =D67/SUM(Portfolio_Num[[Deep Subprime]:[Super Prime]]) -> 0.047161271 | E82: =E67/SUM(Portfolio_Num[[Deep Subprime]:[Super Prime]]) -> 0.021402433 | F82: =F67/SUM(Portfolio_Num[[Deep Subprime]:[Super Prime]]) -> 0.015361148 | G82: =G67/SUM(Portfolio_Num[[Deep Subprime]:[Super Prime]]) -> 0.0054338721
A83: Millenial | B83: 50,000-1,00,000 | C83: =C68/SUM(Portfolio_Num[[Deep Subprime]:[Super Prime]]) -> 0.013581206 | D83: =D68/SUM(Portfolio_Num[[Deep Subprime]:[Super Prime]]) -> 0.022741465 | E83: =E68/SUM(Portfolio_Num[[Deep Subprime]:[Super Prime]]) -> 0.032377692 | F83: =F68/SUM(Portfolio_Num[[Deep Subprime]:[Super Prime]]) -> 0.036758941 | G83: =G68/SUM(Portfolio_Num[[Deep Subprime]:[Super Prime]]) -> 0.023428097
A84: Millenial | B84: >1,00,000 | C84: =C69/SUM(Portfolio_Num[[Deep Subprime]:[Super Prime]]) -> 0.0020137625 | D84: =D69/SUM(Portfolio_Num[[Deep Subprime]:[Super Prime]]) -> 0.0069423652 | E84: =E69/SUM(Portfolio_Num[[Deep Subprime]:[Super Prime]]) -> 0.013442307 | F84: =F69/SUM(Portfolio_Num[[Deep Subprime]:[Super Prime]]) -> 0.028192017 | G84: =G69/SUM(Portfolio_Num[[Deep Subprime]:[Super Prime]]) -> 0.041137305
A85: Gen X | B85: <50,000 | C85: =C70/SUM(Portfolio_Num[[Deep Subprime]:[Super Prime]]) -> 0.020352401 | D85: =D70/SUM(Portfolio_Num[[Deep Subprime]:[Super Prime]]) -> 0.016881584 | E85: =E70/SUM(Portfolio_Num[[Deep Subprime]:[Super Prime]]) -> 0.0076610948 | F85: =F70/SUM(Portfolio_Num[[Deep Subprime]:[Super Prime]]) -> 0.0054985905 | G85: =G70/SUM(Portfolio_Num[[Deep Subprime]:[Super Prime]]) -> 0.0019450784
A86: Gen X | B86: 50,000-1,00,000 | C86: =C71/SUM(Portfolio_Num[[Deep Subprime]:[Super Prime]]) -> 0.0089126629 | D86: =D71/SUM(Portfolio_Num[[Deep Subprime]:[Super Prime]]) -> 0.01492408 | E86: =E71/SUM(Portfolio_Num[[Deep Subprime]:[Super Prime]]) -> 0.021247851 | F86: =F71/SUM(Portfolio_Num[[Deep Subprime]:[Super Prime]]) -> 0.024123045 | G86: =G71/SUM(Portfolio_Num[[Deep Subprime]:[Super Prime]]) -> 0.015374682
A87: Gen X | B87: >1,00,000 | C87: =C72/SUM(Portfolio_Num[[Deep Subprime]:[Super Prime]]) -> 0.0014416703 | D87: =D72/SUM(Portfolio_Num[[Deep Subprime]:[Super Prime]]) -> 0.0049701003 | E87: =E72/SUM(Portfolio_Num[[Deep Subprime]:[Super Prime]]) -> 0.0096234658 | F87: =F72/SUM(Portfolio_Num[[Deep Subprime]:[Super Prime]]) -> 0.020182913 | G87: =G72/SUM(Portfolio_Num[[Deep Subprime]:[Super Prime]]) -> 0.029450558
A88: Baby Boomer | B88: <50,000 | C88: =C73/SUM(Portfolio_Num[[Deep Subprime]:[Super Prime]]) -> 0.020763943 | D88: =D73/SUM(Portfolio_Num[[Deep Subprime]:[Super Prime]]) -> 0.017222944 | E88: =E73/SUM(Portfolio_Num[[Deep Subprime]:[Super Prime]]) -> 0.0078160084 | F88: =F73/SUM(Portfolio_Num[[Deep Subprime]:[Super Prime]]) -> 0.0056097765 | G88: =G73/SUM(Portfolio_Num[[Deep Subprime]:[Super Prime]]) -> 0.0019844095
A89: Baby Boomer | B89: 50,000-1,00,000 | C89: =C74/SUM(Portfolio_Num[[Deep Subprime]:[Super Prime]]) -> 0.0041331292 | D89: =D74/SUM(Portfolio_Num[[Deep Subprime]:[Super Prime]]) -> 0.0069208442 | E89: =E74/SUM(Portfolio_Num[[Deep Subprime]:[Super Prime]]) -> 0.0098534093 | F89: =F74/SUM(Portfolio_Num[[Deep Subprime]:[Super Prime]]) -> 0.011186742 | G89: =G74/SUM(Portfolio_Num[[Deep Subprime]:[Super Prime]]) -> 0.0071298051
A90: Baby Boomer | B90: >1,00,000 | C90: =C75/SUM(Portfolio_Num[[Deep Subprime]:[Super Prime]]) -> 0.00049027401 | D90: =D75/SUM(Portfolio_Num[[Deep Subprime]:[Super Prime]]) -> 0.0016901999 | E90: =E75/SUM(Portfolio_Num[[Deep Subprime]:[Super Prime]]) -> 0.0032726867 | F90: =F75/SUM(Portfolio_Num[[Deep Subprime]:[Super Prime]]) -> 0.006863676 | G90: =G75/SUM(Portfolio_Num[[Deep Subprime]:[Super Prime]]) -> 0.010015357
A92: Default Rate | J92: Default Behaviour Multiplier
A93: Generation | B93: Income Bracket | C93: Deep Subprime | D93: Sub Prime | E93: Near Prime | F93: Prime | G93: Super Prime | J93: Generation | K93: <50,000 | L93: 50,000-1,00,000 | M93: >1,00,000
A94: Gen Z | B94: <50,000 | C94: ='Default Rates'!$D$11 * INDEX($K$94:$M$97, MATCH($A94,$J$94:$J$97,0), MATCH($B94,$K$93:$M$93,0)) -> 0.0385 | D94: ='Default Rates'!$D$12 * INDEX($K$94:$M$97, MATCH($A94,$J$94:$J$97,0), MATCH($B94,$K$93:$M$93,0)) -> 0.0121 | E94: ='Default Rates'!$D$13 * INDEX($K$94:$M$97, MATCH($A94,$J$94:$J$97,0), MATCH($B94,$K$93:$M$93,0)) -> 0.0088 | F94: ='Default Rates'!$D$14 * INDEX($K$94:$M$97, MATCH($A94,$J$94:$J$97,0), MATCH($B94,$K$93:$M$93,0)) -> 0.0077 | G94: ='Default Rates'!$D$15 * INDEX($K$94:$M$97, MATCH($A94,$J$94:$J$97,0), MATCH($B94,$K$93:$M$93,0)) -> 0.0088 | J94: Gen Z | K94: 1.1 | L94: 1.08 | M94: 1
A95: Gen Z | B95: 50,000-1,00,000 | C95: ='Default Rates'!$D$11 * INDEX($K$94:$M$97, MATCH($A95,$J$94:$J$97,0), MATCH($B95,$K$93:$M$93,0)) -> 0.0378 | D95: ='Default Rates'!$D$12 * INDEX($K$94:$M$97, MATCH($A95,$J$94:$J$97,0), MATCH($B95,$K$93:$M$93,0)) -> 0.01188 | E95: ='Default Rates'!$D$13 * INDEX($K$94:$M$97, MATCH($A95,$J$94:$J$97,0), MATCH($B95,$K$93:$M$93,0)) -> 0.00864 | F95: ='Default Rates'!$D$14 * INDEX($K$94:$M$97, MATCH($A95,$J$94:$J$97,0), MATCH($B95,$K$93:$M$93,0)) -> 0.00756 | G95: ='Default Rates'!$D$15 * INDEX($K$94:$M$97, MATCH($A95,$J$94:$J$97,0), MATCH($B95,$K$93:$M$93,0)) -> 0.00864 | J95: Millenial | K95: 1.1 | L95: 1.04 | M95: 1
A96: Gen Z | B96: >1,00,000 | C96: ='Default Rates'!$D$11 * INDEX($K$94:$M$97, MATCH($A96,$J$94:$J$97,0), MATCH($B96,$K$93:$M$93,0)) -> 0.035 | D96: ='Default Rates'!$D$12 * INDEX($K$94:$M$97, MATCH($A96,$J$94:$J$97,0), MATCH($B96,$K$93:$M$93,0)) -> 0.011 | E96: ='Default Rates'!$D$13 * INDEX($K$94:$M$97, MATCH($A96,$J$94:$J$97,0), MATCH($B96,$K$93:$M$93,0)) -> 0.008 | F96: ='Default Rates'!$D$14 * INDEX($K$94:$M$97, MATCH($A96,$J$94:$J$97,0), MATCH($B96,$K$93:$M$93,0)) -> 0.007 | G96: ='Default Rates'!$D$15 * INDEX($K$94:$M$97, MATCH($A96,$J$94:$J$97,0), MATCH($B96,$K$93:$M$93,0)) -> 0.008 | J96: Gen X | K96: 1 | L96: 1 | M96: 1
A97: Millenial | B97: <50,000 | C97: ='Default Rates'!$D$11 * INDEX($K$94:$M$97, MATCH($A97,$J$94:$J$97,0), MATCH($B97,$K$93:$M$93,0)) -> 0.0385 | D97: ='Default Rates'!$D$12 * INDEX($K$94:$M$97, MATCH($A97,$J$94:$J$97,0), MATCH($B97,$K$93:$M$93,0)) -> 0.0121 | E97: ='Default Rates'!$D$13 * INDEX($K$94:$M$97, MATCH($A97,$J$94:$J$97,0), MATCH($B97,$K$93:$M$93,0)) -> 0.0088 | F97: ='Default Rates'!$D$14 * INDEX($K$94:$M$97, MATCH($A97,$J$94:$J$97,0), MATCH($B97,$K$93:$M$93,0)) -> 0.0077 | G97: ='Default Rates'!$D$15 * INDEX($K$94:$M$97, MATCH($A97,$J$94:$J$97,0), MATCH($B97,$K$93:$M$93,0)) -> 0.0088 | J97: Baby Boomer | K97: 1.05 | L97: 1 | M97: 1
A98: Millenial | B98: 50,000-1,00,000 | C98: ='Default Rates'!$D$11 * INDEX($K$94:$M$97, MATCH($A98,$J$94:$J$97,0), MATCH($B98,$K$93:$M$93,0)) -> 0.0364 | D98: ='Default Rates'!$D$12 * INDEX($K$94:$M$97, MATCH($A98,$J$94:$J$97,0), MATCH($B98,$K$93:$M$93,0)) -> 0.01144 | E98: ='Default Rates'!$D$13 * INDEX($K$94:$M$97, MATCH($A98,$J$94:$J$97,0), MATCH($B98,$K$93:$M$93,0)) -> 0.00832 | F98: ='Default Rates'!$D$14 * INDEX($K$94:$M$97, MATCH($A98,$J$94:$J$97,0), MATCH($B98,$K$93:$M$93,0)) -> 0.00728 | G98: ='Default Rates'!$D$15 * INDEX($K$94:$M$97, MATCH($A98,$J$94:$J$97,0), MATCH($B98,$K$93:$M$93,0)) -> 0.00832
A99: Millenial | B99: >1,00,000 | C99: ='Default Rates'!$D$11 * INDEX($K$94:$M$97, MATCH($A99,$J$94:$J$97,0), MATCH($B99,$K$93:$M$93,0)) -> 0.035 | D99: ='Default Rates'!$D$12 * INDEX($K$94:$M$97, MATCH($A99,$J$94:$J$97,0), MATCH($B99,$K$93:$M$93,0)) -> 0.011 | E99: ='Default Rates'!$D$13 * INDEX($K$94:$M$97, MATCH($A99,$J$94:$J$97,0), MATCH($B99,$K$93:$M$93,0)) -> 0.008 | F99: ='Default Rates'!$D$14 * INDEX($K$94:$M$97, MATCH($A99,$J$94:$J$97,0), MATCH($B99,$K$93:$M$93,0)) -> 0.007 | G99: ='Default Rates'!$D$15 * INDEX($K$94:$M$97, MATCH($A99,$J$94:$J$97,0), MATCH($B99,$K$93:$M$93,0)) -> 0.008
A100: Gen X | B100: <50,000 | C100: ='Default Rates'!$D$11 * INDEX($K$94:$M$97, MATCH($A100,$J$94:$J$97,0), MATCH($B100,$K$93:$M$93,0)) -> 0.035 | D100: ='Default Rates'!$D$12 * INDEX($K$94:$M$97, MATCH($A100,$J$94:$J$97,0), MATCH($B100,$K$93:$M$93,0)) -> 0.011 | E100: ='Default Rates'!$D$13 * INDEX($K$94:$M$97, MATCH($A100,$J$94:$J$97,0), MATCH($B100,$K$93:$M$93,0)) -> 0.008 | F100: ='Default Rates'!$D$14 * INDEX($K$94:$M$97, MATCH($A100,$J$94:$J$97,0), MATCH($B100,$K$93:$M$93,0)) -> 0.007 | G100: ='Default Rates'!$D$15 * INDEX($K$94:$M$97, MATCH($A100,$J$94:$J$97,0), MATCH($B100,$K$93:$M$93,0)) -> 0.008
A101: Gen X | B101: 50,000-1,00,000 | C101: ='Default Rates'!$D$11 * INDEX($K$94:$M$97, MATCH($A101,$J$94:$J$97,0), MATCH($B101,$K$93:$M$93,0)) -> 0.035 | D101: ='Default Rates'!$D$12 * INDEX($K$94:$M$97, MATCH($A101,$J$94:$J$97,0), MATCH($B101,$K$93:$M$93,0)) -> 0.011 | E101: ='Default Rates'!$D$13 * INDEX($K$94:$M$97, MATCH($A101,$J$94:$J$97,0), MATCH($B101,$K$93:$M$93,0)) -> 0.008 | F101: ='Default Rates'!$D$14 * INDEX($K$94:$M$97, MATCH($A101,$J$94:$J$97,0), MATCH($B101,$K$93:$M$93,0)) -> 0.007 | G101: ='Default Rates'!$D$15 * INDEX($K$94:$M$97, MATCH($A101,$J$94:$J$97,0), MATCH($B101,$K$93:$M$93,0)) -> 0.008
A102: Gen X | B102: >1,00,000 | C102: ='Default Rates'!$D$11 * INDEX($K$94:$M$97, MATCH($A102,$J$94:$J$97,0), MATCH($B102,$K$93:$M$93,0)) -> 0.035 | D102: ='Default Rates'!$D$12 * INDEX($K$94:$M$97, MATCH($A102,$J$94:$J$97,0), MATCH($B102,$K$93:$M$93,0)) -> 0.011 | E102: ='Default Rates'!$D$13 * INDEX($K$94:$M$97, MATCH($A102,$J$94:$J$97,0), MATCH($B102,$K$93:$M$93,0)) -> 0.008 | F102: ='Default Rates'!$D$14 * INDEX($K$94:$M$97, MATCH($A102,$J$94:$J$97,0), MATCH($B102,$K$93:$M$93,0)) -> 0.007 | G102: ='Default Rates'!$D$15 * INDEX($K$94:$M$97, MATCH($A102,$J$94:$J$97,0), MATCH($B102,$K$93:$M$93,0)) -> 0.008
A103: Baby Boomer | B103: <50,000 | C103: ='Default Rates'!$D$11 * INDEX($K$94:$M$97, MATCH($A103,$J$94:$J$97,0), MATCH($B103,$K$93:$M$93,0)) -> 0.03675 | D103: ='Default Rates'!$D$12 * INDEX($K$94:$M$97, MATCH($A103,$J$94:$J$97,0), MATCH($B103,$K$93:$M$93,0)) -> 0.01155 | E103: ='Default Rates'!$D$13 * INDEX($K$94:$M$97, MATCH($A103,$J$94:$J$97,0), MATCH($B103,$K$93:$M$93,0)) -> 0.0084 | F103: ='Default Rates'!$D$14 * INDEX($K$94:$M$97, MATCH($A103,$J$94:$J$97,0), MATCH($B103,$K$93:$M$93,0)) -> 0.00735 | G103: ='Default Rates'!$D$15 * INDEX($K$94:$M$97, MATCH($A103,$J$94:$J$97,0), MATCH($B103,$K$93:$M$93,0)) -> 0.0084
A104: Baby Boomer | B104: 50,000-1,00,000 | C104: ='Default Rates'!$D$11 * INDEX($K$94:$M$97, MATCH($A104,$J$94:$J$97,0), MATCH($B104,$K$93:$M$93,0)) -> 0.035 | D104: ='Default Rates'!$D$12 * INDEX($K$94:$M$97, MATCH($A104,$J$94:$J$97,0), MATCH($B104,$K$93:$M$93,0)) -> 0.011 | E104: ='Default Rates'!$D$13 * INDEX($K$94:$M$97, MATCH($A104,$J$94:$J$97,0), MATCH($B104,$K$93:$M$93,0)) -> 0.008 | F104: ='Default Rates'!$D$14 * INDEX($K$94:$M$97, MATCH($A104,$J$94:$J$97,0), MATCH($B104,$K$93:$M$93,0)) -> 0.007 | G104: ='Default Rates'!$D$15 * INDEX($K$94:$M$97, MATCH($A104,$J$94:$J$97,0), MATCH($B104,$K$93:$M$93,0)) -> 0.008
A105: Baby Boomer | B105: >1,00,000 | C105: ='Default Rates'!$D$11 * INDEX($K$94:$M$97, MATCH($A105,$J$94:$J$97,0), MATCH($B105,$K$93:$M$93,0)) -> 0.035 | D105: ='Default Rates'!$D$12 * INDEX($K$94:$M$97, MATCH($A105,$J$94:$J$97,0), MATCH($B105,$K$93:$M$93,0)) -> 0.011 | E105: ='Default Rates'!$D$13 * INDEX($K$94:$M$97, MATCH($A105,$J$94:$J$97,0), MATCH($B105,$K$93:$M$93,0)) -> 0.008 | F105: ='Default Rates'!$D$14 * INDEX($K$94:$M$97, MATCH($A105,$J$94:$J$97,0), MATCH($B105,$K$93:$M$93,0)) -> 0.007 | G105: ='Default Rates'!$D$15 * INDEX($K$94:$M$97, MATCH($A105,$J$94:$J$97,0), MATCH($B105,$K$93:$M$93,0)) -> 0.008
J106: Credit Category | K106: Loan Originations | L106: Loan Count (in M) | M106: Average Loans
L107: =Table54[[#This Row],[Loan Originations]]*'User Segmentation'!$I$47 -> 0
A108: Portfolio Default Rate | C108: {=TRANSPOSE(Table54[])} -> 0 | D108: Deep Subprime | E108: Subprime | F108: Near Prime | G108: Prime | H108: Super Prime | J108: Deep Subprime | K108: 0.4688 | L108: =Table54[[#This Row],[Loan Originations]]*'User Segmentation'!$I$47 -> 157.42304 | M108: =Table54[[#This Row],[Loan Count (in M)]]/SUM(Portfolio_Num[Deep Subprime]) -> 13.144811
A109: =SUMPRODUCT(C94:G105,Portfolio_Perc[[Deep Subprime]:[Super Prime]]) -> 0.015690751 | C109: 0 | D109: 0.4688 | E109: 0.1667 | F109: 0.1323 | G109: 0.1375 | H109: 0.0948 | J109: Subprime | K109: 0.1667 | L109: =Table54[[#This Row],[Loan Originations]]*'User Segmentation'!$I$47 -> 55.97786 | M109: =Table54[[#This Row],[Loan Count (in M)]]/SUM(Portfolio_Num[Sub Prime]) -> 4.7048192
...

Sheet Support Tables
A1: Base ATS Values | I1: ATS Scale
A2: Generation | B2: Income Bracket | C2: Deep Subprime | D2: Sub Prime | E2: Near Prime | F2: Prime | G2: Super Prime | I2: =145/126 -> 1.1507937
A3: Gen Z | B3: <50000 | C3: 49.84 | D3: 58.91 | E3: 77.03 | F3: 99.69 | G3: 131.41
A4: Gen Z | B4: 50000-100000 | C4: 72.5 | D4: 86.09 | E4: 108.75 | F4: 145 | G4: 185
A5: Gen Z | B5: >100000 | C5: 95 | D5: 118 | E5: 158 | F5: 220 | G5: 290
A6: Millenial | B6: <50000 | C6: 63.44 | D6: 77.03 | E6: 104.22 | F6: 135.94 | G6: 168
A7: Millenial | B7: 50000-100000 | C7: 86.09 | D7: 113.28 | E7: 163.13 | F7: 218 | G7: 292
A8: Millenial | B8: >100000 | C8: 132 | D8: 182 | E8: 265 | F8: 338 | G8: 395
A9: Gen X | B9: <50000 | C9: 67.97 | D9: 81.56 | E9: 108.75 | F9: 140.47 | G9: 167.66
A10: Gen X | B10: 50000-100000 | C10: 99.69 | D10: 135.94 | E10: 199.38 | F10: 275 | G10: 360
A11: Gen X | B11: >100000 | C11: 158 | D11: 224 | E11: 328 | F11: 368 | G11: 395
A12: Baby Boomer | B12: <50000 | C12: 54.38 | D12: 67.97 | E12: 86.09 | F12: 108.75 | G12: 135.94
A13: Baby Boomer | B13: 50000-100000 | C13: 81.56 | D13: 104.22 | E13: 145 | F13: 192 | G13: 255
A14: Baby Boomer | B14: >100000 | C14: 124 | D14: 168 | E14: 245 | F14: 318 | G14: 375
A16: Average Ticket Size | I16: Expected Credit Loss (ECL)
A17: Generation | B17: Income Bracket | C17: Deep Subprime | D17: Sub Prime | E17: Near Prime | F17: Prime | G17: Super Prime | I17: Generation | J17: Income Bracket | K17: Deep Subprime | L17: Sub Prime | M17: Near Prime | N17: Prime | O17: Super Prime
A18: Gen Z | B18: <50,000 | C18: =C3*$I$2 -> 57.355556 | D18: =D3*$I$2 -> 67.793254 | E18: =E3*$I$2 -> 88.645635 | F18: =F3*$I$2 -> 114.72262 | G18: =G3*$I$2 -> 151.22579 | I18: Gen Z | J18: <50,000 | K18: =ATS_Table[[#This Row],[Deep Subprime]]*'Dynamic PD'!N3*'EAD Estimate'!$E$2*'EAD Estimate'!$F$2 -> 1.4077204 | L18: =ATS_Table[[#This Row],[Sub Prime]]*'Dynamic PD'!O3*'EAD Estimate'!$E$3*'EAD Estimate'!$F$3 -> 0.46141783 | M18: =ATS_Table[[#This Row],[Near Prime]]*'Dynamic PD'!P3*'EAD Estimate'!$E$4*'EAD Estimate'!$F$4 -> 0.40369222 | N18: =ATS_Table[[#This Row],[Prime]]*'Dynamic PD'!Q3*'EAD Estimate'!$E$5*'EAD Estimate'!$F$5 -> 0.43064003 | O18: =ATS_Table[[#This Row],[Super Prime]]*'Dynamic PD'!R3*'EAD Estimate'!$E$6*'EAD Estimate'!$F$6 -> 0.58887324
A19: Gen Z | B19: 50,000-1,00,000 | C19: =C4*$I$2 -> 83.43254 | D19: =D4*$I$2 -> 99.071825 | E19: =E4*$I$2 -> 125.14881 | F19: =F4*$I$2 -> 166.86508 | G19: =G4*$I$2 -> 212.89683 | I19: Gen Z | J19: 50,000-1,00,000 | K19: =ATS_Table[[#This Row],[Deep Subprime]]*'Dynamic PD'!N4*'EAD Estimate'!$E$2*'EAD Estimate'!$F$2 -> 2.0105156 | L19: =ATS_Table[[#This Row],[Sub Prime]]*'Dynamic PD'!O4*'EAD Estimate'!$E$3*'EAD Estimate'!$F$3 -> 0.66204747 | M19: =ATS_Table[[#This Row],[Near Prime]]*'Dynamic PD'!P4*'EAD Estimate'!$E$4*'EAD Estimate'!$F$4 -> 0.55956536 | N19: =ATS_Table[[#This Row],[Prime]]*'Dynamic PD'!Q4*'EAD Estimate'!$E$5*'EAD Estimate'!$F$5 -> 0.61498125 | O19: =ATS_Table[[#This Row],[Super Prime]]*'Dynamic PD'!R4*'EAD Estimate'!$E$6*'EAD Estimate'!$F$6 -> 0.81394714
A20: Gen Z | B20: >1,00,000 | C20: =C5*$I$2 -> 109.3254 | D20: =D5*$I$2 -> 135.79365 | E20: =E5*$I$2 -> 181.8254 | F20: =F5*$I$2 -> 253.1746 | G20: =G5*$I$2 -> 333.73016 | I20: Gen Z | J20: >1,00,000 | K20: =ATS_Table[[#This Row],[Deep Subprime]]*'Dynamic PD'!N5*'EAD Estimate'!$E$2*'EAD Estimate'!$F$2 -> 2.4393229 | L20: =ATS_Table[[#This Row],[Sub Prime]]*'Dynamic PD'!O5*'EAD Estimate'!$E$3*'EAD Estimate'!$F$3 -> 0.84022321 | M20: =ATS_Table[[#This Row],[Near Prime]]*'Dynamic PD'!P5*'EAD Estimate'!$E$4*'EAD Estimate'!$F$4 -> 0.75275714 | N20: =ATS_Table[[#This Row],[Prime]]*'Dynamic PD'!Q5*'EAD Estimate'!$E$5*'EAD Estimate'!$F$5 -> 0.86395833 | O20: =ATS_Table[[#This Row],[Super Prime]]*'Dynamic PD'!R5*'EAD Estimate'!$E$6*'EAD Estimate'!$F$6 -> 1.1814048
A21: Millenial | B21: <50,000 | C21: =C6*$I$2 -> 73.006349 | D21: =D6*$I$2 -> 88.645635 | E21: =E6*$I$2 -> 119.93571 | F21: =F6*$I$2 -> 156.43889 | G21: =G6*$I$2 -> 193.33333 | I21: Millenial | J21: <50,000 | K21: =ATS_Table[[#This Row],[Deep Subprime]]*'Dynamic PD'!N6*'EAD Estimate'!$E$2*'EAD Estimate'!$F$2 -> 1.7918496 | L21: =ATS_Table[[#This Row],[Sub Prime]]*'Dynamic PD'!O6*'EAD Estimate'!$E$3*'EAD Estimate'!$F$3 -> 0.60334435 | M21: =ATS_Table[[#This Row],[Near Prime]]*'Dynamic PD'!P6*'EAD Estimate'!$E$4*'EAD Estimate'!$F$4 -> 0.54618724 | N21: =ATS_Table[[#This Row],[Prime]]*'Dynamic PD'!Q6*'EAD Estimate'!$E$5*'EAD Estimate'!$F$5 -> 0.58723248 | O21: =ATS_Table[[#This Row],[Super Prime]]*'Dynamic PD'!R6*'EAD Estimate'!$E$6*'EAD Estimate'!$F$6 -> 0.75284
A22: Millenial | B22: 50,000-1,00,000 | C22: =C7*$I$2 -> 99.071825 | D22: =D7*$I$2 -> 130.3619 | E22: =E7*$I$2 -> 187.72897 | F22: =F7*$I$2 -> 250.87302 | G22: =G7*$I$2 -> 336.03175 | I22: Millenial | J22: 50,000-1,00,000 | K22: =ATS_Table[[#This Row],[Deep Subprime]]*'Dynamic PD'!N7*'EAD Estimate'!$E$2*'EAD Estimate'!$F$2 -> 2.2989617 | L22: =ATS_Table[[#This Row],[Sub Prime]]*'Dynamic PD'!O7*'EAD Estimate'!$E$3*'EAD Estimate'!$F$3 -> 0.83887886 | M22: =ATS_Table[[#This Row],[Near Prime]]*'Dynamic PD'!P7*'EAD Estimate'!$E$4*'EAD Estimate'!$F$4 -> 0.80828585 | N22: =ATS_Table[[#This Row],[Prime]]*'Dynamic PD'!Q7*'EAD Estimate'!$E$5*'EAD Estimate'!$F$5 -> 0.89034833 | O22: =ATS_Table[[#This Row],[Super Prime]]*'Dynamic PD'!R7*'EAD Estimate'!$E$6*'EAD Estimate'!$F$6 -> 1.2371345
A23: Millenial | B23: >1,00,000 | C23: =C8*$I$2 -> 151.90476 | D23: =D8*$I$2 -> 209.44444 | E23: =E8*$I$2 -> 304.96032 | F23: =F8*$I$2 -> 388.96825 | G23: =G8*$I$2 -> 454.56349 | I23: Millenial | J23: >1,00,000 | K23: =ATS_Table[[#This Row],[Deep Subprime]]*'Dynamic PD'!N8*'EAD Estimate'!$E$2*'EAD Estimate'!$F$2 -> 3.389375 | L23: =ATS_Table[[#This Row],[Sub Prime]]*'Dynamic PD'!O8*'EAD Estimate'!$E$3*'EAD Estimate'!$F$3 -> 1.2959375 | M23: =ATS_Table[[#This Row],[Near Prime]]*'Dynamic PD'!P8*'EAD Estimate'!$E$4*'EAD Estimate'!$F$4 -> 1.2625357 | N23: =ATS_Table[[#This Row],[Prime]]*'Dynamic PD'!Q8*'EAD Estimate'!$E$5*'EAD Estimate'!$F$5 -> 1.3273542 | O23: =ATS_Table[[#This Row],[Super Prime]]*'Dynamic PD'!R8*'EAD Estimate'!$E$6*'EAD Estimate'!$F$6 -> 1.6091548
A24: Gen X | B24: <50,000 | C24: =C9*$I$2 -> 78.219444 | D24: =D9*$I$2 -> 93.85873 | E24: =E9*$I$2 -> 125.14881 | F24: =F9*$I$2 -> 161.65198 | G24: =G9*$I$2 -> 192.94206 | I24: Gen X | J24: <50,000 | K24: =ATS_Table[[#This Row],[Deep Subprime]]*'Dynamic PD'!N9*'EAD Estimate'!$E$2*'EAD Estimate'!$F$2 -> 1.7452714 | L24: =ATS_Table[[#This Row],[Sub Prime]]*'Dynamic PD'!O9*'EAD Estimate'!$E$3*'EAD Estimate'!$F$3 -> 0.58075089 | M24: =ATS_Table[[#This Row],[Near Prime]]*'Dynamic PD'!P9*'EAD Estimate'!$E$4*'EAD Estimate'!$F$4 -> 0.51811607 | N24: =ATS_Table[[#This Row],[Prime]]*'Dynamic PD'!Q9*'EAD Estimate'!$E$5*'EAD Estimate'!$F$5 -> 0.5516374 | O24: =ATS_Table[[#This Row],[Super Prime]]*'Dynamic PD'!R9*'EAD Estimate'!$E$6*'EAD Estimate'!$F$6 -> 0.6830149
A25: Gen X | B25: 50,000-1,00,000 | C25: =C10*$I$2 -> 114.72262 | D25: =D10*$I$2 -> 156.43889 | E25: =E10*$I$2 -> 229.44524 | F25: =F10*$I$2 -> 316.46825 | G25: =G10*$I$2 -> 414.28571 | I25: Gen X | J25: 50,000-1,00,000 | K25: =ATS_Table[[#This Row],[Deep Subprime]]*'Dynamic PD'!N10*'EAD Estimate'!$E$2*'EAD Estimate'!$F$2 -> 2.5597484 | L25: =ATS_Table[[#This Row],[Sub Prime]]*'Dynamic PD'!O10*'EAD Estimate'!$E$3*'EAD Estimate'!$F$3 -> 0.96796562 | M25: =ATS_Table[[#This Row],[Near Prime]]*'Dynamic PD'!P10*'EAD Estimate'!$E$4*'EAD Estimate'!$F$4 -> 0.94990329 | N25: =ATS_Table[[#This Row],[Prime]]*'Dynamic PD'!Q10*'EAD Estimate'!$E$5*'EAD Estimate'!$F$5 -> 1.0799479 | O25: =ATS_Table[[#This Row],[Super Prime]]*'Dynamic PD'!R10*'EAD Estimate'!$E$6*'EAD Estimate'!$F$6 -> 1.4665714
A26: Gen X | B26: >1,00,000 | C26: =C11*$I$2 -> 181.8254 | D26: =D11*$I$2 -> 257.77778 | E26: =E11*$I$2 -> 377.46032 | F26: =F11*$I$2 -> 423.49206 | G26: =G11*$I$2 -> 454.56349 | I26: Gen X | J26: >1,00,000 | K26: =ATS_Table[[#This Row],[Deep Subprime]]*'Dynamic PD'!N11*'EAD Estimate'!$E$2*'EAD Estimate'!$F$2 -> 4.0569792 | L26: =ATS_Table[[#This Row],[Sub Prime]]*'Dynamic PD'!O11*'EAD Estimate'!$E$3*'EAD Estimate'!$F$3 -> 1.595 | M26: =ATS_Table[[#This Row],[Near Prime]]*'Dynamic PD'!P11*'EAD Estimate'!$E$4*'EAD Estimate'!$F$4 -> 1.5626857 | N26: =ATS_Table[[#This Row],[Prime]]*'Dynamic PD'!Q11*'EAD Estimate'!$E$5*'EAD Estimate'!$F$5 -> 1.4451667 | O26: =ATS_Table[[#This Row],[Super Prime]]*'Dynamic PD'!R11*'EAD Estimate'!$E$6*'EAD Estimate'!$F$6 -> 1.6091548
A27: Baby Boomer | B27: <50,000 | C27: =C12*$I$2 -> 62.580159 | D27: =D12*$I$2 -> 78.219444 | E27: =E12*$I$2 -> 99.071825 | F27: =F12*$I$2 -> 125.14881 | G27: =G12*$I$2 -> 156.43889 | I27: Baby Boomer | J27: <50,000 | K27: =ATS_Table[[#This Row],[Deep Subprime]]*'Dynamic PD'!N12*'EAD Estimate'!$E$2*'EAD Estimate'!$F$2 -> 1.4661358 | L27: =ATS_Table[[#This Row],[Sub Prime]]*'Dynamic PD'!O12*'EAD Estimate'!$E$3*'EAD Estimate'!$F$3 -> 0.50818195 | M27: =ATS_Table[[#This Row],[Near Prime]]*'Dynamic PD'!P12*'EAD Estimate'!$E$4*'EAD Estimate'!$F$4 -> 0.43066522 | N27: =ATS_Table[[#This Row],[Prime]]*'Dynamic PD'!Q12*'EAD Estimate'!$E$5*'EAD Estimate'!$F$5 -> 0.44842383 | O27: =ATS_Table[[#This Row],[Super Prime]]*'Dynamic PD'!R12*'EAD Estimate'!$E$6*'EAD Estimate'!$F$6 -> 0.58148335
A28: Baby Boomer | B28: 50,000-1,00,000 | C28: =C13*$I$2 -> 93.85873 | D28: =D13*$I$2 -> 119.93571 | E28: =E13*$I$2 -> 166.86508 | F28: =F13*$I$2 -> 220.95238 | G28: =G13*$I$2 -> 293.45238 | I28: Baby Boomer | J28: 50,000-1,00,000 | K28: =ATS_Table[[#This Row],[Deep Subprime]]*'Dynamic PD'!N13*'EAD Estimate'!$E$2*'EAD Estimate'!$F$2 -> 2.0942229 | L28: =ATS_Table[[#This Row],[Sub Prime]]*'Dynamic PD'!O13*'EAD Estimate'!$E$3*'EAD Estimate'!$F$3 -> 0.74210223 | M28: =ATS_Table[[#This Row],[Near Prime]]*'Dynamic PD'!P13*'EAD Estimate'!$E$4*'EAD Estimate'!$F$4 -> 0.69082143 | N28: =ATS_Table[[#This Row],[Prime]]*'Dynamic PD'!Q13*'EAD Estimate'!$E$5*'EAD Estimate'!$F$5 -> 0.754 | O28: =ATS_Table[[#This Row],[Super Prime]]*'Dynamic PD'!R13*'EAD Estimate'!$E$6*'EAD Estimate'!$F$6 -> 1.0388214
A29: Baby Boomer | B29: >1,00,000 | C29: =C14*$I$2 -> 142.69841 | D29: =D14*$I$2 -> 193.33333 | E29: =E14*$I$2 -> 281.94444 | F29: =F14*$I$2 -> 365.95238 | G29: =G14*$I$2 -> 431.54762 | I29: Baby Boomer | J29: >1,00,000 | K29: =ATS_Table[[#This Row],[Deep Subprime]]*'Dynamic PD'!N14*'EAD Estimate'!$E$2*'EAD Estimate'!$F$2 -> 3.1839583 | L29: =ATS_Table[[#This Row],[Sub Prime]]*'Dynamic PD'!O14*'EAD Estimate'!$E$3*'EAD Estimate'!$F$3 -> 1.19625 | M29: =ATS_Table[[#This Row],[Near Prime]]*'Dynamic PD'!P14*'EAD Estimate'!$E$4*'EAD Estimate'!$F$4 -> 1.16725 | N29: =ATS_Table[[#This Row],[Prime]]*'Dynamic PD'!Q14*'EAD Estimate'!$E$5*'EAD Estimate'!$F$5 -> 1.2488125 | O29: =ATS_Table[[#This Row],[Super Prime]]*'Dynamic PD'!R14*'EAD Estimate'!$E$6*'EAD Estimate'!$F$6 -> 1.5276786
A31: Average Revenue Per User | I31: Funding Cost (FC)
A32: Generation | B32: Column1 | C32: Deep Subprime | D32: Sub Prime | E32: Near Prime | F32: Prime | G32: Super Prime | I32: Generation | J32: Income Bracket | K32: Deep Subprime | L32: Sub Prime | M32: Near Prime | N32: Prime | O32: Super Prime
A33: Gen Z | B33: <50,000 | C33: =C18*'Portfolio x PD x Loan Count'!C132*'User Segmentation'!$I$49/'Portfolio x PD x Loan Count'!C64 -> 37.71548 | D33: =D18*'Portfolio x PD x Loan Count'!D132*'User Segmentation'!$I$49/'Portfolio x PD x Loan Count'!D64 -> 15.945047 | E33: =E18*'Portfolio x PD x Loan Count'!E132*'User Segmentation'!$I$49/'Portfolio x PD x Loan Count'!E64 -> 21.426557 | F33: =F18*'Portfolio x PD x Loan Count'!F132*'User Segmentation'!$I$49/'Portfolio x PD x Loan Count'!F64 -> 25.864405 | G33: =G18*'Portfolio x PD x Loan Count'!G132*'User Segmentation'!$I$49/'Portfolio x PD x Loan Count'!G64 -> 29.17635 | I33: Gen Z | J33: <50,000 | K33: {=C18*Dynamic_Row_Table[[Funding Rate]:[Funding Rate]]*Dynamic_Row_Table[[Tenure (in months)]:[Tenure (in months)]]/12} -> 0.68109722 | L33: {=D18*Dynamic_Row_Table[[Funding Rate]:[Funding Rate]]*Dynamic_Row_Table[[Tenure (in months)]:[Tenure (in months)]]/12} -> 0.80504489 | M33: {=E18*Dynamic_Row_Table[[Funding Rate]:[Funding Rate]]*Dynamic_Row_Table[[Tenure (in months)]:[Tenure (in months)]]/12} -> 1.0526669 | N33: {=F18*Dynamic_Row_Table[[Funding Rate]:[Funding Rate]]*Dynamic_Row_Table[[Tenure (in months)]:[Tenure (in months)]]/12} -> 1.3623311 | O33: {=G18*Dynamic_Row_Table[[Funding Rate]:[Funding Rate]]*Dynamic_Row_Table[[Tenure (in months)]:[Tenure (in months)]]/12} -> 1.7958063
A34: Gen Z | B34: 50,000-1,00,000 | C34: =C19*'Portfolio x PD x Loan Count'!C133*'User Segmentation'!$I$49/'Portfolio x PD x Loan Count'!C65 -> 54.863008 | D34: =D19*'Portfolio x PD x Loan Count'!D133*'User Segmentation'!$I$49/'Portfolio x PD x Loan Count'!D65 -> 23.301802 | E34: =E19*'Portfolio x PD x Loan Count'!E133*'User Segmentation'!$I$49/'Portfolio x PD x Loan Count'!E65 -> 30.249747 | F34: =F19*'Portfolio x PD x Loan Count'!F133*'User Segmentation'!$I$49/'Portfolio x PD x Loan Count'!F65 -> 37.620009 | G34: =G19*'Portfolio x PD x Loan Count'!G133*'User Segmentation'!$I$49/'Portfolio x PD x Loan Count'!G65 -> 41.074688 | I34: Gen Z | J34: 50,000-1,00,000 | K34: {=C19*Dynamic_Row_Table[[Funding Rate]:[Funding Rate]]*Dynamic_Row_Table[[Tenure (in months)]:[Tenure (in months)]]/12} -> 0.99076141 | L34: {=D19*Dynamic_Row_Table[[Funding Rate]:[Funding Rate]]*Dynamic_Row_Table[[Tenure (in months)]:[Tenure (in months)]]/12} -> 1.1764779 | M34: {=E19*Dynamic_Row_Table[[Funding Rate]:[Funding Rate]]*Dynamic_Row_Table[[Tenure (in months)]:[Tenure (in months)]]/12} -> 1.4861421 | N34: {=F19*Dynamic_Row_Table[[Funding Rate]:[Funding Rate]]*Dynamic_Row_Table[[Tenure (in months)]:[Tenure (in months)]]/12} -> 1.9815228 | O34: {=G19*Dynamic_Row_Table[[Funding Rate]:[Funding Rate]]*Dynamic_Row_Table[[Tenure (in months)]:[Tenure (in months)]]/12} -> 2.5281498
A35: Gen Z | B35: >1,00,000 | C35: =C20*'Portfolio x PD x Loan Count'!C134*'User Segmentation'!$I$49/'Portfolio x PD x Loan Count'!C66 -> 71.889458 | D35: =D20*'Portfolio x PD x Loan Count'!D134*'User Segmentation'!$I$49/'Portfolio x PD x Loan Count'!D66 -> 31.938815 | E35: =E20*'Portfolio x PD x Loan Count'!E134*'User Segmentation'!$I$49/'Portfolio x PD x Loan Count'!E66 -> 43.949058 | F35: =F20*'Portfolio x PD x Loan Count'!F134*'User Segmentation'!$I$49/'Portfolio x PD x Loan Count'!F66 -> 57.078635 | G35: =G20*'Portfolio x PD x Loan Count'!G134*'User Segmentation'!$I$49/'Portfolio x PD x Loan Count'!G66 -> 64.387348 | I35: Gen Z | J35: >1,00,000 | K35: {=C20*Dynamic_Row_Table[[Funding Rate]:[Funding Rate]]*Dynamic_Row_Table[[Tenure (in months)]:[Tenure (in months)]]/12} -> 1.2982391 | L35: {=D20*Dynamic_Row_Table[[Funding Rate]:[Funding Rate]]*Dynamic_Row_Table[[Tenure (in months)]:[Tenure (in months)]]/12} -> 1.6125496 | M35: {=E20*Dynamic_Row_Table[[Funding Rate]:[Funding Rate]]*Dynamic_Row_Table[[Tenure (in months)]:[Tenure (in months)]]/12} -> 2.1591766 | N35: {=F20*Dynamic_Row_Table[[Funding Rate]:[Funding Rate]]*Dynamic_Row_Table[[Tenure (in months)]:[Tenure (in months)]]/12} -> 3.0064484 | O35: {=G20*Dynamic_Row_Table[[Funding Rate]:[Funding Rate]]*Dynamic_Row_Table[[Tenure (in months)]:[Tenure (in months)]]/12} -> 3.9630456
A36: Millenial | B36: <50,000 | C36: =C21*'Portfolio x PD x Loan Count'!C135*'User Segmentation'!$I$49/'Portfolio x PD x Loan Count'!C67 -> 48.007024 | D36: =D21*'Portfolio x PD x Loan Count'!D135*'User Segmentation'!$I$49/'Portfolio x PD x Loan Count'!D67 -> 20.84955 | E36: =E21*'Portfolio x PD x Loan Count'!E135*'User Segmentation'!$I$49/'Portfolio x PD x Loan Count'!E67 -> 28.989689 | F36: =F21*'Portfolio x PD x Loan Count'!F135*'User Segmentation'!$I$49/'Portfolio x PD x Loan Count'!F67 -> 35.269407 | G36: =G21*'Portfolio x PD x Loan Count'!G135*'User Segmentation'!$I$49/'Portfolio x PD x Loan Count'!G67 -> 37.300257 | I36: Millenial | J36: <50,000 | K36: {=C21*Dynamic_Row_Table[[Funding Rate]:[Funding Rate]]*Dynamic_Row_Table[[Tenure (in months)]:[Tenure (in months)]]/12} -> 0.8669504 | L36: {=D21*Dynamic_Row_Table[[Funding Rate]:[Funding Rate]]*Dynamic_Row_Table[[Tenure (in months)]:[Tenure (in months)]]/12} -> 1.0526669 | M36: {=E21*Dynamic_Row_Table[[Funding Rate]:[Funding Rate]]*Dynamic_Row_Table[[Tenure (in months)]:[Tenure (in months)]]/12} -> 1.4242366 | N36: {=F21*Dynamic_Row_Table[[Funding Rate]:[Funding Rate]]*Dynamic_Row_Table[[Tenure (in months)]:[Tenure (in months)]]/12} -> 1.8577118 | O36: {=G21*Dynamic_Row_Table[[Funding Rate]:[Funding Rate]]*Dynamic_Row_Table[[Tenure (in months)]:[Tenure (in months)]]/12} -> 2.2958333
A37: Millenial | B37: 50,000-1,00,000 | C37: =C22*'Portfolio x PD x Loan Count'!C136*'User Segmentation'!$I$49/'Portfolio x PD x Loan Count'!C68 -> 65.146984 | D37: =D22*'Portfolio x PD x Loan Count'!D136*'User Segmentation'!$I$49/'Portfolio x PD x Loan Count'!D68 -> 30.661262 | E37: =E22*'Portfolio x PD x Loan Count'!E136*'User Segmentation'!$I$49/'Portfolio x PD x Loan Count'!E68 -> 45.376012 | F37: =F22*'Portfolio x PD x Loan Count'!F136*'User Segmentation'!$I$49/'Portfolio x PD x Loan Count'!F68 -> 56.559738 | G37: =G22*'Portfolio x PD x Loan Count'!G136*'User Segmentation'!$I$49/'Portfolio x PD x Loan Count'!G68 -> 64.831399 | I37: Millenial | J37: 50,000-1,00,000 | K37: {=C22*Dynamic_Row_Table[[Funding Rate]:[Funding Rate]]*Dynamic_Row_Table[[Tenure (in months)]:[Tenure (in months)]]/12} -> 1.1764779 | L37: {=D22*Dynamic_Row_Table[[Funding Rate]:[Funding Rate]]*Dynamic_Row_Table[[Tenure (in months)]:[Tenure (in months)]]/12} -> 1.5480476 | M37: {=E22*Dynamic_Row_Table[[Funding Rate]:[Funding Rate]]*Dynamic_Row_Table[[Tenure (in months)]:[Tenure (in months)]]/12} -> 2.2292815 | N37: {=F22*Dynamic_Row_Table[[Funding Rate]:[Funding Rate]]*Dynamic_Row_Table[[Tenure (in months)]:[Tenure (in months)]]/12} -> 2.9791171 | O37: {=G22*Dynamic_Row_Table[[Funding Rate]:[Funding Rate]]*Dynamic_Row_Table[[Tenure (in months)]:[Tenure (in months)]]/12} -> 3.990377
A38: Millenial | B38: >1,00,000 | C38: =C23*'Portfolio x PD x Loan Count'!C137*'User Segmentation'!$I$49/'Portfolio x PD x Loan Count'!C69 -> 99.88851 | D38: =D23*'Portfolio x PD x Loan Count'!D137*'User Segmentation'!$I$49/'Portfolio x PD x Loan Count'!D69 -> 49.261562 | E38: =E23*'Portfolio x PD x Loan Count'!E137*'User Segmentation'!$I$49/'Portfolio x PD x Loan Count'!E69 -> 73.712028 | F38: =F23*'Portfolio x PD x Loan Count'!F137*'User Segmentation'!$I$49/'Portfolio x PD x Loan Count'!F69 -> 87.693539 | G38: =G23*'Portfolio x PD x Loan Count'!G137*'User Segmentation'!$I$49/'Portfolio x PD x Loan Count'!G69 -> 87.700009 | I38: Millenial | J38: >1,00,000 | K38: {=C23*Dynamic_Row_Table[[Funding Rate]:[Funding Rate]]*Dynamic_Row_Table[[Tenure (in months)]:[Tenure (in months)]]/12} -> 1.803869 | L38: {=D23*Dynamic_Row_Table[[Funding Rate]:[Funding Rate]]*Dynamic_Row_Table[[Tenure (in months)]:[Tenure (in months)]]/12} -> 2.4871528 | M38: {=E23*Dynamic_Row_Table[[Funding Rate]:[Funding Rate]]*Dynamic_Row_Table[[Tenure (in months)]:[Tenure (in months)]]/12} -> 3.6214038 | N38: {=F23*Dynamic_Row_Table[[Funding Rate]:[Funding Rate]]*Dynamic_Row_Table[[Tenure (in months)]:[Tenure (in months)]]/12} -> 4.618998 | O38: {=G23*Dynamic_Row_Table[[Funding Rate]:[Funding Rate]]*Dynamic_Row_Table[[Tenure (in months)]:[Tenure (in months)]]/12} -> 5.3979415
A39: Gen X | B39: <50,000 | C39: =C24*'Portfolio x PD x Loan Count'!C138*'User Segmentation'!$I$49/'Portfolio x PD x Loan Count'!C70 -> 51.435016 | D39: =D24*'Portfolio x PD x Loan Count'!D138*'User Segmentation'!$I$49/'Portfolio x PD x Loan Count'!D70 -> 22.075676 | E39: =E24*'Portfolio x PD x Loan Count'!E138*'User Segmentation'!$I$49/'Portfolio x PD x Loan Count'!E70 -> 30.249747 | F39: =F24*'Portfolio x PD x Loan Count'!F138*'User Segmentation'!$I$49/'Portfolio x PD x Loan Count'!F70 -> 36.444708 | G39: =G24*'Portfolio x PD x Loan Count'!G138*'User Segmentation'!$I$49/'Portfolio x PD x Loan Count'!G70 -> 37.224768 | I39: Gen X | J39: <50,000 | K39: {=C24*Dynamic_Row_Table[[Funding Rate]:[Funding Rate]]*Dynamic_Row_Table[[Tenure (in months)]:[Tenure (in months)]]/12} -> 0.9288559 | L39: {=D24*Dynamic_Row_Table[[Funding Rate]:[Funding Rate]]*Dynamic_Row_Table[[Tenure (in months)]:[Tenure (in months)]]/12} -> 1.1145724 | M39: {=E24*Dynamic_Row_Table[[Funding Rate]:[Funding Rate]]*Dynamic_Row_Table[[Tenure (in months)]:[Tenure (in months)]]/12} -> 1.4861421 | N39: {=F24*Dynamic_Row_Table[[Funding Rate]:[Funding Rate]]*Dynamic_Row_Table[[Tenure (in months)]:[Tenure (in months)]]/12} -> 1.9196173 | O39: {=G24*Dynamic_Row_Table[[Funding Rate]:[Funding Rate]]*Dynamic_Row_Table[[Tenure (in months)]:[Tenure (in months)]]/12} -> 2.291187
A40: Gen X | B40: 50,000-1,00,000 | C40: =C25*'Portfolio x PD x Loan Count'!C139*'User Segmentation'!$I$49/'Portfolio x PD x Loan Count'!C71 -> 75.438527 | D40: =D25*'Portfolio x PD x Loan Count'!D139*'User Segmentation'!$I$49/'Portfolio x PD x Loan Count'!D71 -> 36.794598 | E40: =E25*'Portfolio x PD x Loan Count'!E139*'User Segmentation'!$I$49/'Portfolio x PD x Loan Count'!E71 -> 55.459261 | F40: =F25*'Portfolio x PD x Loan Count'!F139*'User Segmentation'!$I$49/'Portfolio x PD x Loan Count'!F71 -> 71.348293 | G40: =G25*'Portfolio x PD x Loan Count'!G139*'User Segmentation'!$I$49/'Portfolio x PD x Loan Count'!G71 -> 79.929122 | I40: Gen X | J40: 50,000-1,00,000 | K40: {=C25*Dynamic_Row_Table[[Funding Rate]:[Funding Rate]]*Dynamic_Row_Table[[Tenure (in months)]:[Tenure (in months)]]/12} -> 1.3623311 | L40: {=D25*Dynamic_Row_Table[[Funding Rate]:[Funding Rate]]*Dynamic_Row_Table[[Tenure (in months)]:[Tenure (in months)]]/12} -> 1.8577118 | M40: {=E25*Dynamic_Row_Table[[Funding Rate]:[Funding Rate]]*Dynamic_Row_Table[[Tenure (in months)]:[Tenure (in months)]]/12} -> 2.7246622 | N40: {=F25*Dynamic_Row_Table[[Funding Rate]:[Funding Rate]]*Dynamic_Row_Table[[Tenure (in months)]:[Tenure (in months)]]/12} -> 3.7580605 | O40: {=G25*Dynamic_Row_Table[[Funding Rate]:[Funding Rate]]*Dynamic_Row_Table[[Tenure (in months)]:[Tenure (in months)]]/12} -> 4.9196429
A41: Gen X | B41: >1,00,000 | C41: =C26*'Portfolio x PD x Loan Count'!C140*'User Segmentation'!$I$49/'Portfolio x PD x Loan Count'!C72 -> 119.56352 | D41: =D26*'Portfolio x PD x Loan Count'!D140*'User Segmentation'!$I$49/'Portfolio x PD x Loan Count'!D72 -> 60.629615 | E41: =E26*'Portfolio x PD x Loan Count'!E140*'User Segmentation'!$I$49/'Portfolio x PD x Loan Count'!E72 -> 91.23602 | F41: =F26*'Portfolio x PD x Loan Count'!F140*'User Segmentation'!$I$49/'Portfolio x PD x Loan Count'!F72 -> 95.476989 | G41: =G26*'Portfolio x PD x Loan Count'!G140*'User Segmentation'!$I$49/'Portfolio x PD x Loan Count'!G72 -> 87.700009 | I41: Gen X | J41: >1,00,000 | K41: {=C26*Dynamic_Row_Table[[Funding Rate]:[Funding Rate]]*Dynamic_Row_Table[[Tenure (in months)]:[Tenure (in months)]]/12} -> 2.1591766 | L41: {=D26*Dynamic_Row_Table[[Funding Rate]:[Funding Rate]]*Dynamic_Row_Table[[Tenure (in months)]:[Tenure (in months)]]/12} -> 3.0611111 | M41: {=E26*Dynamic_Row_Table[[Funding Rate]:[Funding Rate]]*Dynamic_Row_Table[[Tenure (in months)]:[Tenure (in months)]]/12} -> 4.4823413 | N41: {=F26*Dynamic_Row_Table[[Funding Rate]:[Funding Rate]]*Dynamic_Row_Table[[Tenure (in months)]:[Tenure (in months)]]/12} -> 5.0289683 | O41: {=G26*Dynamic_Row_Table[[Funding Rate]:[Funding Rate]]*Dynamic_Row_Table[[Tenure (in months)]:[Tenure (in months)]]/12} -> 5.3979415
A42: Baby Boomer | B42: <50,000 | C42: =C27*'Portfolio x PD x Loan Count'!C141*'User Segmentation'!$I$49/'Portfolio x PD x Loan Count'!C73 -> 41.151039 | D42: =D27*'Portfolio x PD x Loan Count'!D141*'User Segmentation'!$I$49/'Portfolio x PD x Loan Count'!D73 -> 18.397299 | E42: =E27*'Portfolio x PD x Loan Count'!E141*'User Segmentation'!$I$49/'Portfolio x PD x Loan Count'!E73 -> 23.946674 | F42: =F27*'Portfolio x PD x Loan Count'!F141*'User Segmentation'!$I$49/'Portfolio x PD x Loan Count'!F73 -> 28.215007 | G42: =G27*'Portfolio x PD x Loan Count'!G141*'User Segmentation'!$I$49/'Portfolio x PD x Loan Count'!G73 -> 30.182125 | I42: Baby Boomer | J42: <50,000 | K42: {=C27*Dynamic_Row_Table[[Funding Rate]:[Funding Rate]]*Dynamic_Row_Table[[Tenure (in months)]:[Tenure (in months)]]/12} -> 0.74313938 | L42: {=D27*Dynamic_Row_Table[[Funding Rate]:[Funding Rate]]*Dynamic_Row_Table[[Tenure (in months)]:[Tenure (in months)]]/12} -> 0.9288559 | M42: {=E27*Dynamic_Row_Table[[Funding Rate]:[Funding Rate]]*Dynamic_Row_Table[[Tenure (in months)]:[Tenure (in months)]]/12} -> 1.1764779 | N42: {=F27*Dynamic_Row_Table[[Funding Rate]:[Funding Rate]]*Dynamic_Row_Table[[Tenure (in months)]:[Tenure (in months)]]/12} -> 1.4861421 | O42: {=G27*Dynamic_Row_Table[[Funding Rate]:[Funding Rate]]*Dynamic_Row_Table[[Tenure (in months)]:[Tenure (in months)]]/12} -> 1.8577118
A43: Baby Boomer | B43: 50,000-1,00,000 | C43: =C28*'Portfolio x PD x Loan Count'!C142*'User Segmentation'!$I$49/'Portfolio x PD x Loan Count'!C74 -> 61.718992 | D43: =D28*'Portfolio x PD x Loan Count'!D142*'User Segmentation'!$I$49/'Portfolio x PD x Loan Count'!D74 -> 28.209011 | E43: =E28*'Portfolio x PD x Loan Count'!E142*'User Segmentation'!$I$49/'Portfolio x PD x Loan Count'!E74 -> 40.332996 | F43: =F28*'Portfolio x PD x Loan Count'!F142*'User Segmentation'!$I$49/'Portfolio x PD x Loan Count'!F74 -> 49.814081 | G43: =G28*'Portfolio x PD x Loan Count'!G142*'User Segmentation'!$I$49/'Portfolio x PD x Loan Count'!G74 -> 56.616461 | I43: Baby Boomer | J43: 50,000-1,00,000 | K43: {=C28*Dynamic_Row_Table[[Funding Rate]:[Funding Rate]]*Dynamic_Row_Table[[Tenure (in months)]:[Tenure (in months)]]/12} -> 1.1145724 | L43: {=D28*Dynamic_Row_Table[[Funding Rate]:[Funding Rate]]*Dynamic_Row_Table[[Tenure (in months)]:[Tenure (in months)]]/12} -> 1.4242366 | M43: {=E28*Dynamic_Row_Table[[Funding Rate]:[Funding Rate]]*Dynamic_Row_Table[[Tenure (in months)]:[Tenure (in months)]]/12} -> 1.9815228 | N43: {=F28*Dynamic_Row_Table[[Funding Rate]:[Funding Rate]]*Dynamic_Row_Table[[Tenure (in months)]:[Tenure (in months)]]/12} -> 2.6238095 | O43: {=G28*Dynamic_Row_Table[[Funding Rate]:[Funding Rate]]*Dynamic_Row_Table[[Tenure (in months)]:[Tenure (in months)]]/12} -> 3.484747
A44: Baby Boomer | B44: >1,00,000 | C44: =C29*'Portfolio x PD x Loan Count'!C143*'User Segmentation'!$I$49/'Portfolio x PD x Loan Count'!C75 -> 93.834661 | D44: =D29*'Portfolio x PD x Loan Count'!D143*'User Segmentation'!$I$49/'Portfolio x PD x Loan Count'!D75 -> 45.472211 | E44: =E29*'Portfolio x PD x Loan Count'!E143*'User Segmentation'!$I$49/'Portfolio x PD x Loan Count'!E75 -> 68.148856 | F44: =F29*'Portfolio x PD x Loan Count'!F143*'User Segmentation'!$I$49/'Portfolio x PD x Loan Count'!F75 -> 82.504572 | G44: =G29*'Portfolio x PD x Loan Count'!G143*'User Segmentation'!$I$49/'Portfolio x PD x Loan Count'!G75 -> 83.259502 | I44: Baby Boomer | J44: >1,00,000 | K44: {=C29*Dynamic_Row_Table[[Funding Rate]:[Funding Rate]]*Dynamic_Row_Table[[Tenure (in months)]:[Tenure (in months)]]/12} -> 1.6945437 | L44: {=D29*Dynamic_Row_Table[[Funding Rate]:[Funding Rate]]*Dynamic_Row_Table[[Tenure (in months)]:[Tenure (in months)]]/12} -> 2.2958333 | M44: {=E29*Dynamic_Row_Table[[Funding Rate]:[Funding Rate]]*Dynamic_Row_Table[[Tenure (in months)]:[Tenure (in months)]]/12} -> 3.3480903 | N44: {=F29*Dynamic_Row_Table[[Funding Rate]:[Funding Rate]]*Dynamic_Row_Table[[Tenure (in months)]:[Tenure (in months)]]/12} -> 4.3456845 | O44: {=G29*Dynamic_Row_Table[[Funding Rate]:[Funding Rate]]*Dynamic_Row_Table[[Tenure (in months)]:[Tenure (in months)]]/12} -> 5.124628
A46: Revenue Per Segment (In M) | I46: Revenue per Loan (in $)
A47: Generation | B47: Column1 | C47: Deep Subprime | D47: Sub Prime | E47: Near Prime | F47: Prime | G47: Super Prime | I47: Generation | J47: Income Bracket | K47: Deep Subprime | L47: Sub Prime | M47: Near Prime | N47: Prime | O47: Super Prime
A48: Gen Z | B48: <50,000 | C48: =C33*'Portfolio x PD x Loan Count'!C64 -> 190.67979 | D48: =D33*'Portfolio x PD x Loan Count'!D64 -> 66.866469 | E48: =E33*'Portfolio x PD x Loan Count'!E64 -> 40.77675 | F48: =F33*'Portfolio x PD x Loan Count'!F64 -> 35.328342 | G48: =G33*'Portfolio x PD x Loan Count'!G64 -> 14.097349 | I48: Gen Z | J48: <50,000 | K48: =C18*'User Segmentation'!$I$49 -> 2.8677778 | L48: =D18*'User Segmentation'!$I$49 -> 3.3896627 | M48: =E18*'User Segmentation'!$I$49 -> 4.4322817 | N48: =F18*'User Segmentation'!$I$49 -> 5.736131 | O48: =G18*'User Segmentation'!$I$49 -> 7.5612897
A49: Gen Z | B49: 50,000-1,00,000 | C49: =C34*'Portfolio x PD x Loan Count'!C65 -> 15.289488 | D49: =D34*'Portfolio x PD x Loan Count'!D65 -> 10.87384 | E49: =E34*'Portfolio x PD x Loan Count'!E65 -> 20.097527 | F49: =F34*'Portfolio x PD x Loan Count'!F65 -> 28.376372 | G49: =G34*'Portfolio x PD x Loan Count'!G65 -> 19.746325 | I49: Gen Z | J49: 50,000-1,00,000 | K49: =C19*'User Segmentation'!$I$49 -> 4.171627 | L49: =D19*'User Segmentation'!$I$49 -> 4.9535913 | M49: =E19*'User Segmentation'!$I$49 -> 6.2574405 | N49: =F19*'User Segmentation'!$I$49 -> 8.343254 | O49: =G19*'User Segmentation'!$I$49 -> 10.644841
A50: Gen Z | B50: >1,00,000 | C50: =C35*'Portfolio x PD x Loan Count'!C66 -> 0.99020972 | D50: =D35*'Portfolio x PD x Loan Count'!D66 -> 1.5166312 | E50: =E35*'Portfolio x PD x Loan Count'!E66 -> 4.0408908 | F50: =F35*'Portfolio x PD x Loan Count'!F66 -> 11.006607 | G50: =G35*'Portfolio x PD x Loan Count'!G66 -> 18.117159 | I50: Gen Z | J50: >1,00,000 | K50: =C20*'User Segmentation'!$I$49 -> 5.4662698 | L50: =D20*'User Segmentation'!$I$49 -> 6.7896825 | M50: =E20*'User Segmentation'!$I$49 -> 9.0912698 | N50: =F20*'User Segmentation'!$I$49 -> 12.65873 | O50: =G20*'User Segmentation'!$I$49 -> 16.686508
A51: Millenial | B51: <50,000 | C51: =C36*'Portfolio x PD x Loan Count'!C67 -> 140.73606 | D51: =D36*'Portfolio x PD x Loan Count'!D67 -> 50.698469 | E51: =E36*'Portfolio x PD x Loan Count'!E67 -> 31.990377 | F51: =F36*'Portfolio x PD x Loan Count'!F67 -> 27.934088 | G51: =G36*'Portfolio x PD x Loan Count'!G67 -> 10.450424 | I51: Millenial | J51: <50,000 | K51: =C21*'User Segmentation'!$I$49 -> 3.6503175 | L51: =D21*'User Segmentation'!$I$49 -> 4.4322817 | M51: =E21*'User Segmentation'!$I$49 -> 5.9967857 | N51: =F21*'User Segmentation'!$I$49 -> 7.8219444 | O51: =G21*'User Segmentation'!$I$49 -> 9.6666667
A52: Millenial | B52: 50,000-1,00,000 | C52: =C37*'Portfolio x PD x Loan Count'!C68 -> 45.618954 | D52: =D37*'Portfolio x PD x Loan Count'!D68 -> 35.951841 | E52: =E37*'Portfolio x PD x Loan Count'!E68 -> 75.750389 | F52: =F37*'Portfolio x PD x Loan Count'!F68 -> 107.1971 | G52: =G37*'Portfolio x PD x Loan Count'!G68 -> 78.313219 | I52: Millenial | J52: 50,000-1,00,000 | K52: =C22*'User Segmentation'!$I$49 -> 4.9535913 | L52: =D22*'User Segmentation'!$I$49 -> 6.5180952 | M52: =E22*'User Segmentation'!$I$49 -> 9.3864484 | N52: =F22*'User Segmentation'!$I$49 -> 12.543651 | O52: =G22*'User Segmentation'!$I$49 -> 16.801587
A53: Millenial | B53: >1,00,000 | C53: =C38*'Portfolio x PD x Loan Count'!C69 -> 10.371378 | D53: =D38*'Portfolio x PD x Loan Count'!D69 -> 17.633085 | E53: =E38*'Portfolio x PD x Loan Count'!E69 -> 51.088698 | F53: =F38*'Portfolio x PD x Loan Count'!F69 -> 127.46954 | G53: =G38*'Portfolio x PD x Loan Count'!G69 -> 186.01507 | I53: Millenial | J53: >1,00,000 | K53: =C23*'User Segmentation'!$I$49 -> 7.5952381 | L53: =D23*'User Segmentation'!$I$49 -> 10.472222 | M53: =E23*'User Segmentation'!$I$49 -> 15.248016 | N53: =F23*'User Segmentation'!$I$49 -> 19.448413 | O53: =G23*'User Segmentation'!$I$49 -> 22.728175
A54: Gen X | B54: <50,000 | C54: =C39*'Portfolio x PD x Loan Count'!C70 -> 53.97432 | D54: =D39*'Portfolio x PD x Loan Count'!D70 -> 19.214977 | E54: =E39*'Portfolio x PD x Loan Count'!E70 -> 11.948826 | F54: =F39*'Portfolio x PD x Loan Count'!F70 -> 10.332336 | G54: =G39*'Portfolio x PD x Loan Count'!G70 -> 3.7332044 | I54: Gen X | J54: <50,000 | K54: =C24*'User Segmentation'!$I$49 -> 3.9109722 | L54: =D24*'User Segmentation'!$I$49 -> 4.6929365 | M54: =E24*'User Segmentation'!$I$49 -> 6.2574405 | N54: =F24*'User Segmentation'!$I$49 -> 8.0825992 | O54: =G24*'User Segmentation'!$I$49 -> 9.6471032
A55: Gen X | B55: 50,000-1,00,000 | C55: =C40*'Portfolio x PD x Loan Count'!C71 -> 34.666767 | D55: =D40*'Portfolio x PD x Loan Count'!D71 -> 28.312895 | E55: =E40*'Portfolio x PD x Loan Count'!E71 -> 60.75776 | F55: =F40*'Portfolio x PD x Loan Count'!F71 -> 88.741828 | G55: =G40*'Portfolio x PD x Loan Count'!G71 -> 63.361267 | I55: Gen X | J55: 50,000-1,00,000 | K55: =C25*'User Segmentation'!$I$49 -> 5.736131 | L55: =D25*'User Segmentation'!$I$49 -> 7.8219444 | M55: =E25*'User Segmentation'!$I$49 -> 11.472262 | N55: =F25*'User Segmentation'!$I$49 -> 15.823413 | O55: =G25*'User Segmentation'!$I$49 -> 20.714286
A56: Gen X | B56: >1,00,000 | C56: =C41*'Portfolio x PD x Loan Count'!C72 -> 8.8874524 | D56: =D41*'Portfolio x PD x Loan Count'!D72 -> 15.536837 | E56: =E41*'Portfolio x PD x Loan Count'!E72 -> 45.27 | F56: =F41*'Portfolio x PD x Loan Count'!F72 -> 99.356255 | G56: =G41*'Portfolio x PD x Loan Count'!G72 -> 133.16982 | I56: Gen X | J56: >1,00,000 | K56: =C26*'User Segmentation'!$I$49 -> 9.0912698 | L56: =D26*'User Segmentation'!$I$49 -> 12.888889 | M56: =E26*'User Segmentation'!$I$49 -> 18.873016 | N56: =F26*'User Segmentation'!$I$49 -> 21.174603 | O56: =G26*'User Segmentation'!$I$49 -> 22.728175
A57: Baby Boomer | B57: <50,000 | C57: =C42*'Portfolio x PD x Loan Count'!C73 -> 44.055821 | D57: =D42*'Portfolio x PD x Loan Count'!D73 -> 16.337067 | E57: =E42*'Portfolio x PD x Loan Count'!E73 -> 9.6503457 | F57: =F42*'Portfolio x PD x Loan Count'!F73 -> 8.1609061 | G57: =G42*'Portfolio x PD x Loan Count'!G73 -> 3.0881171 | I57: Baby Boomer | J57: <50,000 | K57: =C27*'User Segmentation'!$I$49 -> 3.1290079 | L57: =D27*'User Segmentation'!$I$49 -> 3.9109722 | M57: =E27*'User Segmentation'!$I$49 -> 4.9535913 | N57: =F27*'User Segmentation'!$I$49 -> 6.2574405 | O57: =G27*'User Segmentation'!$I$49 -> 7.8219444
A58: Baby Boomer | B58: 50,000-1,00,000 | C58: =C43*'Portfolio x PD x Loan Count'!C74 -> 13.152565 | D58: =D43*'Portfolio x PD x Loan Count'!D74 -> 10.066062 | E58: =E43*'Portfolio x PD x Loan Count'!E74 -> 20.490836 | F58: =F43*'Portfolio x PD x Loan Count'!F74 -> 28.732169 | G58: =G43*'Portfolio x PD x Loan Count'!G74 -> 20.812921 | I58: Baby Boomer | J58: 50,000-1,00,000 | K58: =C28*'User Segmentation'!$I$49 -> 4.6929365 | L58: =D28*'User Segmentation'!$I$49 -> 5.9967857 | M58: =E28*'User Segmentation'!$I$49 -> 8.343254 | N58: =F28*'User Segmentation'!$I$49 -> 11.047619 | O58: =G28*'User Segmentation'!$I$49 -> 14.672619
A59: Baby Boomer | B59: >1,00,000 | C59: =C44*'Portfolio x PD x Loan Count'!C75 -> 2.3720007 | D59: =D44*'Portfolio x PD x Loan Count'!D75 -> 3.9627513 | E59: =E44*'Portfolio x PD x Loan Count'!E75 -> 11.499413 | F59: =F44*'Portfolio x PD x Loan Count'!F75 -> 29.19762 | G59: =G44*'Portfolio x PD x Loan Count'!G75 -> 42.994502 | I59: Baby Boomer | J59: >1,00,000 | K59: =C29*'User Segmentation'!$I$49 -> 7.1349206 | L59: =D29*'User Segmentation'!$I$49 -> 9.6666667 | M59: =E29*'User Segmentation'!$I$49 -> 14.097222 | N59: =F29*'User Segmentation'!$I$49 -> 18.297619 | O59: =G29*'User Segmentation'!$I$49 -> 21.577381

Sheet EAD Estimate
A1: Credit Category | B1: P(0.75) | C1: P(0.5) | D1: P(0.25) | E1: EAD | F1: LGD
A2: Deep Subprime | B2: 0.65 | C2: 0.25 | D2: 0.1 | E2: =B2*0.75+C2*0.5+D2*0.25 -> 0.6375 | F2: 1
A3: Sub Prime | B3: 0.45 | C3: 0.35 | D3: 0.2 | E3: =B3*0.75+C3*0.5+D3*0.25 -> 0.5625 | F3: 1
A4: Near Prime | B4: 0.3 | C4: 0.47 | D4: 0.23 | E4: =B4*0.75+C4*0.5+D4*0.25 -> 0.5175 | F4: 1
A5: Prime | B5: 0.25 | C5: 0.45 | D5: 0.3 | E5: =B5*0.75+C5*0.5+D5*0.25 -> 0.4875 | F5: 1
A6: Super Prime | B6: 0.15 | C6: 0.47 | D6: 0.38 | E6: =B6*0.75+C6*0.5+D6*0.25 -> 0.4425 | F6: 1

Sheet Dynamic PD
F1: Income Beta | G1: Beta Value | L1: {='Portfolio x PD x Loan Count'!A92:G105} -> Default Rate | M1: 0 | N1: 0 | O1: 0 | P1: 0 | Q1: 0 | R1: 0
F2: <50,000 | G2: 1.4 | L2: Generation | M2: Income Bracket | N2: Deep Subprime | O2: Sub Prime | P2: Near Prime | Q2: Prime | R2: Super Prime
F3: 50,000-1,00,000 | G3: 1.2 | L3: Gen Z | M3: <50,000 | N3: 0.0385 | O3: 0.0121 | P3: 0.0088 | Q3: 0.0077 | R3: 0.0088
F4: >1,00,000 | G4: 1.05 | L4: Gen Z | M4: 50,000-1,00,000 | N4: 0.0378 | O4: 0.01188 | P4: 0.00864 | Q4: 0.00756 | R4: 0.00864
L5: Gen Z | M5: >1,00,000 | N5: 0.035 | O5: 0.011 | P5: 0.008 | Q5: 0.007 | R5: 0.008
F6: Credit Category Beta | G6: Beta Value | L6: Millenial | M6: <50,000 | N6: 0.0385 | O6: 0.0121 | P6: 0.0088 | Q6: 0.0077 | R6: 0.0088
F7: Deep Subprime | G7: 1.35 | L7: Millenial | M7: 50,000-1,00,000 | N7: 0.0364 | O7: 0.01144 | P7: 0.00832 | Q7: 0.00728 | R7: 0.00832
F8: Sub Prime | G8: 1.2 | L8: Millenial | M8: >1,00,000 | N8: 0.035 | O8: 0.011 | P8: 0.008 | Q8: 0.007 | R8: 0.008
F9: Near Prime | G9: 1.1 | L9: Gen X | M9: <50,000 | N9: 0.035 | O9: 0.011 | P9: 0.008 | Q9: 0.007 | R9: 0.008
F10: Prime | G10: 1.05 | L10: Gen X | M10: 50,000-1,00,000 | N10: 0.035 | O10: 0.011 | P10: 0.008 | Q10: 0.007 | R10: 0.008
F11: Super Prime | G11: 1.02 | L11: Gen X | M11: >1,00,000 | N11: 0.035 | O11: 0.011 | P11: 0.008 | Q11: 0.007 | R11: 0.008
L12: Baby Boomer | M12: <50,000 | N12: 0.03675 | O12: 0.01155 | P12: 0.0084 | Q12: 0.00735 | R12: 0.0084
F13: Beta Segment | G13: LGD | H13: Fixed Cost | I13: Funding Rate | J13: Tenure (in months) | L13: Baby Boomer | M13: 50,000-1,00,000 | N13: 0.035 | O13: 0.011 | P13: 0.008 | Q13: 0.007 | R13: 0.008
F14: =(VLOOKUP($G$17,Beta_Income[#All],2,0))*(VLOOKUP($H$17,Beta_Credit[#All],2,0)) -> 1.32 | H14: 3 | I14: =(9.5% +Dashboard!$Q$25/10000) -> 0.095 | J14: 1.5 | L14: Baby Boomer | M14: >1,00,000 | N14: 0.035 | O14: 0.011 | P14: 0.008 | Q14: 0.007 | R14: 0.008
F16: Generation | G16: Income | H16: Credit Category | J16: Ticket Size | L16: PD(0)
F17: Gen Z | G17: 50,000-1,00,000 | H17: Near Prime | I17: 0 | J17: {=Table69[[ATS]:[ATS]]*(1+$I$17)} -> 125.14881 | L17: {=INDEX($N$3:$R$14, MATCH(1,($L$3:$L$14=$F$17)*($M$3:$M$14=$G$17),0), MATCH($H$17,$N$2:$R$2,0))} -> 0.00864
F19: PD(T) | L19: {='Support Tables'!A16:G29} -> Average Ticket Size | M19: 0 | N19: 0 | O19: 0 | P19: 0 | Q19: 0 | R19: 0
F20: {=IF($J$17<Table69[ATS],Table68[PD(0)],Table68[PD(0)]*($J$17/Table69[ATS])^Dynamic_Row_Table[Beta Segment])} -> 0.00864 | L20: Generation | M20: Income Bracket | N20: Deep Subprime | O20: Sub Prime | P20: Near Prime | Q20: Prime | R20: Super Prime
L21: Gen Z | M21: <50,000 | N21: 57.355556 | O21: 67.793254 | P21: 88.645635 | Q21: 114.72262 | R21: 151.22579
L22: Gen Z | M22: 50,000-1,00,000 | N22: 83.43254 | O22: 99.071825 | P22: 125.14881 | Q22: 166.86508 | R22: 212.89683
L23: Gen Z | M23: >1,00,000 | N23: 109.3254 | O23: 135.79365 | P23: 181.8254 | Q23: 253.1746 | R23: 333.73016
L24: Millenial | M24: <50,000 | N24: 73.006349 | O24: 88.645635 | P24: 119.93571 | Q24: 156.43889 | R24: 193.33333
L25: Millenial | M25: 50,000-1,00,000 | N25: 99.071825 | O25: 130.3619 | P25: 187.72897 | Q25: 250.87302 | R25: 336.03175
L26: Millenial | M26: >1,00,000 | N26: 151.90476 | O26: 209.44444 | P26: 304.96032 | Q26: 388.96825 | R26: 454.56349
L27: Gen X | M27: <50,000 | N27: 78.219444 | O27: 93.85873 | P27: 125.14881 | Q27: 161.65198 | R27: 192.94206
L28: Gen X | M28: 50,000-1,00,000 | N28: 114.72262 | O28: 156.43889 | P28: 229.44524 | Q28: 316.46825 | R28: 414.28571
L29: Gen X | M29: >1,00,000 | N29: 181.8254 | O29: 257.77778 | P29: 377.46032 | Q29: 423.49206 | R29: 454.56349
L30: Baby Boomer | M30: <50,000 | N30: 62.580159 | O30: 78.219444 | P30: 99.071825 | Q30: 125.14881 | R30: 156.43889
L31: Baby Boomer | M31: 50,000-1,00,000 | N31: 93.85873 | O31: 119.93571 | P31: 166.86508 | Q31: 220.95238 | R31: 293.45238
L32: Baby Boomer | M32: >1,00,000 | N32: 142.69841 | O32: 193.33333 | P32: 281.94444 | Q32: 365.95238 | R32: 431.54762
L34: ATS
L35: {=INDEX($N$21:$R$32,MATCH(1,($L$21:$L$32=$F$17)*($M$21:$M$32=$G$17),0),MATCH($H$17,$N$20:$R$20,0))} -> 125.14881

Sheet Contribution Margin
A1: CM per Loan (in $)
A2: Generation | B2: Income Bracket | C2: Deep Subprime | D2: Sub Prime | E2: Near Prime | F2: Prime | G2: Super Prime | I2: Generation | J2: Income Bracket | K2: Deep Subprime | L2: Sub Prime | M2: Near Prime | N2: Prime | O2: Super Prime
A3: Gen Z | B3: <50,000 | C3: {='Support Tables'!K48-'Support Tables'!K33-'Support Tables'!K18-Dynamic_Row_Table[[Fixed Cost]:[Fixed Cost]]} -> -2.2210399 | D3: {='Support Tables'!L48-'Support Tables'!L33-'Support Tables'!L18-Dynamic_Row_Table[[Fixed Cost]:[Fixed Cost]]} -> -0.87680003 | E3: {='Support Tables'!M48-'Support Tables'!M33-'Support Tables'!M18-Dynamic_Row_Table[[Fixed Cost]:[Fixed Cost]]} -> -0.02407739 | F3: {='Support Tables'!N48-'Support Tables'!N33-'Support Tables'!N18-Dynamic_Row_Table[[Fixed Cost]:[Fixed Cost]]} -> 0.94315982 | G3: {='Support Tables'!O48-'Support Tables'!O33-'Support Tables'!O18-Dynamic_Row_Table[[Fixed Cost]:[Fixed Cost]]} -> 2.1766101 | I3: Gen Z | J3: <50,000 | K3: =IF(CMPerLoan[[#This Row],[Deep Subprime]]>0,1,0) -> 0 | L3: =IF(CMPerLoan[[#This Row],[Sub Prime]]>0,1,0) -> 0 | M3: =IF(CMPerLoan[[#This Row],[Near Prime]]>0,1,0) -> 0 | N3: =IF(CMPerLoan[[#This Row],[Prime]]>0,1,0) -> 1 | O3: =IF(CMPerLoan[[#This Row],[Super Prime]]>0,1,0) -> 1
A4: Gen Z | B4: 50,000-1,00,000 | C4: {='Support Tables'!K49-'Support Tables'!K34-'Support Tables'!K19-Dynamic_Row_Table[[Fixed Cost]:[Fixed Cost]]} -> -1.82965 | D4: {='Support Tables'!L49-'Support Tables'!L34-'Support Tables'!L19-Dynamic_Row_Table[[Fixed Cost]:[Fixed Cost]]} -> 0.11506587 | E4: {='Support Tables'!M49-'Support Tables'!M34-'Support Tables'!M19-Dynamic_Row_Table[[Fixed Cost]:[Fixed Cost]]} -> 1.211733 | F4: {='Support Tables'!N49-'Support Tables'!N34-'Support Tables'!N19-Dynamic_Row_Table[[Fixed Cost]:[Fixed Cost]]} -> 2.7467499 | G4: {='Support Tables'!O49-'Support Tables'!O34-'Support Tables'!O19-Dynamic_Row_Table[[Fixed Cost]:[Fixed Cost]]} -> 4.3027443 | I4: Gen Z | J4: 50,000-1,00,000 | K4: =IF(CMPerLoan[[#This Row],[Deep Subprime]]>0,1,0) -> 0 | L4: =IF(CMPerLoan[[#This Row],[Sub Prime]]>0,1,0) -> 1 | M4: =IF(CMPerLoan[[#This Row],[Near Prime]]>0,1,0) -> 1 | N4: =IF(CMPerLoan[[#This Row],[Prime]]>0,1,0) -> 1 | O4: =IF(CMPerLoan[[#This Row],[Super Prime]]>0,1,0) -> 1
A5: Gen Z | B5: >1,00,000 | C5: {='Support Tables'!K50-'Support Tables'!K35-'Support Tables'!K20-Dynamic_Row_Table[[Fixed Cost]:[Fixed Cost]]} -> -1.2712922 | D5: {='Support Tables'!L50-'Support Tables'!L35-'Support Tables'!L20-Dynamic_Row_Table[[Fixed Cost]:[Fixed Cost]]} -> 1.3369097 | E5: {='Support Tables'!M50-'Support Tables'!M35-'Support Tables'!M20-Dynamic_Row_Table[[Fixed Cost]:[Fixed Cost]]} -> 3.1793361 | F5: {='Support Tables'!N50-'Support Tables'!N35-'Support Tables'!N20-Dynamic_Row_Table[[Fixed Cost]:[Fixed Cost]]} -> 5.7883234 | G5: {='Support Tables'!O50-'Support Tables'!O35-'Support Tables'!O20-Dynamic_Row_Table[[Fixed Cost]:[Fixed Cost]]} -> 8.5420575 | I5: Gen Z | J5: >1,00,000 | K5: =IF(CMPerLoan[[#This Row],[Deep Subprime]]>0,1,0) -> 0 | L5: =IF(CMPerLoan[[#This Row],[Sub Prime]]>0,1,0) -> 1 | M5: =IF(CMPerLoan[[#This Row],[Near Prime]]>0,1,0) -> 1 | N5: =IF(CMPerLoan[[#This Row],[Prime]]>0,1,0) -> 1 | O5: =IF(CMPerLoan[[#This Row],[Super Prime]]>0,1,0) -> 1
A6: Millenial | B6: <50,000 | C6: {='Support Tables'!K51-'Support Tables'!K36-'Support Tables'!K21-Dynamic_Row_Table[[Fixed Cost]:[Fixed Cost]]} -> -2.0084825 | D6: {='Support Tables'!L51-'Support Tables'!L36-'Support Tables'!L21-Dynamic_Row_Table[[Fixed Cost]:[Fixed Cost]]} -> -0.22372952 | E6: {='Support Tables'!M51-'Support Tables'!M36-'Support Tables'!M21-Dynamic_Row_Table[[Fixed Cost]:[Fixed Cost]]} -> 1.0263619 | F6: {='Support Tables'!N51-'Support Tables'!N36-'Support Tables'!N21-Dynamic_Row_Table[[Fixed Cost]:[Fixed Cost]]} -> 2.3770002 | G6: {='Support Tables'!O51-'Support Tables'!O36-'Support Tables'!O21-Dynamic_Row_Table[[Fixed Cost]:[Fixed Cost]]} -> 3.6179933 | I6: Millenial | J6: <50,000 | K6: =IF(CMPerLoan[[#This Row],[Deep Subprime]]>0,1,0) -> 0 | L6: =IF(CMPerLoan[[#This Row],[Sub Prime]]>0,1,0) -> 0 | M6: =IF(CMPerLoan[[#This Row],[Near Prime]]>0,1,0) -> 1 | N6: =IF(CMPerLoan[[#This Row],[Prime]]>0,1,0) -> 1 | O6: =IF(CMPerLoan[[#This Row],[Super Prime]]>0,1,0) -> 1
A7: Millenial | B7: 50,000-1,00,000 | C7: {='Support Tables'!K52-'Support Tables'!K37-'Support Tables'!K22-Dynamic_Row_Table[[Fixed Cost]:[Fixed Cost]]} -> -1.5218484 | D7: {='Support Tables'!L52-'Support Tables'!L37-'Support Tables'!L22-Dynamic_Row_Table[[Fixed Cost]:[Fixed Cost]]} -> 1.1311688 | E7: {='Support Tables'!M52-'Support Tables'!M37-'Support Tables'!M22-Dynamic_Row_Table[[Fixed Cost]:[Fixed Cost]]} -> 3.3488811 | F7: {='Support Tables'!N52-'Support Tables'!N37-'Support Tables'!N22-Dynamic_Row_Table[[Fixed Cost]:[Fixed Cost]]} -> 5.6741854 | G7: {='Support Tables'!O52-'Support Tables'!O37-'Support Tables'!O22-Dynamic_Row_Table[[Fixed Cost]:[Fixed Cost]]} -> 8.5740758 | I7: Millenial | J7: 50,000-1,00,000 | K7: =IF(CMPerLoan[[#This Row],[Deep Subprime]]>0,1,0) -> 0 | L7: =IF(CMPerLoan[[#This Row],[Sub Prime]]>0,1,0) -> 1 | M7: =IF(CMPerLoan[[#This Row],[Near Prime]]>0,1,0) -> 1 | N7: =IF(CMPerLoan[[#This Row],[Prime]]>0,1,0) -> 1 | O7: =IF(CMPerLoan[[#This Row],[Super Prime]]>0,1,0) -> 1
A8: Millenial | B8: >1,00,000 | C8: {='Support Tables'!K53-'Support Tables'!K38-'Support Tables'!K23-Dynamic_Row_Table[[Fixed Cost]:[Fixed Cost]]} -> -0.59800595 | D8: {='Support Tables'!L53-'Support Tables'!L38-'Support Tables'!L23-Dynamic_Row_Table[[Fixed Cost]:[Fixed Cost]]} -> 3.6891319 | E8: {='Support Tables'!M53-'Support Tables'!M38-'Support Tables'!M23-Dynamic_Row_Table[[Fixed Cost]:[Fixed Cost]]} -> 7.3640764 | F8: {='Support Tables'!N53-'Support Tables'!N38-'Support Tables'!N23-Dynamic_Row_Table[[Fixed Cost]:[Fixed Cost]]} -> 10.502061 | G8: {='Support Tables'!O53-'Support Tables'!O38-'Support Tables'!O23-Dynamic_Row_Table[[Fixed Cost]:[Fixed Cost]]} -> 12.721078 | I8: Millenial | J8: >1,00,000 | K8: =IF(CMPerLoan[[#This Row],[Deep Subprime]]>0,1,0) -> 0 | L8: =IF(CMPerLoan[[#This Row],[Sub Prime]]>0,1,0) -> 1 | M8: =IF(CMPerLoan[[#This Row],[Near Prime]]>0,1,0) -> 1 | N8: =IF(CMPerLoan[[#This Row],[Prime]]>0,1,0) -> 1 | O8: =IF(CMPerLoan[[#This Row],[Super Prime]]>0,1,0) -> 1
A9: Gen X | B9: <50,000 | C9: {='Support Tables'!K54-'Support Tables'!K39-'Support Tables'!K24-Dynamic_Row_Table[[Fixed Cost]:[Fixed Cost]]} -> -1.763155 | D9: {='Support Tables'!L54-'Support Tables'!L39-'Support Tables'!L24-Dynamic_Row_Table[[Fixed Cost]:[Fixed Cost]]} -> -0.0023868056 | E9: {='Support Tables'!M54-'Support Tables'!M39-'Support Tables'!M24-Dynamic_Row_Table[[Fixed Cost]:[Fixed Cost]]} -> 1.2531823 | F9: {='Support Tables'!N54-'Support Tables'!N39-'Support Tables'!N24-Dynamic_Row_Table[[Fixed Cost]:[Fixed Cost]]} -> 2.6113445 | G9: {='Support Tables'!O54-'Support Tables'!O39-'Support Tables'!O24-Dynamic_Row_Table[[Fixed Cost]:[Fixed Cost]]} -> 3.6729013 | I9: Gen X | J9: <50,000 | K9: =IF(CMPerLoan[[#This Row],[Deep Subprime]]>0,1,0) -> 0 | L9: =IF(CMPerLoan[[#This Row],[Sub Prime]]>0,1,0) -> 0 | M9: =IF(CMPerLoan[[#This Row],[Near Prime]]>0,1,0) -> 1 | N9: =IF(CMPerLoan[[#This Row],[Prime]]>0,1,0) -> 1 | O9: =IF(CMPerLoan[[#This Row],[Super Prime]]>0,1,0) -> 1
A10: Gen X | B10: 50,000-1,00,000 | C10: {='Support Tables'!K55-'Support Tables'!K40-'Support Tables'!K25-Dynamic_Row_Table[[Fixed Cost]:[Fixed Cost]]} -> -1.1859486 | D10: {='Support Tables'!L55-'Support Tables'!L40-'Support Tables'!L25-Dynamic_Row_Table[[Fixed Cost]:[Fixed Cost]]} -> 1.996267 | E10: {='Support Tables'!M55-'Support Tables'!M40-'Support Tables'!M25-Dynamic_Row_Table[[Fixed Cost]:[Fixed Cost]]} -> 4.7976964 | F10: {='Support Tables'!N55-'Support Tables'!N40-'Support Tables'!N25-Dynamic_Row_Table[[Fixed Cost]:[Fixed Cost]]} -> 7.9854043 | G10: {='Support Tables'!O55-'Support Tables'!O40-'Support Tables'!O25-Dynamic_Row_Table[[Fixed Cost]:[Fixed Cost]]} -> 11.328071 | I10: Gen X | J10: 50,000-1,00,000 | K10: =IF(CMPerLoan[[#This Row],[Deep Subprime]]>0,1,0) -> 0 | L10: =IF(CMPerLoan[[#This Row],[Sub Prime]]>0,1,0) -> 1 | M10: =IF(CMPerLoan[[#This Row],[Near Prime]]>0,1,0) -> 1 | N10: =IF(CMPerLoan[[#This Row],[Prime]]>0,1,0) -> 1 | O10: =IF(CMPerLoan[[#This Row],[Super Prime]]>0,1,0) -> 1
A11: Gen X | B11: >1,00,000 | C11: {='Support Tables'!K56-'Support Tables'!K41-'Support Tables'!K26-Dynamic_Row_Table[[Fixed Cost]:[Fixed Cost]]} -> -0.12488591 | D11: {='Support Tables'!L56-'Support Tables'!L41-'Support Tables'!L26-Dynamic_Row_Table[[Fixed Cost]:[Fixed Cost]]} -> 5.2327778 | E11: {='Support Tables'!M56-'Support Tables'!M41-'Support Tables'!M26-Dynamic_Row_Table[[Fixed Cost]:[Fixed Cost]]} -> 9.8279889 | F11: {='Support Tables'!N56-'Support Tables'!N41-'Support Tables'!N26-Dynamic_Row_Table[[Fixed Cost]:[Fixed Cost]]} -> 11.700468 | G11: {='Support Tables'!O56-'Support Tables'!O41-'Support Tables'!O26-Dynamic_Row_Table[[Fixed Cost]:[Fixed Cost]]} -> 12.721078 | I11: Gen X | J11: >1,00,000 | K11: =IF(CMPerLoan[[#This Row],[Deep Subprime]]>0,1,0) -> 0 | L11: =IF(CMPerLoan[[#This Row],[Sub Prime]]>0,1,0) -> 1 | M11: =IF(CMPerLoan[[#This Row],[Near Prime]]>0,1,0) -> 1 | N11: =IF(CMPerLoan[[#This Row],[Prime]]>0,1,0) -> 1 | O11: =IF(CMPerLoan[[#This Row],[Super Prime]]>0,1,0) -> 1
A12: Baby Boomer | B12: <50,000 | C12: {='Support Tables'!K57-'Support Tables'!K42-'Support Tables'!K27-Dynamic_Row_Table[[Fixed Cost]:[Fixed Cost]]} -> -2.0802672 | D12: {='Support Tables'!L57-'Support Tables'!L42-'Support Tables'!L27-Dynamic_Row_Table[[Fixed Cost]:[Fixed Cost]]} -> -0.52606563 | E12: {='Support Tables'!M57-'Support Tables'!M42-'Support Tables'!M27-Dynamic_Row_Table[[Fixed Cost]:[Fixed Cost]]} -> 0.34644812 | F12: {='Support Tables'!N57-'Support Tables'!N42-'Support Tables'!N27-Dynamic_Row_Table[[Fixed Cost]:[Fixed Cost]]} -> 1.3228745 | G12: {='Support Tables'!O57-'Support Tables'!O42-'Support Tables'!O27-Dynamic_Row_Table[[Fixed Cost]:[Fixed Cost]]} -> 2.3827493 | I12: Baby Boomer | J12: <50,000 | K12: =IF(CMPerLoan[[#This Row],[Deep Subprime]]>0,1,0) -> 0 | L12: =IF(CMPerLoan[[#This Row],[Sub Prime]]>0,1,0) -> 0 | M12: =IF(CMPerLoan[[#This Row],[Near Prime]]>0,1,0) -> 1 | N12: =IF(CMPerLoan[[#This Row],[Prime]]>0,1,0) -> 1 | O12: =IF(CMPerLoan[[#This Row],[Super Prime]]>0,1,0) -> 1
A13: Baby Boomer | B13: 50,000-1,00,000 | C13: {='Support Tables'!K58-'Support Tables'!K43-'Support Tables'!K28-Dynamic_Row_Table[[Fixed Cost]:[Fixed Cost]]} -> -1.5158588 | D13: {='Support Tables'!L58-'Support Tables'!L43-'Support Tables'!L28-Dynamic_Row_Table[[Fixed Cost]:[Fixed Cost]]} -> 0.83044688 | E13: {='Support Tables'!M58-'Support Tables'!M43-'Support Tables'!M28-Dynamic_Row_Table[[Fixed Cost]:[Fixed Cost]]} -> 2.6709097 | F13: {='Support Tables'!N58-'Support Tables'!N43-'Support Tables'!N28-Dynamic_Row_Table[[Fixed Cost]:[Fixed Cost]]} -> 4.6698095 | G13: {='Support Tables'!O58-'Support Tables'!O43-'Support Tables'!O28-Dynamic_Row_Table[[Fixed Cost]:[Fixed Cost]]} -> 7.1490506 | I13: Baby Boomer | J13: 50,000-1,00,000 | K13: =IF(CMPerLoan[[#This Row],[Deep Subprime]]>0,1,0) -> 0 | L13: =IF(CMPerLoan[[#This Row],[Sub Prime]]>0,1,0) -> 1 | M13: =IF(CMPerLoan[[#This Row],[Near Prime]]>0,1,0) -> 1 | N13: =IF(CMPerLoan[[#This Row],[Prime]]>0,1,0) -> 1 | O13: =IF(CMPerLoan[[#This Row],[Super Prime]]>0,1,0) -> 1
A14: Baby Boomer | B14: >1,00,000 | C14: {='Support Tables'!K59-'Support Tables'!K44-'Support Tables'!K29-Dynamic_Row_Table[[Fixed Cost]:[Fixed Cost]]} -> -0.74358135 | D14: {='Support Tables'!L59-'Support Tables'!L44-'Support Tables'!L29-Dynamic_Row_Table[[Fixed Cost]:[Fixed Cost]]} -> 3.1745833 | E14: {='Support Tables'!M59-'Support Tables'!M44-'Support Tables'!M29-Dynamic_Row_Table[[Fixed Cost]:[Fixed Cost]]} -> 6.5818819 | F14: {='Support Tables'!N59-'Support Tables'!N44-'Support Tables'!N29-Dynamic_Row_Table[[Fixed Cost]:[Fixed Cost]]} -> 9.703122 | G14: {='Support Tables'!O59-'Support Tables'!O44-'Support Tables'!O29-Dynamic_Row_Table[[Fixed Cost]:[Fixed Cost]]} -> 11.925074 | I14: Baby Boomer | J14: >1,00,000 | K14: =IF(CMPerLoan[[#This Row],[Deep Subprime]]>0,1,0) -> 0 | L14: =IF(CMPerLoan[[#This Row],[Sub Prime]]>0,1,0) -> 1 | M14: =IF(CMPerLoan[[#This Row],[Near Prime]]>0,1,0) -> 1 | N14: =IF(CMPerLoan[[#This Row],[Prime]]>0,1,0) -> 1 | O14: =IF(CMPerLoan[[#This Row],[Super Prime]]>0,1,0) -> 1
A16: CM per User (in $) | I16: # Profitable Loans(in M)
A17: Generation | B17: Income Bracket | C17: Deep Subprime | D17: Sub Prime | E17: Near Prime | F17: Prime | G17: Super Prime | I17: Generation | J17: Income Bracket | K17: Deep Subprime | L17: Sub Prime | M17: Near Prime | N17: Prime | O17: Super Prime
A18: Gen Z | B18: <50,000 | C18: =C3*'Portfolio x PD x Loan Count'!C132/'Portfolio x PD x Loan Count'!C64 -> -29.209929 | D18: =D3*'Portfolio x PD x Loan Count'!D132/'Portfolio x PD x Loan Count'!D64 -> -4.1244865 | E18: =E3*'Portfolio x PD x Loan Count'!E132/'Portfolio x PD x Loan Count'!E64 -> -0.11639503 | F18: =F3*'Portfolio x PD x Loan Count'!F132/'Portfolio x PD x Loan Count'!F64 -> 4.2527389 | G18: =G3*'Portfolio x PD x Loan Count'!G132/'Portfolio x PD x Loan Count'!G64 -> 8.3987708 | I18: Gen Z | J18: <50,000 | K18: =K3*'Portfolio x PD x Loan Count'!C132 -> 0 | L18: =L3*'Portfolio x PD x Loan Count'!D132 -> 0 | M18: =M3*'Portfolio x PD x Loan Count'!E132 -> 0 | N18: =N3*'Portfolio x PD x Loan Count'!F132 -> 6.1589148 | O18: =O3*'Portfolio x PD x Loan Count'!G132 -> 1.8644106
A19: Gen Z | B19: 50,000-1,00,000 | C19: =C4*'Portfolio x PD x Loan Count'!C133/'Portfolio x PD x Loan Count'!C65 -> -24.062579 | D19: =D4*'Portfolio x PD x Loan Count'!D133/'Portfolio x PD x Loan Count'!D65 -> 0.54127237 | E19: =E4*'Portfolio x PD x Loan Count'!E133/'Portfolio x PD x Loan Count'!E65 -> 5.8577652 | F19: =F4*'Portfolio x PD x Loan Count'!F133/'Portfolio x PD x Loan Count'!F65 -> 12.385187 | G19: =G4*'Portfolio x PD x Loan Count'!G133/'Portfolio x PD x Loan Count'!G65 -> 16.602773 | I19: Gen Z | J19: 50,000-1,00,000 | K19: =K4*'Portfolio x PD x Loan Count'!C133 -> 0 | L19: =L4*'Portfolio x PD x Loan Count'!D133 -> 2.1951427 | M19: =M4*'Portfolio x PD x Loan Count'!E133 -> 3.2117808 | N19: =N4*'Portfolio x PD x Loan Count'!F133 -> 3.4011157 | O19: =O4*'Portfolio x PD x Loan Count'!G133 -> 1.8550135
A20: Gen Z | B20: >1,00,000 | C20: =C5*'Portfolio x PD x Loan Count'!C134/'Portfolio x PD x Loan Count'!C66 -> -16.719355 | D20: =D5*'Portfolio x PD x Loan Count'!D134/'Portfolio x PD x Loan Count'!D66 -> 6.2888525 | E20: =E5*'Portfolio x PD x Loan Count'!E134/'Portfolio x PD x Loan Count'!E66 -> 15.369561 | F20: =F5*'Portfolio x PD x Loan Count'!F134/'Portfolio x PD x Loan Count'!F66 -> 26.099742 | G20: =G5*'Portfolio x PD x Loan Count'!G134/'Portfolio x PD x Loan Count'!G66 -> 32.960787 | I20: Gen Z | J20: >1,00,000 | K20: =K5*'Portfolio x PD x Loan Count'!C134 -> 0 | L20: =L5*'Portfolio x PD x Loan Count'!D134 -> 0.22337292 | M20: =M5*'Portfolio x PD x Loan Count'!E134 -> 0.44448035 | N20: =N5*'Portfolio x PD x Loan Count'!F134 -> 0.86948744 | O20: =O5*'Portfolio x PD x Loan Count'!G134 -> 1.085737
A21: Millenial | B21: <50,000 | C21: =C6*'Portfolio x PD x Loan Count'!C135/'Portfolio x PD x Loan Count'!C67 -> -26.414488 | D21: =D6*'Portfolio x PD x Loan Count'!D135/'Portfolio x PD x Loan Count'!D67 -> -1.0524286 | E21: =E6*'Portfolio x PD x Loan Count'!E135/'Portfolio x PD x Loan Count'!E67 -> 4.9616432 | F21: =F6*'Portfolio x PD x Loan Count'!F135/'Portfolio x PD x Loan Count'!F67 -> 10.717973 | G21: =G6*'Portfolio x PD x Loan Count'!G135/'Portfolio x PD x Loan Count'!G67 -> 13.96056 | I21: Millenial | J21: <50,000 | K21: =K6*'Portfolio x PD x Loan Count'!C135 -> 0 | L21: =L6*'Portfolio x PD x Loan Count'!D135 -> 0 | M21: =M6*'Portfolio x PD x Loan Count'!E135 -> 5.3345873 | N21: =N6*'Portfolio x PD x Loan Count'!F135 -> 3.5712461 | O21: =O6*'Portfolio x PD x Loan Count'!G135 -> 1.0810783
A22: Millenial | B22: 50,000-1,00,000 | C22: =C7*'Portfolio x PD x Loan Count'!C136/'Portfolio x PD x Loan Count'!C68 -> -20.014536 | D22: =D7*'Portfolio x PD x Loan Count'!D136/'Portfolio x PD x Loan Count'!D68 -> 5.3210426 | E22: =E7*'Portfolio x PD x Loan Count'!E136/'Portfolio x PD x Loan Count'!E68 -> 16.189176 | F22: =F7*'Portfolio x PD x Loan Count'!F136/'Portfolio x PD x Loan Count'!F68 -> 25.58509 | G22: =G7*'Portfolio x PD x Loan Count'!G136/'Portfolio x PD x Loan Count'!G68 -> 33.084334 | I22: Millenial | J22: 50,000-1,00,000 | K22: =K7*'Portfolio x PD x Loan Count'!C136 -> 0 | L22: =L7*'Portfolio x PD x Loan Count'!D136 -> 5.5156974 | M22: =M7*'Portfolio x PD x Loan Count'!E136 -> 8.0701865 | N22: =N7*'Portfolio x PD x Loan Count'!F136 -> 8.5459252 | O22: =O7*'Portfolio x PD x Loan Count'!G136 -> 4.6610607
A23: Millenial | B23: >1,00,000 | C23: =C8*'Portfolio x PD x Loan Count'!C137/'Portfolio x PD x Loan Count'!C69 -> -7.8646545 | D23: =D8*'Portfolio x PD x Loan Count'!D137/'Portfolio x PD x Loan Count'!D69 -> 17.353757 | E23: =E8*'Portfolio x PD x Loan Count'!E137/'Portfolio x PD x Loan Count'!E69 -> 35.599452 | F23: =F8*'Portfolio x PD x Loan Count'!F137/'Portfolio x PD x Loan Count'!F69 -> 47.35414 | G23: =G8*'Portfolio x PD x Loan Count'!G137/'Portfolio x PD x Loan Count'!G69 -> 49.086154 | I23: Millenial | J23: >1,00,000 | K23: =K8*'Portfolio x PD x Loan Count'!C137 -> 0 | L23: =L8*'Portfolio x PD x Loan Count'!D137 -> 1.6837959 | M23: =M8*'Portfolio x PD x Loan Count'!E137 -> 3.3505145 | N23: =N8*'Portfolio x PD x Loan Count'!F137 -> 6.5542385 | O23: =O8*'Portfolio x PD x Loan Count'!G137 -> 8.1843383
A24: Gen X | B24: <50,000 | C24: =C9*'Portfolio x PD x Loan Count'!C138/'Portfolio x PD x Loan Count'!C70 -> -23.188072 | D24: =D9*'Portfolio x PD x Loan Count'!D138/'Portfolio x PD x Loan Count'!D70 -> -0.011227585 | E24: =E9*'Portfolio x PD x Loan Count'!E138/'Portfolio x PD x Loan Count'!E70 -> 6.0581396 | F24: =F9*'Portfolio x PD x Loan Count'!F138/'Portfolio x PD x Loan Count'!F70 -> 11.774639 | G24: =G9*'Portfolio x PD x Loan Count'!G138/'Portfolio x PD x Loan Count'!G70 -> 14.17243 | I24: Gen X | J24: <50,000 | K24: =K9*'Portfolio x PD x Loan Count'!C138 -> 0 | L24: =L9*'Portfolio x PD x Loan Count'!D138 -> 0 | M24: =M9*'Portfolio x PD x Loan Count'!E138 -> 1.9095389 | N24: =N9*'Portfolio x PD x Loan Count'!F138 -> 1.2783432 | O24: =O9*'Portfolio x PD x Loan Count'!G138 -> 0.38697673
A25: Gen X | B25: 50,000-1,00,000 | C25: =C10*'Portfolio x PD x Loan Count'!C139/'Portfolio x PD x Loan Count'!C71 -> -15.596962 | D25: =D10*'Portfolio x PD x Loan Count'!D139/'Portfolio x PD x Loan Count'!D71 -> 9.3904836 | E25: =E10*'Portfolio x PD x Loan Count'!E139/'Portfolio x PD x Loan Count'!E71 -> 23.193046 | F25: =F10*'Portfolio x PD x Loan Count'!F139/'Portfolio x PD x Loan Count'!F71 -> 36.006453 | G25: =G10*'Portfolio x PD x Loan Count'!G139/'Portfolio x PD x Loan Count'!G71 -> 43.711032 | I25: Gen X | J25: 50,000-1,00,000 | K25: =K10*'Portfolio x PD x Loan Count'!C139 -> 0 | L25: =L10*'Portfolio x PD x Loan Count'!D139 -> 3.6196748 | M25: =M10*'Portfolio x PD x Loan Count'!E139 -> 5.2960576 | N25: =N10*'Portfolio x PD x Loan Count'!F139 -> 5.608261 | O25: =O10*'Portfolio x PD x Loan Count'!G139 -> 3.0588198
A26: Gen X | B26: >1,00,000 | C26: =C11*'Portfolio x PD x Loan Count'!C140/'Portfolio x PD x Loan Count'!C72 -> -1.6424328 | D26: =D11*'Portfolio x PD x Loan Count'!D140/'Portfolio x PD x Loan Count'!D72 -> 24.615101 | E26: =E11*'Portfolio x PD x Loan Count'!E140/'Portfolio x PD x Loan Count'!E72 -> 47.510509 | F26: =F11*'Portfolio x PD x Loan Count'!F140/'Portfolio x PD x Loan Count'!F72 -> 52.7578 | G26: =G11*'Portfolio x PD x Loan Count'!G140/'Portfolio x PD x Loan Count'!G72 -> 49.086154 | I26: Gen X | J26: >1,00,000 | K26: =K11*'Portfolio x PD x Loan Count'!C140 -> 0 | L26: =L11*'Portfolio x PD x Loan Count'!D140 -> 1.2054443 | M26: =M11*'Portfolio x PD x Loan Count'!E140 -> 2.3986628 | N26: =N11*'Portfolio x PD x Loan Count'!F140 -> 4.6922369 | O26: =O11*'Portfolio x PD x Loan Count'!G140 -> 5.8592397
A27: Baby Boomer | B27: <50,000 | C27: =C12*'Portfolio x PD x Loan Count'!C141/'Portfolio x PD x Loan Count'!C73 -> -27.358562 | D27: =D12*'Portfolio x PD x Loan Count'!D141/'Portfolio x PD x Loan Count'!D73 -> -2.4746242 | E27: =E12*'Portfolio x PD x Loan Count'!E141/'Portfolio x PD x Loan Count'!E73 -> 1.6748011 | F27: =F12*'Portfolio x PD x Loan Count'!F141/'Portfolio x PD x Loan Count'!F73 -> 5.9648852 | G27: =G12*'Portfolio x PD x Loan Count'!G141/'Portfolio x PD x Loan Count'!G73 -> 9.194189 | I27: Baby Boomer | J27: <50,000 | K27: =K12*'Portfolio x PD x Loan Count'!C141 -> 0 | L27: =L12*'Portfolio x PD x Loan Count'!D141 -> 0 | M27: =M12*'Portfolio x PD x Loan Count'!E141 -> 1.9481514 | N27: =N12*'Portfolio x PD x Loan Count'!F141 -> 1.3041924 | O27: =O12*'Portfolio x PD x Loan Count'!G141 -> 0.39480172
A28: Baby Boomer | B28: 50,000-1,00,000 | C28: =C13*'Portfolio x PD x Loan Count'!C142/'Portfolio x PD x Loan Count'!C74 -> -19.935765 | D28: =D13*'Portfolio x PD x Loan Count'!D142/'Portfolio x PD x Loan Count'!D74 -> 3.9064402 | E28: =E13*'Portfolio x PD x Loan Count'!E142/'Portfolio x PD x Loan Count'!E74 -> 12.911724 | F28: =F13*'Portfolio x PD x Loan Count'!F142/'Portfolio x PD x Loan Count'!F74 -> 21.056326 | G28: =G13*'Portfolio x PD x Loan Count'!G142/'Portfolio x PD x Loan Count'!G74 -> 27.585665 | I28: Baby Boomer | J28: 50,000-1,00,000 | K28: =K13*'Portfolio x PD x Loan Count'!C142 -> 0 | L28: =L13*'Portfolio x PD x Loan Count'!D142 -> 1.6785762 | M28: =M13*'Portfolio x PD x Loan Count'!E142 -> 2.4559765 | N28: =N13*'Portfolio x PD x Loan Count'!F142 -> 2.6007567 | O28: =O13*'Portfolio x PD x Loan Count'!G142 -> 1.4184871
A29: Baby Boomer | B29: >1,00,000 | C29: =C14*'Portfolio x PD x Loan Count'!C143/'Portfolio x PD x Loan Count'!C75 -> -9.7791843 | D29: =D14*'Portfolio x PD x Loan Count'!D143/'Portfolio x PD x Loan Count'!D75 -> 14.933309 | E29: =E14*'Portfolio x PD x Loan Count'!E143/'Portfolio x PD x Loan Count'!E75 -> 31.818164 | F29: =F14*'Portfolio x PD x Loan Count'!F143/'Portfolio x PD x Loan Count'!F75 -> 43.751699 | G29: =G14*'Portfolio x PD x Loan Count'!G143/'Portfolio x PD x Loan Count'!G75 -> 46.014656 | I29: Baby Boomer | J29: >1,00,000 | K29: =K14*'Portfolio x PD x Loan Count'!C143 -> 0 | L29: =L14*'Portfolio x PD x Loan Count'!D143 -> 0.40993979 | M29: =M14*'Portfolio x PD x Loan Count'!E143 -> 0.8157219 | N29: =N14*'Portfolio x PD x Loan Count'!F143 -> 1.595706 | O29: =O14*'Portfolio x PD x Loan Count'!G143 -> 1.9925728
A31: %Profitable Loans | B31: %Unprofitable Loans
A32: =SUM(K18:K29,L18:L29,M18:M29,N18:N29,O18:O29)/'User Segmentation'!$I$47 -> 0.38651061 | B32: =1-LoanComp[[#This Row],[%Profitable Loans ]] -> 0.61348939

Sheet Dynamic CM
A1: User Profiles
A2: Users | B2: Generation | C2: Income Bracket | D2: Credit Category | E2: Portfolio % | F2: ATS | G2: PD(0) | H2: Beta Val
A3: User1 | B3: Gen Z | C3: <50,000 | D3: Deep Subprime | E3: {=INDEX(Portfolio_Perc[[Deep Subprime]:[Super Prime]], MATCH(1,(Portfolio_Perc[Generation]=UserProfiles[[#This Row],[Generation]:[Generation]])*(Portfolio_Perc[Income Bracket]=UserProfiles[[#This Row],[Income Bracket]:[Income Bracket]]),0), MATCH(UserProfiles[[#This Row],[Credit Category]:[Credit Category]],Portfolio_Perc[[#Headers],[Deep Subprime]:[Super Prime]],0))} -> 0.098055593 | F3: {=INDEX( ATS_Table[[Deep Subprime]:[Super Prime]], MATCH(1, (ATS_Table[Generation]=UserProfiles[[#This Row],[Generation]])* (ATS_Table[Income Bracket]=UserProfiles[[#This Row],[Income Bracket]]), 0), MATCH(UserProfiles[[#This Row],[Credit Category]], ATS_Table[[#Headers],[Deep Subprime]:[Super Prime]], 0) )} -> 57.355556 | G3: {=INDEX('Dynamic PD'!$N$3:$R$14, MATCH(1,('Dynamic PD'!$L$3:$L$14=UserProfiles[[#This Row],[Generation]])*('Dynamic PD'!$M$3:$M$14=UserProfiles[[#This Row],[Income Bracket]]),0),MATCH(UserProfiles[[#This Row],[Credit Category]],'Dynamic PD'!$N$2:$R$2,0))} -> 0.0385 | H3: =(VLOOKUP(UserProfiles[[#This Row],[Income Bracket]],Beta_Income[],2,FALSE))*(VLOOKUP(UserProfiles[[#This Row],[Credit Category]],Beta_Credit[],2,FALSE)) -> 1.89
A4: User2 | B4: Millenial | C4: 50,000-1,00,000 | D4: Near Prime | E4: {=INDEX(Portfolio_Perc[[Deep Subprime]:[Super Prime]], MATCH(1,(Portfolio_Perc[Generation]=UserProfiles[[#This Row],[Generation]:[Generation]])*(Portfolio_Perc[Income Bracket]=UserProfiles[[#This Row],[Income Bracket]:[Income Bracket]]),0), MATCH(UserProfiles[[#This Row],[Credit Category]:[Credit Category]],Portfolio_Perc[[#Headers],[Deep Subprime]:[Super Prime]],0))} -> 0.032377692 | F4: {=INDEX( ATS_Table[[Deep Subprime]:[Super Prime]], MATCH(1, (ATS_Table[Generation]=UserProfiles[[#This Row],[Generation]])* (ATS_Table[Income Bracket]=UserProfiles[[#This Row],[Income Bracket]]), 0), MATCH(UserProfiles[[#This Row],[Credit Category]], ATS_Table[[#Headers],[Deep Subprime]:[Super Prime]], 0) )} -> 187.72897 | G4: {=INDEX('Dynamic PD'!$N$3:$R$14, MATCH(1,('Dynamic PD'!$L$3:$L$14=UserProfiles[[#This Row],[Generation]])*('Dynamic PD'!$M$3:$M$14=UserProfiles[[#This Row],[Income Bracket]]),0),MATCH(UserProfiles[[#This Row],[Credit Category]],'Dynamic PD'!$N$2:$R$2,0))} -> 0.00832 | H4: =(VLOOKUP(UserProfiles[[#This Row],[Income Bracket]],Beta_Income[],2,FALSE))*(VLOOKUP(UserProfiles[[#This Row],[Credit Category]],Beta_Credit[],2,FALSE)) -> 1.32
A5: User3 | B5: Gen X | C5: >1,00,000 | D5: Super Prime | E5: {=INDEX(Portfolio_Perc[[Deep Subprime]:[Super Prime]], MATCH(1,(Portfolio_Perc[Generation]=UserProfiles[[#This Row],[Generation]:[Generation]])*(Portfolio_Perc[Income Bracket]=UserProfiles[[#This Row],[Income Bracket]:[Income Bracket]]),0), MATCH(UserProfiles[[#This Row],[Credit Category]:[Credit Category]],Portfolio_Perc[[#Headers],[Deep Subprime]:[Super Prime]],0))} -> 0.029450558 | F5: {=INDEX( ATS_Table[[Deep Subprime]:[Super Prime]], MATCH(1, (ATS_Table[Generation]=UserProfiles[[#This Row],[Generation]])* (ATS_Table[Income Bracket]=UserProfiles[[#This Row],[Income Bracket]]), 0), MATCH(UserProfiles[[#This Row],[Credit Category]], ATS_Table[[#Headers],[Deep Subprime]:[Super Prime]], 0) )} -> 454.56349 | G5: {=INDEX('Dynamic PD'!$N$3:$R$14, MATCH(1,('Dynamic PD'!$L$3:$L$14=UserProfiles[[#This Row],[Generation]])*('Dynamic PD'!$M$3:$M$14=UserProfiles[[#This Row],[Income Bracket]]),0),MATCH(UserProfiles[[#This Row],[Credit Category]],'Dynamic PD'!$N$2:$R$2,0))} -> 0.008 | H5: =(VLOOKUP(UserProfiles[[#This Row],[Income Bracket]],Beta_Income[],2,FALSE))*(VLOOKUP(UserProfiles[[#This Row],[Credit Category]],Beta_Credit[],2,FALSE)) -> 1.071
A6: Selected User | B6: =Dashboard!$H$15 -> Gen Z | C6: =Dashboard!$M$15 -> 50,000-1,00,000 | D6: =Dashboard!$R$15 -> Near Prime | E6: {=INDEX(Portfolio_Perc[[Deep Subprime]:[Super Prime]], MATCH(1,(Portfolio_Perc[Generation]=UserProfiles[[#This Row],[Generation]:[Generation]])*(Portfolio_Perc[Income Bracket]=UserProfiles[[#This Row],[Income Bracket]:[Income Bracket]]),0), MATCH(UserProfiles[[#This Row],[Credit Category]:[Credit Category]],Portfolio_Perc[[#Headers],[Deep Subprime]:[Super Prime]],0))} -> 0.012885706 | F6: {=INDEX( ATS_Table[[Deep Subprime]:[Super Prime]], MATCH(1, (ATS_Table[Generation]=UserProfiles[[#This Row],[Generation]])* (ATS_Table[Income Bracket]=UserProfiles[[#This Row],[Income Bracket]]), 0), MATCH(UserProfiles[[#This Row],[Credit Category]], ATS_Table[[#Headers],[Deep Subprime]:[Super Prime]], 0) )} -> 125.14881 | G6: {=INDEX('Dynamic PD'!$N$3:$R$14, MATCH(1,('Dynamic PD'!$L$3:$L$14=UserProfiles[[#This Row],[Generation]])*('Dynamic PD'!$M$3:$M$14=UserProfiles[[#This Row],[Income Bracket]]),0),MATCH(UserProfiles[[#This Row],[Credit Category]],'Dynamic PD'!$N$2:$R$2,0))} -> 0.00864 | H6: =(VLOOKUP(UserProfiles[[#This Row],[Income Bracket]],Beta_Income[],2,FALSE))*(VLOOKUP(UserProfiles[[#This Row],[Credit Category]],Beta_Credit[],2,FALSE)) -> 1.32
A8: Delta | B8: =$B$3 & "," & CHAR(10) & $C$3 & "," & CHAR(10) & $D$3 -> Gen Z, <50,000, Deep Subprime | C8: =$B$4 & "," & CHAR(10) & $C$4 & "," & CHAR(10) & $D$4 -> Millenial, 50,000-1,00,000, Near Prime | D8: =$B$5 & "," & CHAR(10) & $C$5 & "," & CHAR(10) & $D$5 -> Gen X, >1,00,000, Super Prime | E8: =$B$6 & "," & CHAR(10) & $C$6 & "," & CHAR(10) & $D$6 -> Gen Z, 50,000-1,00,000, Near Prime | Q8: Delta | R8: Gen Z, <50,000, Deep Subprime | S8: Millenial, 50,000-1,00,000, Near Prime | T8: Gen X, >1,00,000, Super Prime | U8: Millenial, 50,000-1,00,000, Sub Prime
A9: -0.75 | B9: {=($F$3*(1+$A9)*'User Segmentation'!$I$49) -Dynamic_Row_Table[[Fixed Cost]:[Fixed Cost]] -(Dynamic_Row_Table[[Funding Rate]:[Funding Rate]]*Dynamic_Row_Table[[Tenure (in months)]:[Tenure (in months)]]*$F$3*(1+$A9)/12) -(IF($A9<0,'Dynamic CM'!$G$3,'Dynamic CM'!$G$3*(($F$3*(1+$A9)/$F$3)^'Dynamic CM'!$H$3)) *VLOOKUP($D$3,EAD_Table[#All],MATCH("EAD",EAD_Table[#Headers],0),FALSE) *$F$3*(1+$A9))} -> -2.80526 | C9: {=($F$4*(1+$A9)*'User Segmentation'!$I$49) -Dynamic_Row_Table[[Fixed Cost]:[Fixed Cost]] -(Dynamic_Row_Table[[Funding Rate]:[Funding Rate]]*Dynamic_Row_Table[[Tenure (in months)]:[Tenure (in months)]]*$F$4*(1+$A9)/12) -(IF($A9<0,'Dynamic CM'!$G$4,'Dynamic CM'!$G$4*(($F$4*(1+$A9)/$F$4)^'Dynamic CM'!$H$4)) *VLOOKUP($D$4,EAD_Table[#All],MATCH("EAD",EAD_Table[#Headers],0),FALSE) *$F$4*(1+$A9))} -> -1.4127797 | D9: {=($F$5*(1+$A9)*'User Segmentation'!$I$49) -Dynamic_Row_Table[[Fixed Cost]:[Fixed Cost]] -(Dynamic_Row_Table[[Funding Rate]:[Funding Rate]]*Dynamic_Row_Table[[Tenure (in months)]:[Tenure (in months)]]*$F$5*(1+$A9)/12) -(IF($A9<0,'Dynamic CM'!$G$5,'Dynamic CM'!$G$5*(($F$5*(1+$A9)/$F$5)^'Dynamic CM'!$H$5)) *VLOOKUP($D$5,EAD_Table[#All],MATCH("EAD",EAD_Table[#Headers],0),FALSE) *$F$5*(1+$A9))} -> 0.93026959 | E9: {=($F$6*(1+$A9)*'User Segmentation'!$I$49) -Dynamic_Row_Table[[Fixed Cost]:[Fixed Cost]] -(Dynamic_Row_Table[[Funding Rate]:[Funding Rate]]*Dynamic_Row_Table[[Tenure (in months)]:[Tenure (in months)]]*$F$6*(1+$A9)/12) -(IF($A9<0,'Dynamic CM'!$G$6,'Dynamic CM'!$G$6*(($F$6*(1+$A9)/$F$6)^'Dynamic CM'!$H$6)) *VLOOKUP($D$6,EAD_Table[#All],MATCH("EAD",EAD_Table[#Headers],0),FALSE) *$F$6*(1+$A9))} -> -1.9470667 | Q9: -0.9 | R9: {=($F$3*(1+$Q9)*'User Segmentation'!$I$49) -Dynamic_Row_Table[[Fixed Cost]:[Fixed Cost]] -(Dynamic_Row_Table[[Funding Rate]:[Funding Rate]]*Dynamic_Row_Table[[Tenure (in months)]:[Tenure (in months)]]*$F$3*(1+$Q9)/12) -(IF($Q9<0,'Dynamic CM'!$G$3,'Dynamic CM'!$G$3*(($F$3*(1+$Q9)/$F$3)^'Dynamic CM'!$H$3)) *VLOOKUP($D$3,EAD_Table[#All],MATCH("EAD",EAD_Table[#Headers],0),FALSE) *$F$3*(1+$Q9))} -> -2.922104 | S9: {=($F$4*(1+$Q9)*'User Segmentation'!$I$49) -Dynamic_Row_Table[[Fixed Cost]:[Fixed Cost]] -(Dynamic_Row_Table[[Funding Rate]:[Funding Rate]]*Dynamic_Row_Table[[Tenure (in months)]:[Tenure (in months)]]*$F$4*(1+$Q9)/12) -(IF($Q9<0,'Dynamic CM'!$G$4,'Dynamic CM'!$G$4*(($F$4*(1+$Q9)/$F$4)^'Dynamic CM'!$H$4)) *VLOOKUP($D$4,EAD_Table[#All],MATCH("EAD",EAD_Table[#Headers],0),FALSE) *$F$4*(1+$Q9))} -> -2.3651119 | T9: {=($F$5*(1+$Q9)*'User Segmentation'!$I$49) -Dynamic_Row_Table[[Fixed Cost]:[Fixed Cost]] -(Dynamic_Row_Table[[Funding Rate]:[Funding Rate]]*Dynamic_Row_Table[[Tenure (in months)]:[Tenure (in months)]]*$F$5*(1+$Q9)/12) -(IF($Q9<0,'Dynamic CM'!$G$5,'Dynamic CM'!$G$5*(($F$5*(1+$Q9)/$F$5)^'Dynamic CM'!$H$5)) *VLOOKUP($D$5,EAD_Table[#All],MATCH("EAD",EAD_Table[#Headers],0),FALSE) *$F$5*(1+$Q9))} -> -1.4278922 | U9: {=($F$6*(1+$Q9)*'User Segmentation'!$I$49) -Dynamic_Row_Table[[Fixed Cost]:[Fixed Cost]] -(Dynamic_Row_Table[[Funding Rate]:[Funding Rate]]*Dynamic_Row_Table[[Tenure (in months)]:[Tenure (in months)]]*$F$6*(1+$Q9)/12) -(IF($Q9<0,'Dynamic CM'!$G$6,'Dynamic CM'!$G$6*(($F$6*(1+$Q9)/$F$6)^'Dynamic CM'!$H$6)) *VLOOKUP($D$6,EAD_Table[#All],MATCH("EAD",EAD_Table[#Headers],0),FALSE) *$F$6*(1+$Q9))} -> -2.5788267
A10: -0.5 | B10: {=($F$3*(1+$A10)*'User Segmentation'!$I$49) -Dynamic_Row_Table[[Fixed Cost]:[Fixed Cost]] -(Dynamic_Row_Table[[Funding Rate]:[Funding Rate]]*Dynamic_Row_Table[[Tenure (in months)]:[Tenure (in months)]]*$F$3*(1+$A10)/12) -(IF($A10<0,'Dynamic CM'!$G$3,'Dynamic CM'!$G$3*(($F$3*(1+$A10)/$F$3)^'Dynamic CM'!$H$3)) *VLOOKUP($D$3,EAD_Table[#All],MATCH("EAD",EAD_Table[#Headers],0),FALSE) *$F$3*(1+$A10))} -> -2.6105199 | C10: {=($F$4*(1+$A10)*'User Segmentation'!$I$49) -Dynamic_Row_Table[[Fixed Cost]:[Fixed Cost]] -(Dynamic_Row_Table[[Funding Rate]:[Funding Rate]]*Dynamic_Row_Table[[Tenure (in months)]:[Tenure (in months)]]*$F$4*(1+$A10)/12) -(IF($A10<0,'Dynamic CM'!$G$4,'Dynamic CM'!$G$4*(($F$4*(1+$A10)/$F$4)^'Dynamic CM'!$H$4)) *VLOOKUP($D$4,EAD_Table[#All],MATCH("EAD",EAD_Table[#Headers],0),FALSE) *$F$4*(1+$A10))} -> 0.17444053 | D10: {=($F$5*(1+$A10)*'User Segmentation'!$I$49) -Dynamic_Row_Table[[Fixed Cost]:[Fixed Cost]] -(Dynamic_Row_Table[[Funding Rate]:[Funding Rate]]*Dynamic_Row_Table[[Tenure (in months)]:[Tenure (in months)]]*$F$5*(1+$A10)/12) -(IF($A10<0,'Dynamic CM'!$G$5,'Dynamic CM'!$G$5*(($F$5*(1+$A10)/$F$5)^'Dynamic CM'!$H$5)) *VLOOKUP($D$5,EAD_Table[#All],MATCH("EAD",EAD_Table[#Headers],0),FALSE) *$F$5*(1+$A10))} -> 4.8605392 | E10: {=($F$6*(1+$A10)*'User Segmentation'!$I$49) -Dynamic_Row_Table[[Fixed Cost]:[Fixed Cost]] -(Dynamic_Row_Table[[Funding Rate]:[Funding Rate]]*Dynamic_Row_Table[[Tenure (in months)]:[Tenure (in months)]]*$F$6*(1+$A10)/12) -(IF($A10<0,'Dynamic CM'!$G$6,'Dynamic CM'!$G$6*(($F$6*(1+$A10)/$F$6)^'Dynamic CM'!$H$6)) *VLOOKUP($D$6,EAD_Table[#All],MATCH("EAD",EAD_Table[#Headers],0),FALSE) *$F$6*(1+$A10))} -> -0.8941335 | Q10: -0.8 | R10: {=($F$3*(1+$Q10)*'User Segmentation'!$I$49) -Dynamic_Row_Table[[Fixed Cost]:[Fixed Cost]] -(Dynamic_Row_Table[[Funding Rate]:[Funding Rate]]*Dynamic_Row_Table[[Tenure (in months)]:[Tenure (in months)]]*$F$3*(1+$Q10)/12) -(IF($Q10<0,'Dynamic CM'!$G$3,'Dynamic CM'!$G$3*(($F$3*(1+$Q10)/$F$3)^'Dynamic CM'!$H$3)) *VLOOKUP($D$3,EAD_Table[#All],MATCH("EAD",EAD_Table[#Headers],0),FALSE) *$F$3*(1+$Q10))} -> -2.844208 | S10: {=($F$4*(1+$Q10)*'User Segmentation'!$I$49) -Dynamic_Row_Table[[Fixed Cost]:[Fixed Cost]] -(Dynamic_Row_Table[[Funding Rate]:[Funding Rate]]*Dynamic_Row_Table[[Tenure (in months)]:[Tenure (in months)]]*$F$4*(1+$Q10)/12) -(IF($Q10<0,'Dynamic CM'!$G$4,'Dynamic CM'!$G$4*(($F$4*(1+$Q10)/$F$4)^'Dynamic CM'!$H$4)) *VLOOKUP($D$4,EAD_Table[#All],MATCH("EAD",EAD_Table[#Headers],0),FALSE) *$F$4*(1+$Q10))} -> -1.7302238 | T10: {=($F$5*(1+$Q10)*'User Segmentation'!$I$49) -Dynamic_Row_Table[[Fixed Cost]:[Fixed Cost]] -(Dynamic_Row_Table[[Funding Rate]:[Funding Rate]]*Dynamic_Row_Table[[Tenure (in months)]:[Tenure (in months)]]*$F$5*(1+$Q10)/12) -(IF($Q10<0,'Dynamic CM'!$G$5,'Dynamic CM'!$G$5*(($F$5*(1+$Q10)/$F$5)^'Dynamic CM'!$H$5)) *VLOOKUP($D$5,EAD_Table[#All],MATCH("EAD",EAD_Table[#Headers],0),FALSE) *$F$5*(1+$Q10))} -> 0.14421567 | U10: {=($F$6*(1+$Q10)*'User Segmentation'!$I$49) -Dynamic_Row_Table[[Fixed Cost]:[Fixed Cost]] -(Dynamic_Row_Table[[Funding Rate]:[Funding Rate]]*Dynamic_Row_Table[[Tenure (in months)]:[Tenure (in months)]]*$F$6*(1+$Q10)/12) -(IF($Q10<0,'Dynamic CM'!$G$6,'Dynamic CM'!$G$6*(($F$6*(1+$Q10)/$F$6)^'Dynamic CM'!$H$6)) *VLOOKUP($D$6,EAD_Table[#All],MATCH("EAD",EAD_Table[#Headers],0),FALSE) *$F$6*(1+$Q10))} -> -2.1576534
A11: -0.25 | B11: {=($F$3*(1+$A11)*'User Segmentation'!$I$49) -Dynamic_Row_Table[[Fixed Cost]:[Fixed Cost]] -(Dynamic_Row_Table[[Funding Rate]:[Funding Rate]]*Dynamic_Row_Table[[Tenure (in months)]:[Tenure (in months)]]*$F$3*(1+$A11)/12) -(IF($A11<0,'Dynamic CM'!$G$3,'Dynamic CM'!$G$3*(($F$3*(1+$A11)/$F$3)^'Dynamic CM'!$H$3)) *VLOOKUP($D$3,EAD_Table[#All],MATCH("EAD",EAD_Table[#Headers],0),FALSE) *$F$3*(1+$A11))} -> -2.4157799 | C11: {=($F$4*(1+$A11)*'User Segmentation'!$I$49) -Dynamic_Row_Table[[Fixed Cost]:[Fixed Cost]] -(Dynamic_Row_Table[[Funding Rate]:[Funding Rate]]*Dynamic_Row_Table[[Tenure (in months)]:[Tenure (in months)]]*$F$4*(1+$A11)/12) -(IF($A11<0,'Dynamic CM'!$G$4,'Dynamic CM'!$G$4*(($F$4*(1+$A11)/$F$4)^'Dynamic CM'!$H$4)) *VLOOKUP($D$4,EAD_Table[#All],MATCH("EAD",EAD_Table[#Headers],0),FALSE) *$F$4*(1+$A11))} -> 1.7616608 | D11: {=($F$5*(1+$A11)*'User Segmentation'!$I$49) -Dynamic_Row_Table[[Fixed Cost]:[Fixed Cost]] -(Dynamic_Row_Table[[Funding Rate]:[Funding Rate]]*Dynamic_Row_Table[[Tenure (in months)]:[Tenure (in months)]]*$F$5*(1+$A11)/12) -(IF($A11<0,'Dynamic CM'!$G$5,'Dynamic CM'!$G$5*(($F$5*(1+$A11)/$F$5)^'Dynamic CM'!$H$5)) *VLOOKUP($D$5,EAD_Table[#All],MATCH("EAD",EAD_Table[#Headers],0),FALSE) *$F$5*(1+$A11))} -> 8.7908088 | E11: {=($F$6*(1+$A11)*'User Segmentation'!$I$49) -Dynamic_Row_Table[[Fixed Cost]:[Fixed Cost]] -(Dynamic_Row_Table[[Funding Rate]:[Funding Rate]]*Dynamic_Row_Table[[Tenure (in months)]:[Tenure (in months)]]*$F$6*(1+$A11)/12) -(IF($A11<0,'Dynamic CM'!$G$6,'Dynamic CM'!$G$6*(($F$6*(1+$A11)/$F$6)^'Dynamic CM'!$H$6)) *VLOOKUP($D$6,EAD_Table[#All],MATCH("EAD",EAD_Table[#Headers],0),FALSE) *$F$6*(1+$A11))} -> 0.15879975 | Q11: -0.7 | R11: {=($F$3*(1+$Q11)*'User Segmentation'!$I$49) -Dynamic_Row_Table[[Fixed Cost]:[Fixed Cost]] -(Dynamic_Row_Table[[Funding Rate]:[Funding Rate]]*Dynamic_Row_Table[[Tenure (in months)]:[Tenure (in months)]]*$F$3*(1+$Q11)/12) -(IF($Q11<0,'Dynamic CM'!$G$3,'Dynamic CM'!$G$3*(($F$3*(1+$Q11)/$F$3)^'Dynamic CM'!$H$3)) *VLOOKUP($D$3,EAD_Table[#All],MATCH("EAD",EAD_Table[#Headers],0),FALSE) *$F$3*(1+$Q11))} -> -2.766312 | S11: {=($F$4*(1+$Q11)*'User Segmentation'!$I$49) -Dynamic_Row_Table[[Fixed Cost]:[Fixed Cost]] -(Dynamic_Row_Table[[Funding Rate]:[Funding Rate]]*Dynamic_Row_Table[[Tenure (in months)]:[Tenure (in months)]]*$F$4*(1+$Q11)/12) -(IF($Q11<0,'Dynamic CM'!$G$4,'Dynamic CM'!$G$4*(($F$4*(1+$Q11)/$F$4)^'Dynamic CM'!$H$4)) *VLOOKUP($D$4,EAD_Table[#All],MATCH("EAD",EAD_Table[#Headers],0),FALSE) *$F$4*(1+$Q11))} -> -1.0953357 | T11: {=($F$5*(1+$Q11)*'User Segmentation'!$I$49) -Dynamic_Row_Table[[Fixed Cost]:[Fixed Cost]] -(Dynamic_Row_Table[[Funding Rate]:[Funding Rate]]*Dynamic_Row_Table[[Tenure (in months)]:[Tenure (in months)]]*$F$5*(1+$Q11)/12) -(IF($Q11<0,'Dynamic CM'!$G$5,'Dynamic CM'!$G$5*(($F$5*(1+$Q11)/$F$5)^'Dynamic CM'!$H$5)) *VLOOKUP($D$5,EAD_Table[#All],MATCH("EAD",EAD_Table[#Headers],0),FALSE) *$F$5*(1+$Q11))} -> 1.7163235 | U11: {=($F$6*(1+$Q11)*'User Segmentation'!$I$49) -Dynamic_Row_Table[[Fixed Cost]:[Fixed Cost]] -(Dynamic_Row_Table[[Funding Rate]:[Funding Rate]]*Dynamic_Row_Table[[Tenure (in months)]:[Tenure (in months)]]*$F$6*(1+$Q11)/12) -(IF($Q11<0,'Dynamic CM'!$G$6,'Dynamic CM'!$G$6*(($F$6*(1+$Q11)/$F$6)^'Dynamic CM'!$H$6)) *VLOOKUP($D$6,EAD_Table[#All],MATCH("EAD",EAD_Table[#Headers],0),FALSE) *$F$6*(1+$Q11))} -> -1.7364801
A12: 0 | B12: {=($F$3*(1+$A12)*'User Segmentation'!$I$49) -Dynamic_Row_Table[[Fixed Cost]:[Fixed Cost]] -(Dynamic_Row_Table[[Funding Rate]:[Funding Rate]]*Dynamic_Row_Table[[Tenure (in months)]:[Tenure (in months)]]*$F$3*(1+$A12)/12) -(IF($A12<0,'Dynamic CM'!$G$3,'Dynamic CM'!$G$3*(($F$3*(1+$A12)/$F$3)^'Dynamic CM'!$H$3)) *VLOOKUP($D$3,EAD_Table[#All],MATCH("EAD",EAD_Table[#Headers],0),FALSE) *$F$3*(1+$A12))} -> -2.2210399 | C12: {=($F$4*(1+$A12)*'User Segmentation'!$I$49) -Dynamic_Row_Table[[Fixed Cost]:[Fixed Cost]] -(Dynamic_Row_Table[[Funding Rate]:[Funding Rate]]*Dynamic_Row_Table[[Tenure (in months)]:[Tenure (in months)]]*$F$4*(1+$A12)/12) -(IF($A12<0,'Dynamic CM'!$G$4,'Dynamic CM'!$G$4*(($F$4*(1+$A12)/$F$4)^'Dynamic CM'!$H$4)) *VLOOKUP($D$4,EAD_Table[#All],MATCH("EAD",EAD_Table[#Headers],0),FALSE) *$F$4*(1+$A12))} -> 3.3488811 | D12: {=($F$5*(1+$A12)*'User Segmentation'!$I$49) -Dynamic_Row_Table[[Fixed Cost]:[Fixed Cost]] -(Dynamic_Row_Table[[Funding Rate]:[Funding Rate]]*Dynamic_Row_Table[[Tenure (in months)]:[Tenure (in months)]]*$F$5*(1+$A12)/12) -(IF($A12<0,'Dynamic CM'!$G$5,'Dynamic CM'!$G$5*(($F$5*(1+$A12)/$F$5)^'Dynamic CM'!$H$5)) *VLOOKUP($D$5,EAD_Table[#All],MATCH("EAD",EAD_Table[#Headers],0),FALSE) *$F$5*(1+$A12))} -> 12.721078 | E12: {=($F$6*(1+$A12)*'User Segmentation'!$I$49) -Dynamic_Row_Table[[Fixed Cost]:[Fixed Cost]] -(Dynamic_Row_Table[[Funding Rate]:[Funding Rate]]*Dynamic_Row_Table[[Tenure (in months)]:[Tenure (in months)]]*$F$6*(1+$A12)/12) -(IF($A12<0,'Dynamic CM'!$G$6,'Dynamic CM'!$G$6*(($F$6*(1+$A12)/$F$6)^'Dynamic CM'!$H$6)) *VLOOKUP($D$6,EAD_Table[#All],MATCH("EAD",EAD_Table[#Headers],0),FALSE) *$F$6*(1+$A12))} -> 1.211733 | Q12: -0.6 | R12: {=($F$3*(1+$Q12)*'User Segmentation'!$I$49) -Dynamic_Row_Table[[Fixed Cost]:[Fixed Cost]] -(Dynamic_Row_Table[[Funding Rate]:[Funding Rate]]*Dynamic_Row_Table[[Tenure (in months)]:[Tenure (in months)]]*$F$3*(1+$Q12)/12) -(IF($Q12<0,'Dynamic CM'!$G$3,'Dynamic CM'!$G$3*(($F$3*(1+$Q12)/$F$3)^'Dynamic CM'!$H$3)) *VLOOKUP($D$3,EAD_Table[#All],MATCH("EAD",EAD_Table[#Headers],0),FALSE) *$F$3*(1+$Q12))} -> -2.6884159 | S12: {=($F$4*(1+$Q12)*'User Segmentation'!$I$49) -Dynamic_Row_Table[[Fixed Cost]:[Fixed Cost]] -(Dynamic_Row_Table[[Funding Rate]:[Funding Rate]]*Dynamic_Row_Table[[Tenure (in months)]:[Tenure (in months)]]*$F$4*(1+$Q12)/12) -(IF($Q12<0,'Dynamic CM'!$G$4,'Dynamic CM'!$G$4*(($F$4*(1+$Q12)/$F$4)^'Dynamic CM'!$H$4)) *VLOOKUP($D$4,EAD_Table[#All],MATCH("EAD",EAD_Table[#Headers],0),FALSE) *$F$4*(1+$Q12))} -> -0.46044757 | T12: {=($F$5*(1+$Q12)*'User Segmentation'!$I$49) -Dynamic_Row_Table[[Fixed Cost]:[Fixed Cost]] -(Dynamic_Row_Table[[Funding Rate]:[Funding Rate]]*Dynamic_Row_Table[[Tenure (in months)]:[Tenure (in months)]]*$F$5*(1+$Q12)/12) -(IF($Q12<0,'Dynamic CM'!$G$5,'Dynamic CM'!$G$5*(($F$5*(1+$Q12)/$F$5)^'Dynamic CM'!$H$5)) *VLOOKUP($D$5,EAD_Table[#All],MATCH("EAD",EAD_Table[#Headers],0),FALSE) *$F$5*(1+$Q12))} -> 3.2884313 | U12: {=($F$6*(1+$Q12)*'User Segmentation'!$I$49) -Dynamic_Row_Table[[Fixed Cost]:[Fixed Cost]] -(Dynamic_Row_Table[[Funding Rate]:[Funding Rate]]*Dynamic_Row_Table[[Tenure (in months)]:[Tenure (in months)]]*$F$6*(1+$Q12)/12) -(IF($Q12<0,'Dynamic CM'!$G$6,'Dynamic CM'!$G$6*(($F$6*(1+$Q12)/$F$6)^'Dynamic CM'!$H$6)) *VLOOKUP($D$6,EAD_Table[#All],MATCH("EAD",EAD_Table[#Headers],0),FALSE) *$F$6*(1+$Q12))} -> -1.3153068
A13: 0.25 | B13: {=($F$3*(1+$A13)*'User Segmentation'!$I$49) -Dynamic_Row_Table[[Fixed Cost]:[Fixed Cost]] -(Dynamic_Row_Table[[Funding Rate]:[Funding Rate]]*Dynamic_Row_Table[[Tenure (in months)]:[Tenure (in months)]]*$F$3*(1+$A13)/12) -(IF($A13<0,'Dynamic CM'!$G$3,'Dynamic CM'!$G$3*(($F$3*(1+$A13)/$F$3)^'Dynamic CM'!$H$3)) *VLOOKUP($D$3,EAD_Table[#All],MATCH("EAD",EAD_Table[#Headers],0),FALSE) *$F$3*(1+$A13))} -> -2.9494373 | C13: {=($F$4*(1+$A13)*'User Segmentation'!$I$49) -Dynamic_Row_Table[[Fixed Cost]:[Fixed Cost]] -(Dynamic_Row_Table[[Funding Rate]:[Funding Rate]]*Dynamic_Row_Table[[Tenure (in months)]:[Tenure (in months)]]*$F$4*(1+$A13)/12) -(IF($A13<0,'Dynamic CM'!$G$4,'Dynamic CM'!$G$4*(($F$4*(1+$A13)/$F$4)^'Dynamic CM'!$H$4)) *VLOOKUP($D$4,EAD_Table[#All],MATCH("EAD",EAD_Table[#Headers],0),FALSE) *$F$4*(1+$A13))} -> 4.5900323 | D13: {=($F$5*(1+$A13)*'User Segmentation'!$I$49) -Dynamic_Row_Table[[Fixed Cost]:[Fixed Cost]] -(Dynamic_Row_Table[[Funding Rate]:[Funding Rate]]*Dynamic_Row_Table[[Tenure (in months)]:[Tenure (in months)]]*$F$5*(1+$A13)/12) -(IF($A13<0,'Dynamic CM'!$G$5,'Dynamic CM'!$G$5*(($F$5*(1+$A13)/$F$5)^'Dynamic CM'!$H$5)) *VLOOKUP($D$5,EAD_Table[#All],MATCH("EAD",EAD_Table[#Headers],0),FALSE) *$F$5*(1+$A13))} -> 16.108335 | E13: {=($F$6*(1+$A13)*'User Segmentation'!$I$49) -Dynamic_Row_Table[[Fixed Cost]:[Fixed Cost]] -(Dynamic_Row_Table[[Funding Rate]:[Funding Rate]]*Dynamic_Row_Table[[Tenure (in months)]:[Tenure (in months)]]*$F$6*(1+$A13)/12) -(IF($A13<0,'Dynamic CM'!$G$6,'Dynamic CM'!$G$6*(($F$6*(1+$A13)/$F$6)^'Dynamic CM'!$H$6)) *VLOOKUP($D$6,EAD_Table[#All],MATCH("EAD",EAD_Table[#Headers],0),FALSE) *$F$6*(1+$A13))} -> 2.0250874 | Q13: -0.5 | R13: {=($F$3*(1+$Q13)*'User Segmentation'!$I$49) -Dynamic_Row_Table[[Fixed Cost]:[Fixed Cost]] -(Dynamic_Row_Table[[Funding Rate]:[Funding Rate]]*Dynamic_Row_Table[[Tenure (in months)]:[Tenure (in months)]]*$F$3*(1+$Q13)/12) -(IF($Q13<0,'Dynamic CM'!$G$3,'Dynamic CM'!$G$3*(($F$3*(1+$Q13)/$F$3)^'Dynamic CM'!$H$3)) *VLOOKUP($D$3,EAD_Table[#All],MATCH("EAD",EAD_Table[#Headers],0),FALSE) *$F$3*(1+$Q13))} -> -2.6105199 | S13: {=($F$4*(1+$Q13)*'User Segmentation'!$I$49) -Dynamic_Row_Table[[Fixed Cost]:[Fixed Cost]] -(Dynamic_Row_Table[[Funding Rate]:[Funding Rate]]*Dynamic_Row_Table[[Tenure (in months)]:[Tenure (in months)]]*$F$4*(1+$Q13)/12) -(IF($Q13<0,'Dynamic CM'!$G$4,'Dynamic CM'!$G$4*(($F$4*(1+$Q13)/$F$4)^'Dynamic CM'!$H$4)) *VLOOKUP($D$4,EAD_Table[#All],MATCH("EAD",EAD_Table[#Headers],0),FALSE) *$F$4*(1+$Q13))} -> 0.17444053 | T13: {=($F$5*(1+$Q13)*'User Segmentation'!$I$49) -Dynamic_Row_Table[[Fixed Cost]:[Fixed Cost]] -(Dynamic_Row_Table[[Funding Rate]:[Funding Rate]]*Dynamic_Row_Table[[Tenure (in months)]:[Tenure (in months)]]*$F$5*(1+$Q13)/12) -(IF($Q13<0,'Dynamic CM'!$G$5,'Dynamic CM'!$G$5*(($F$5*(1+$Q13)/$F$5)^'Dynamic CM'!$H$5)) *VLOOKUP($D$5,EAD_Table[#All],MATCH("EAD",EAD_Table[#Headers],0),FALSE) *$F$5*(1+$Q13))} -> 4.8605392 | U13: {=($F$6*(1+$Q13)*'User Segmentation'!$I$49) -Dynamic_Row_Table[[Fixed Cost]:[Fixed Cost]] -(Dynamic_Row_Table[[Funding Rate]:[Funding Rate]]*Dynamic_Row_Table[[Tenure (in months)]:[Tenure (in months)]]*$F$6*(1+$Q13)/12) -(IF($Q13<0,'Dynamic CM'!$G$6,'Dynamic CM'!$G$6*(($F$6*(1+$Q13)/$F$6)^'Dynamic CM'!$H$6)) *VLOOKUP($D$6,EAD_Table[#All],MATCH("EAD",EAD_Table[#Headers],0),FALSE) *$F$6*(1+$Q13))} -> -0.8941335
A14: 0.5 | B14: {=($F$3*(1+$A14)*'User Segmentation'!$I$49) -Dynamic_Row_Table[[Fixed Cost]:[Fixed Cost]] -(Dynamic_Row_Table[[Funding Rate]:[Funding Rate]]*Dynamic_Row_Table[[Tenure (in months)]:[Tenure (in months)]]*$F$3*(1+$A14)/12) -(IF($A14<0,'Dynamic CM'!$G$3,'Dynamic CM'!$G$3*(($F$3*(1+$A14)/$F$3)^'Dynamic CM'!$H$3)) *VLOOKUP($D$3,EAD_Table[#All],MATCH("EAD",EAD_Table[#Headers],0),FALSE) *$F$3*(1+$A14))} -> -4.263789 | C14: {=($F$4*(1+$A14)*'User Segmentation'!$I$49) -Dynamic_Row_Table[[Fixed Cost]:[Fixed Cost]] -(Dynamic_Row_Table[[Funding Rate]:[Funding Rate]]*Dynamic_Row_Table[[Tenure (in months)]:[Tenure (in months)]]*$F$4*(1+$A14)/12) -(IF($A14<0,'Dynamic CM'!$G$4,'Dynamic CM'!$G$4*(($F$4*(1+$A14)/$F$4)^'Dynamic CM'!$H$4)) *VLOOKUP($D$4,EAD_Table[#All],MATCH("EAD",EAD_Table[#Headers],0),FALSE) *$F$4*(1+$A14))} -> 5.6651481 | D14: {=($F$5*(1+$A14)*'User Segmentation'!$I$49) -Dynamic_Row_Table[[Fixed Cost]:[Fixed Cost]] -(Dynamic_Row_Table[[Funding Rate]:[Funding Rate]]*Dynamic_Row_Table[[Tenure (in months)]:[Tenure (in months)]]*$F$5*(1+$A14)/12) -(IF($A14<0,'Dynamic CM'!$G$5,'Dynamic CM'!$G$5*(($F$5*(1+$A14)/$F$5)^'Dynamic CM'!$H$5)) *VLOOKUP($D$5,EAD_Table[#All],MATCH("EAD",EAD_Table[#Headers],0),FALSE) *$F$5*(1+$A14))} -> 19.269007 | E14: {=($F$6*(1+$A14)*'User Segmentation'!$I$49) -Dynamic_Row_Table[[Fixed Cost]:[Fixed Cost]] -(Dynamic_Row_Table[[Funding Rate]:[Funding Rate]]*Dynamic_Row_Table[[Tenure (in months)]:[Tenure (in months)]]*$F$6*(1+$A14)/12) -(IF($A14<0,'Dynamic CM'!$G$6,'Dynamic CM'!$G$6*(($F$6*(1+$A14)/$F$6)^'Dynamic CM'!$H$6)) *VLOOKUP($D$6,EAD_Table[#All],MATCH("EAD",EAD_Table[#Headers],0),FALSE) *$F$6*(1+$A14))} -> 2.7234976 | Q14: -0.4 | R14: {=($F$3*(1+$Q14)*'User Segmentation'!$I$49) -Dynamic_Row_Table[[Fixed Cost]:[Fixed Cost]] -(Dynamic_Row_Table[[Funding Rate]:[Funding Rate]]*Dynamic_Row_Table[[Tenure (in months)]:[Tenure (in months)]]*$F$3*(1+$Q14)/12) -(IF($Q14<0,'Dynamic CM'!$G$3,'Dynamic CM'!$G$3*(($F$3*(1+$Q14)/$F$3)^'Dynamic CM'!$H$3)) *VLOOKUP($D$3,EAD_Table[#All],MATCH("EAD",EAD_Table[#Headers],0),FALSE) *$F$3*(1+$Q14))} -> -2.5326239 | S14: {=($F$4*(1+$Q14)*'User Segmentation'!$I$49) -Dynamic_Row_Table[[Fixed Cost]:[Fixed Cost]] -(Dynamic_Row_Table[[Funding Rate]:[Funding Rate]]*Dynamic_Row_Table[[Tenure (in months)]:[Tenure (in months)]]*$F$4*(1+$Q14)/12) -(IF($Q14<0,'Dynamic CM'!$G$4,'Dynamic CM'!$G$4*(($F$4*(1+$Q14)/$F$4)^'Dynamic CM'!$H$4)) *VLOOKUP($D$4,EAD_Table[#All],MATCH("EAD",EAD_Table[#Headers],0),FALSE) *$F$4*(1+$Q14))} -> 0.80932864 | T14: {=($F$5*(1+$Q14)*'User Segmentation'!$I$49) -Dynamic_Row_Table[[Fixed Cost]:[Fixed Cost]] -(Dynamic_Row_Table[[Funding Rate]:[Funding Rate]]*Dynamic_Row_Table[[Tenure (in months)]:[Tenure (in months)]]*$F$5*(1+$Q14)/12) -(IF($Q14<0,'Dynamic CM'!$G$5,'Dynamic CM'!$G$5*(($F$5*(1+$Q14)/$F$5)^'Dynamic CM'!$H$5)) *VLOOKUP($D$5,EAD_Table[#All],MATCH("EAD",EAD_Table[#Headers],0),FALSE) *$F$5*(1+$Q14))} -> 6.432647 | U14: {=($F$6*(1+$Q14)*'User Segmentation'!$I$49) -Dynamic_Row_Table[[Fixed Cost]:[Fixed Cost]] -(Dynamic_Row_Table[[Funding Rate]:[Funding Rate]]*Dynamic_Row_Table[[Tenure (in months)]:[Tenure (in months)]]*$F$6*(1+$Q14)/12) -(IF($Q14<0,'Dynamic CM'!$G$6,'Dynamic CM'!$G$6*(($F$6*(1+$Q14)/$F$6)^'Dynamic CM'!$H$6)) *VLOOKUP($D$6,EAD_Table[#All],MATCH("EAD",EAD_Table[#Headers],0),FALSE) *$F$6*(1+$Q14))} -> -0.4729602 | Y14: ›
A15: 0.75 | B15: {=($F$3*(1+$A15)*'User Segmentation'!$I$49) -Dynamic_Row_Table[[Fixed Cost]:[Fixed Cost]] -(Dynamic_Row_Table[[Funding Rate]:[Funding Rate]]*Dynamic_Row_Table[[Tenure (in months)]:[Tenure (in months)]]*$F$3*(1+$A15)/12) -(IF($A15<0,'Dynamic CM'!$G$3,'Dynamic CM'!$G$3*(($F$3*(1+$A15)/$F$3)^'Dynamic CM'!$H$3)) *VLOOKUP($D$3,EAD_Table[#All],MATCH("EAD",EAD_Table[#Headers],0),FALSE) *$F$3*(1+$A15))} -> -6.2673937 | C15: {=($F$4*(1+$A15)*'User Segmentation'!$I$49) -Dynamic_Row_Table[[Fixed Cost]:[Fixed Cost]] -(Dynamic_Row_Table[[Funding Rate]:[Funding Rate]]*Dynamic_Row_Table[[Tenure (in months)]:[Tenure (in months)]]*$F$4*(1+$A15)/12) -(IF($A15<0,'Dynamic CM'!$G$4,'Dynamic CM'!$G$4*(($F$4*(1+$A15)/$F$4)^'Dynamic CM'!$H$4)) *VLOOKUP($D$4,EAD_Table[#All],MATCH("EAD",EAD_Table[#Headers],0),FALSE) *$F$4*(1+$A15))} -> 6.5642136 | D15: {=($F$5*(1+$A15)*'User Segmentation'!$I$49) -Dynamic_Row_Table[[Fixed Cost]:[Fixed Cost]] -(Dynamic_Row_Table[[Funding Rate]:[Funding Rate]]*Dynamic_Row_Table[[Tenure (in months)]:[Tenure (in months)]]*$F$5*(1+$A15)/12) -(IF($A15<0,'Dynamic CM'!$G$5,'Dynamic CM'!$G$5*(($F$5*(1+$A15)/$F$5)^'Dynamic CM'!$H$5)) *VLOOKUP($D$5,EAD_Table[#All],MATCH("EAD",EAD_Table[#Headers],0),FALSE) *$F$5*(1+$A15))} -> 22.200125 | E15: {=($F$6*(1+$A15)*'User Segmentation'!$I$49) -Dynamic_Row_Table[[Fixed Cost]:[Fixed Cost]] -(Dynamic_Row_Table[[Funding Rate]:[Funding Rate]]*Dynamic_Row_Table[[Tenure (in months)]:[Tenure (in months)]]*$F$6*(1+$A15)/12) -(IF($A15<0,'Dynamic CM'!$G$6,'Dynamic CM'!$G$6*(($F$6*(1+$A15)/$F$6)^'Dynamic CM'!$H$6)) *VLOOKUP($D$6,EAD_Table[#All],MATCH("EAD",EAD_Table[#Headers],0),FALSE) *$F$6*(1+$A15))} -> 3.3000306 | Q15: -0.3 | R15: {=($F$3*(1+$Q15)*'User Segmentation'!$I$49) -Dynamic_Row_Table[[Fixed Cost]:[Fixed Cost]] -(Dynamic_Row_Table[[Funding Rate]:[Funding Rate]]*Dynamic_Row_Table[[Tenure (in months)]:[Tenure (in months)]]*$F$3*(1+$Q15)/12) -(IF($Q15<0,'Dynamic CM'!$G$3,'Dynamic CM'!$G$3*(($F$3*(1+$Q15)/$F$3)^'Dynamic CM'!$H$3)) *VLOOKUP($D$3,EAD_Table[#All],MATCH("EAD",EAD_Table[#Headers],0),FALSE) *$F$3*(1+$Q15))} -> -2.4547279 | S15: {=($F$4*(1+$Q15)*'User Segmentation'!$I$49) -Dynamic_Row_Table[[Fixed Cost]:[Fixed Cost]] -(Dynamic_Row_Table[[Funding Rate]:[Funding Rate]]*Dynamic_Row_Table[[Tenure (in months)]:[Tenure (in months)]]*$F$4*(1+$Q15)/12) -(IF($Q15<0,'Dynamic CM'!$G$4,'Dynamic CM'!$G$4*(($F$4*(1+$Q15)/$F$4)^'Dynamic CM'!$H$4)) *VLOOKUP($D$4,EAD_Table[#All],MATCH("EAD",EAD_Table[#Headers],0),FALSE) *$F$4*(1+$Q15))} -> 1.4442167 | T15: {=($F$5*(1+$Q15)*'User Segmentation'!$I$49) -Dynamic_Row_Table[[Fixed Cost]:[Fixed Cost]] -(Dynamic_Row_Table[[Funding Rate]:[Funding Rate]]*Dynamic_Row_Table[[Tenure (in months)]:[Tenure (in months)]]*$F$5*(1+$Q15)/12) -(IF($Q15<0,'Dynamic CM'!$G$5,'Dynamic CM'!$G$5*(($F$5*(1+$Q15)/$F$5)^'Dynamic CM'!$H$5)) *VLOOKUP($D$5,EAD_Table[#All],MATCH("EAD",EAD_Table[#Headers],0),FALSE) *$F$5*(1+$Q15))} -> 8.0047549 | U15: {=($F$6*(1+$Q15)*'User Segmentation'!$I$49) -Dynamic_Row_Table[[Fixed Cost]:[Fixed Cost]] -(Dynamic_Row_Table[[Funding Rate]:[Funding Rate]]*Dynamic_Row_Table[[Tenure (in months)]:[Tenure (in months)]]*$F$6*(1+$Q15)/12) -(IF($Q15<0,'Dynamic CM'!$G$6,'Dynamic CM'!$G$6*(($F$6*(1+$Q15)/$F$6)^'Dynamic CM'!$H$6)) *VLOOKUP($D$6,EAD_Table[#All],MATCH("EAD",EAD_Table[#Headers],0),FALSE) *$F$6*(1+$Q15))} -> -0.051786896
A16: 1 | B16: {=($F$3*(1+$A16)*'User Segmentation'!$I$49) -Dynamic_Row_Table[[Fixed Cost]:[Fixed Cost]] -(Dynamic_Row_Table[[Funding Rate]:[Funding Rate]]*Dynamic_Row_Table[[Tenure (in months)]:[Tenure (in months)]]*$F$3*(1+$A16)/12) -(IF($A16<0,'Dynamic CM'!$G$3,'Dynamic CM'!$G$3*(($F$3*(1+$A16)/$F$3)^'Dynamic CM'!$H$3)) *VLOOKUP($D$3,EAD_Table[#All],MATCH("EAD",EAD_Table[#Headers],0),FALSE) *$F$3*(1+$A16))} -> -9.0616543 | C16: {=($F$4*(1+$A16)*'User Segmentation'!$I$49) -Dynamic_Row_Table[[Fixed Cost]:[Fixed Cost]] -(Dynamic_Row_Table[[Funding Rate]:[Funding Rate]]*Dynamic_Row_Table[[Tenure (in months)]:[Tenure (in months)]]*$F$4*(1+$A16)/12) -(IF($A16<0,'Dynamic CM'!$G$4,'Dynamic CM'!$G$4*(($F$4*(1+$A16)/$F$4)^'Dynamic CM'!$H$4)) *VLOOKUP($D$4,EAD_Table[#All],MATCH("EAD",EAD_Table[#Headers],0),FALSE) *$F$4*(1+$A16))} -> 7.2783022 | D16: {=($F$5*(1+$A16)*'User Segmentation'!$I$49) -Dynamic_Row_Table[[Fixed Cost]:[Fixed Cost]] -(Dynamic_Row_Table[[Funding Rate]:[Funding Rate]]*Dynamic_Row_Table[[Tenure (in months)]:[Tenure (in months)]]*$F$5*(1+$A16)/12) -(IF($A16<0,'Dynamic CM'!$G$5,'Dynamic CM'!$G$5*(($F$5*(1+$A16)/$F$5)^'Dynamic CM'!$H$5)) *VLOOKUP($D$5,EAD_Table[#All],MATCH("EAD",EAD_Table[#Headers],0),FALSE) *$F$5*(1+$A16))} -> 24.899155 | E16: {=($F$6*(1+$A16)*'User Segmentation'!$I$49) -Dynamic_Row_Table[[Fixed Cost]:[Fixed Cost]] -(Dynamic_Row_Table[[Funding Rate]:[Funding Rate]]*Dynamic_Row_Table[[Tenure (in months)]:[Tenure (in months)]]*$F$6*(1+$A16)/12) -(IF($A16<0,'Dynamic CM'!$G$6,'Dynamic CM'!$G$6*(($F$6*(1+$A16)/$F$6)^'Dynamic CM'!$H$6)) *VLOOKUP($D$6,EAD_Table[#All],MATCH("EAD",EAD_Table[#Headers],0),FALSE) *$F$6*(1+$A16))} -> 3.7485066 | Q16: -0.2 | R16: {=($F$3*(1+$Q16)*'User Segmentation'!$I$49) -Dynamic_Row_Table[[Fixed Cost]:[Fixed Cost]] -(Dynamic_Row_Table[[Funding Rate]:[Funding Rate]]*Dynamic_Row_Table[[Tenure (in months)]:[Tenure (in months)]]*$F$3*(1+$Q16)/12) -(IF($Q16<0,'Dynamic CM'!$G$3,'Dynamic CM'!$G$3*(($F$3*(1+$Q16)/$F$3)^'Dynamic CM'!$H$3)) *VLOOKUP($D$3,EAD_Table[#All],MATCH("EAD",EAD_Table[#Headers],0),FALSE) *$F$3*(1+$Q16))} -> -2.3768319 | S16: {=($F$4*(1+$Q16)*'User Segmentation'!$I$49) -Dynamic_Row_Table[[Fixed Cost]:[Fixed Cost]] -(Dynamic_Row_Table[[Funding Rate]:[Funding Rate]]*Dynamic_Row_Table[[Tenure (in months)]:[Tenure (in months)]]*$F$4*(1+$Q16)/12) -(IF($Q16<0,'Dynamic CM'!$G$4,'Dynamic CM'!$G$4*(($F$4*(1+$Q16)/$F$4)^'Dynamic CM'!$H$4)) *VLOOKUP($D$4,EAD_Table[#All],MATCH("EAD",EAD_Table[#Headers],0),FALSE) *$F$4*(1+$Q16))} -> 2.0791049 | T16: {=($F$5*(1+$Q16)*'User Segmentation'!$I$49) -Dynamic_Row_Table[[Fixed Cost]:[Fixed Cost]] -(Dynamic_Row_Table[[Funding Rate]:[Funding Rate]]*Dynamic_Row_Table[[Tenure (in months)]:[Tenure (in months)]]*$F$5*(1+$Q16)/12) -(IF($Q16<0,'Dynamic CM'!$G$5,'Dynamic CM'!$G$5*(($F$5*(1+$Q16)/$F$5)^'Dynamic CM'!$H$5)) *VLOOKUP($D$5,EAD_Table[#All],MATCH("EAD",EAD_Table[#Headers],0),FALSE) *$F$5*(1+$Q16))} -> 9.5768627 | U16: {=($F$6*(1+$Q16)*'User Segmentation'!$I$49) -Dynamic_Row_Table[[Fixed Cost]:[Fixed Cost]] -(Dynamic_Row_Table[[Funding Rate]:[Funding Rate]]*Dynamic_Row_Table[[Tenure (in months)]:[Tenure (in months)]]*$F$6*(1+$Q16)/12) -(IF($Q16<0,'Dynamic CM'!$G$6,'Dynamic CM'!$G$6*(($F$6*(1+$Q16)/$F$6)^'Dynamic CM'!$H$6)) *VLOOKUP($D$6,EAD_Table[#All],MATCH("EAD",EAD_Table[#Headers],0),FALSE) *$F$6*(1+$Q16))} -> 0.3693864
A17: 1.25 | B17: {=($F$3*(1+$A17)*'User Segmentation'!$I$49) -Dynamic_Row_Table[[Fixed Cost]:[Fixed Cost]] -(Dynamic_Row_Table[[Funding Rate]:[Funding Rate]]*Dynamic_Row_Table[[Tenure (in months)]:[Tenure (in months)]]*$F$3*(1+$A17)/12) -(IF($A17<0,'Dynamic CM'!$G$3,'Dynamic CM'!$G$3*(($F$3*(1+$A17)/$F$3)^'Dynamic CM'!$H$3)) *VLOOKUP($D$3,EAD_Table[#All],MATCH("EAD",EAD_Table[#Headers],0),FALSE) *$F$3*(1+$A17))} -> -12.746381 | C17: {=($F$4*(1+$A17)*'User Segmentation'!$I$49) -Dynamic_Row_Table[[Fixed Cost]:[Fixed Cost]] -(Dynamic_Row_Table[[Funding Rate]:[Funding Rate]]*Dynamic_Row_Table[[Tenure (in months)]:[Tenure (in months)]]*$F$4*(1+$A17)/12) -(IF($A17<0,'Dynamic CM'!$G$4,'Dynamic CM'!$G$4*(($F$4*(1+$A17)/$F$4)^'Dynamic CM'!$H$4)) *VLOOKUP($D$4,EAD_Table[#All],MATCH("EAD",EAD_Table[#Headers],0),FALSE) *$F$4*(1+$A17))} -> 7.7993214 | D17: {=($F$5*(1+$A17)*'User Segmentation'!$I$49) -Dynamic_Row_Table[[Fixed Cost]:[Fixed Cost]] -(Dynamic_Row_Table[[Funding Rate]:[Funding Rate]]*Dynamic_Row_Table[[Tenure (in months)]:[Tenure (in months)]]*$F$5*(1+$A17)/12) -(IF($A17<0,'Dynamic CM'!$G$5,'Dynamic CM'!$G$5*(($F$5*(1+$A17)/$F$5)^'Dynamic CM'!$H$5)) *VLOOKUP($D$5,EAD_Table[#All],MATCH("EAD",EAD_Table[#Headers],0),FALSE) *$F$5*(1+$A17))} -> 27.363879 | E17: {=($F$6*(1+$A17)*'User Segmentation'!$I$49) -Dynamic_Row_Table[[Fixed Cost]:[Fixed Cost]] -(Dynamic_Row_Table[[Funding Rate]:[Funding Rate]]*Dynamic_Row_Table[[Tenure (in months)]:[Tenure (in months)]]*$F$6*(1+$A17)/12) -(IF($A17<0,'Dynamic CM'!$G$6,'Dynamic CM'!$G$6*(($F$6*(1+$A17)/$F$6)^'Dynamic CM'!$H$6)) *VLOOKUP($D$6,EAD_Table[#All],MATCH("EAD",EAD_Table[#Headers],0),FALSE) *$F$6*(1+$A17))} -> 4.0633233 | Q17: -0.1 | R17: {=($F$3*(1+$Q17)*'User Segmentation'!$I$49) -Dynamic_Row_Table[[Fixed Cost]:[Fixed Cost]] -(Dynamic_Row_Table[[Funding Rate]:[Funding Rate]]*Dynamic_Row_Table[[Tenure (in months)]:[Tenure (in months)]]*$F$3*(1+$Q17)/12) -(IF($Q17<0,'Dynamic CM'!$G$3,'Dynamic CM'!$G$3*(($F$3*(1+$Q17)/$F$3)^'Dynamic CM'!$H$3)) *VLOOKUP($D$3,EAD_Table[#All],MATCH("EAD",EAD_Table[#Headers],0),FALSE) *$F$3*(1+$Q17))} -> -2.2989359 | S17: {=($F$4*(1+$Q17)*'User Segmentation'!$I$49) -Dynamic_Row_Table[[Fixed Cost]:[Fixed Cost]] -(Dynamic_Row_Table[[Funding Rate]:[Funding Rate]]*Dynamic_Row_Table[[Tenure (in months)]:[Tenure (in months)]]*$F$4*(1+$Q17)/12) -(IF($Q17<0,'Dynamic CM'!$G$4,'Dynamic CM'!$G$4*(($F$4*(1+$Q17)/$F$4)^'Dynamic CM'!$H$4)) *VLOOKUP($D$4,EAD_Table[#All],MATCH("EAD",EAD_Table[#Headers],0),FALSE) *$F$4*(1+$Q17))} -> 2.713993 | T17: {=($F$5*(1+$Q17)*'User Segmentation'!$I$49) -Dynamic_Row_Table[[Fixed Cost]:[Fixed Cost]] -(Dynamic_Row_Table[[Funding Rate]:[Funding Rate]]*Dynamic_Row_Table[[Tenure (in months)]:[Tenure (in months)]]*$F$5*(1+$Q17)/12) -(IF($Q17<0,'Dynamic CM'!$G$5,'Dynamic CM'!$G$5*(($F$5*(1+$Q17)/$F$5)^'Dynamic CM'!$H$5)) *VLOOKUP($D$5,EAD_Table[#All],MATCH("EAD",EAD_Table[#Headers],0),FALSE) *$F$5*(1+$Q17))} -> 11.148971 | U17: {=($F$6*(1+$Q17)*'User Segmentation'!$I$49) -Dynamic_Row_Table[[Fixed Cost]:[Fixed Cost]] -(Dynamic_Row_Table[[Funding Rate]:[Funding Rate]]*Dynamic_Row_Table[[Tenure (in months)]:[Tenure (in months)]]*$F$6*(1+$Q17)/12) -(IF($Q17<0,'Dynamic CM'!$G$6,'Dynamic CM'!$G$6*(($F$6*(1+$Q17)/$F$6)^'Dynamic CM'!$H$6)) *VLOOKUP($D$6,EAD_Table[#All],MATCH("EAD",EAD_Table[#Headers],0),FALSE) *$F$6*(1+$Q17))} -> 0.79055971
A18: 1.5 | B18: {=($F$3*(1+$A18)*'User Segmentation'!$I$49) -Dynamic_Row_Table[[Fixed Cost]:[Fixed Cost]] -(Dynamic_Row_Table[[Funding Rate]:[Funding Rate]]*Dynamic_Row_Table[[Tenure (in months)]:[Tenure (in months)]]*$F$3*(1+$A18)/12) -(IF($A18<0,'Dynamic CM'!$G$3,'Dynamic CM'!$G$3*(($F$3*(1+$A18)/$F$3)^'Dynamic CM'!$H$3)) *VLOOKUP($D$3,EAD_Table[#All],MATCH("EAD",EAD_Table[#Headers],0),FALSE) *$F$3*(1+$A18))} -> -17.420013 | C18: {=($F$4*(1+$A18)*'User Segmentation'!$I$49) -Dynamic_Row_Table[[Fixed Cost]:[Fixed Cost]] -(Dynamic_Row_Table[[Funding Rate]:[Funding Rate]]*Dynamic_Row_Table[[Tenure (in months)]:[Tenure (in months)]]*$F$4*(1+$A18)/12) -(IF($A18<0,'Dynamic CM'!$G$4,'Dynamic CM'!$G$4*(($F$4*(1+$A18)/$F$4)^'Dynamic CM'!$H$4)) *VLOOKUP($D$4,EAD_Table[#All],MATCH("EAD",EAD_Table[#Headers],0),FALSE) *$F$4*(1+$A18))} -> 8.1198437 | D18: {=($F$5*(1+$A18)*'User Segmentation'!$I$49) -Dynamic_Row_Table[[Fixed Cost]:[Fixed Cost]] -(Dynamic_Row_Table[[Funding Rate]:[Funding Rate]]*Dynamic_Row_Table[[Tenure (in months)]:[Tenure (in months)]]*$F$5*(1+$A18)/12) -(IF($A18<0,'Dynamic CM'!$G$5,'Dynamic CM'!$G$5*(($F$5*(1+$A18)/$F$5)^'Dynamic CM'!$H$5)) *VLOOKUP($D$5,EAD_Table[#All],MATCH("EAD",EAD_Table[#Headers],0),FALSE) *$F$5*(1+$A18))} -> 29.592325 | E18: {=($F$6*(1+$A18)*'User Segmentation'!$I$49) -Dynamic_Row_Table[[Fixed Cost]:[Fixed Cost]] -(Dynamic_Row_Table[[Funding Rate]:[Funding Rate]]*Dynamic_Row_Table[[Tenure (in months)]:[Tenure (in months)]]*$F$6*(1+$A18)/12) -(IF($A18<0,'Dynamic CM'!$G$6,'Dynamic CM'!$G$6*(($F$6*(1+$A18)/$F$6)^'Dynamic CM'!$H$6)) *VLOOKUP($D$6,EAD_Table[#All],MATCH("EAD",EAD_Table[#Headers],0),FALSE) *$F$6*(1+$A18))} -> 4.2393387 | Q18: 0 | R18: {=($F$3*(1+$Q18)*'User Segmentation'!$I$49) -Dynamic_Row_Table[[Fixed Cost]:[Fixed Cost]] -(Dynamic_Row_Table[[Funding Rate]:[Funding Rate]]*Dynamic_Row_Table[[Tenure (in months)]:[Tenure (in months)]]*$F$3*(1+$Q18)/12) -(IF($Q18<0,'Dynamic CM'!$G$3,'Dynamic CM'!$G$3*(($F$3*(1+$Q18)/$F$3)^'Dynamic CM'!$H$3)) *VLOOKUP($D$3,EAD_Table[#All],MATCH("EAD",EAD_Table[#Headers],0),FALSE) *$F$3*(1+$Q18))} -> -2.2210399 | S18: {=($F$4*(1+$Q18)*'User Segmentation'!$I$49) -Dynamic_Row_Table[[Fixed Cost]:[Fixed Cost]] -(Dynamic_Row_Table[[Funding Rate]:[Funding Rate]]*Dynamic_Row_Table[[Tenure (in months)]:[Tenure (in months)]]*$F$4*(1+$Q18)/12) -(IF($Q18<0,'Dynamic CM'!$G$4,'Dynamic CM'!$G$4*(($F$4*(1+$Q18)/$F$4)^'Dynamic CM'!$H$4)) *VLOOKUP($D$4,EAD_Table[#All],MATCH("EAD",EAD_Table[#Headers],0),FALSE) *$F$4*(1+$Q18))} -> 3.3488811 | T18: {=($F$5*(1+$Q18)*'User Segmentation'!$I$49) -Dynamic_Row_Table[[Fixed Cost]:[Fixed Cost]] -(Dynamic_Row_Table[[Funding Rate]:[Funding Rate]]*Dynamic_Row_Table[[Tenure (in months)]:[Tenure (in months)]]*$F$5*(1+$Q18)/12) -(IF($Q18<0,'Dynamic CM'!$G$5,'Dynamic CM'!$G$5*(($F$5*(1+$Q18)/$F$5)^'Dynamic CM'!$H$5)) *VLOOKUP($D$5,EAD_Table[#All],MATCH("EAD",EAD_Table[#Headers],0),FALSE) *$F$5*(1+$Q18))} -> 12.721078 | U18: {=($F$6*(1+$Q18)*'User Segmentation'!$I$49) -Dynamic_Row_Table[[Fixed Cost]:[Fixed Cost]] -(Dynamic_Row_Table[[Funding Rate]:[Funding Rate]]*Dynamic_Row_Table[[Tenure (in months)]:[Tenure (in months)]]*$F$6*(1+$Q18)/12) -(IF($Q18<0,'Dynamic CM'!$G$6,'Dynamic CM'!$G$6*(($F$6*(1+$Q18)/$F$6)^'Dynamic CM'!$H$6)) *VLOOKUP($D$6,EAD_Table[#All],MATCH("EAD",EAD_Table[#Headers],0),FALSE) *$F$6*(1+$Q18))} -> 1.211733
A19: 1.75 | B19: {=($F$3*(1+$A19)*'User Segmentation'!$I$49) -Dynamic_Row_Table[[Fixed Cost]:[Fixed Cost]] -(Dynamic_Row_Table[[Funding Rate]:[Funding Rate]]*Dynamic_Row_Table[[Tenure (in months)]:[Tenure (in months)]]*$F$3*(1+$A19)/12) -(IF($A19<0,'Dynamic CM'!$G$3,'Dynamic CM'!$G$3*(($F$3*(1+$A19)/$F$3)^'Dynamic CM'!$H$3)) *VLOOKUP($D$3,EAD_Table[#All],MATCH("EAD",EAD_Table[#Headers],0),FALSE) *$F$3*(1+$A19))} -> -23.179788 | C19: {=($F$4*(1+$A19)*'User Segmentation'!$I$49) -Dynamic_Row_Table[[Fixed Cost]:[Fixed Cost]] -(Dynamic_Row_Table[[Funding Rate]:[Funding Rate]]*Dynamic_Row_Table[[Tenure (in months)]:[Tenure (in months)]]*$F$4*(1+$A19)/12) -(IF($A19<0,'Dynamic CM'!$G$4,'Dynamic CM'!$G$4*(($F$4*(1+$A19)/$F$4)^'Dynamic CM'!$H$4)) *VLOOKUP($D$4,EAD_Table[#All],MATCH("EAD",EAD_Table[#Headers],0),FALSE) *$F$4*(1+$A19))} -> 8.232985 | D19: {=($F$5*(1+$A19)*'User Segmentation'!$I$49) -Dynamic_Row_Table[[Fixed Cost]:[Fixed Cost]] -(Dynamic_Row_Table[[Funding Rate]:[Funding Rate]]*Dynamic_Row_Table[[Tenure (in months)]:[Tenure (in months)]]*$F$5*(1+$A19)/12) -(IF($A19<0,'Dynamic CM'!$G$5,'Dynamic CM'!$G$5*(($F$5*(1+$A19)/$F$5)^'Dynamic CM'!$H$5)) *VLOOKUP($D$5,EAD_Table[#All],MATCH("EAD",EAD_Table[#Headers],0),FALSE) *$F$5*(1+$A19))} -> 31.582716 | E19: {=($F$6*(1+$A19)*'User Segmentation'!$I$49) -Dynamic_Row_Table[[Fixed Cost]:[Fixed Cost]] -(Dynamic_Row_Table[[Funding Rate]:[Funding Rate]]*Dynamic_Row_Table[[Tenure (in months)]:[Tenure (in months)]]*$F$6*(1+$A19)/12) -(IF($A19<0,'Dynamic CM'!$G$6,'Dynamic CM'!$G$6*(($F$6*(1+$A19)/$F$6)^'Dynamic CM'!$H$6)) *VLOOKUP($D$6,EAD_Table[#All],MATCH("EAD",EAD_Table[#Headers],0),FALSE) *$F$6*(1+$A19))} -> 4.271787 | Q19: 0.1 | R19: {=($F$3*(1+$Q19)*'User Segmentation'!$I$49) -Dynamic_Row_Table[[Fixed Cost]:[Fixed Cost]] -(Dynamic_Row_Table[[Funding Rate]:[Funding Rate]]*Dynamic_Row_Table[[Tenure (in months)]:[Tenure (in months)]]*$F$3*(1+$Q19)/12) -(IF($Q19<0,'Dynamic CM'!$G$3,'Dynamic CM'!$G$3*(($F$3*(1+$Q19)/$F$3)^'Dynamic CM'!$H$3)) *VLOOKUP($D$3,EAD_Table[#All],MATCH("EAD",EAD_Table[#Headers],0),FALSE) *$F$3*(1+$Q19))} -> -2.448786 | S19: {=($F$4*(1+$Q19)*'User Segmentation'!$I$49) -Dynamic_Row_Table[[Fixed Cost]:[Fixed Cost]] -(Dynamic_Row_Table[[Funding Rate]:[Funding Rate]]*Dynamic_Row_Table[[Tenure (in months)]:[Tenure (in months)]]*$F$4*(1+$Q19)/12) -(IF($Q19<0,'Dynamic CM'!$G$4,'Dynamic CM'!$G$4*(($F$4*(1+$Q19)/$F$4)^'Dynamic CM'!$H$4)) *VLOOKUP($D$4,EAD_Table[#All],MATCH("EAD",EAD_Table[#Headers],0),FALSE) *$F$4*(1+$Q19))} -> 3.8645691 | T19: {=($F$5*(1+$Q19)*'User Segmentation'!$I$49) -Dynamic_Row_Table[[Fixed Cost]:[Fixed Cost]] -(Dynamic_Row_Table[[Funding Rate]:[Funding Rate]]*Dynamic_Row_Table[[Tenure (in months)]:[Tenure (in months)]]*$F$5*(1+$Q19)/12) -(IF($Q19<0,'Dynamic CM'!$G$5,'Dynamic CM'!$G$5*(($F$5*(1+$Q19)/$F$5)^'Dynamic CM'!$H$5)) *VLOOKUP($D$5,EAD_Table[#All],MATCH("EAD",EAD_Table[#Headers],0),FALSE) *$F$5*(1+$Q19))} -> 14.102959 | U19: {=($F$6*(1+$Q19)*'User Segmentation'!$I$49) -Dynamic_Row_Table[[Fixed Cost]:[Fixed Cost]] -(Dynamic_Row_Table[[Funding Rate]:[Funding Rate]]*Dynamic_Row_Table[[Tenure (in months)]:[Tenure (in months)]]*$F$6*(1+$Q19)/12) -(IF($Q19<0,'Dynamic CM'!$G$6,'Dynamic CM'!$G$6*(($F$6*(1+$Q19)/$F$6)^'Dynamic CM'!$H$6)) *VLOOKUP($D$6,EAD_Table[#All],MATCH("EAD",EAD_Table[#Headers],0),FALSE) *$F$6*(1+$Q19))} -> 1.5503857
A20: 2 | B20: {=($F$3*(1+$A20)*'User Segmentation'!$I$49) -Dynamic_Row_Table[[Fixed Cost]:[Fixed Cost]] -(Dynamic_Row_Table[[Funding Rate]:[Funding Rate]]*Dynamic_Row_Table[[Tenure (in months)]:[Tenure (in months)]]*$F$3*(1+$A20)/12) -(IF($A20<0,'Dynamic CM'!$G$3,'Dynamic CM'!$G$3*(($F$3*(1+$A20)/$F$3)^'Dynamic CM'!$H$3)) *VLOOKUP($D$3,EAD_Table[#All],MATCH("EAD",EAD_Table[#Headers],0),FALSE) *$F$3*(1+$A20))} -> -30.121878 | C20: {=($F$4*(1+$A20)*'User Segmentation'!$I$49) -Dynamic_Row_Table[[Fixed Cost]:[Fixed Cost]] -(Dynamic_Row_Table[[Funding Rate]:[Funding Rate]]*Dynamic_Row_Table[[Tenure (in months)]:[Tenure (in months)]]*$F$4*(1+$A20)/12) -(IF($A20<0,'Dynamic CM'!$G$4,'Dynamic CM'!$G$4*(($F$4*(1+$A20)/$F$4)^'Dynamic CM'!$H$4)) *VLOOKUP($D$4,EAD_Table[#All],MATCH("EAD",EAD_Table[#Headers],0),FALSE) *$F$4*(1+$A20))} -> 8.1323163 | D20: {=($F$5*(1+$A20)*'User Segmentation'!$I$49) -Dynamic_Row_Table[[Fixed Cost]:[Fixed Cost]] -(Dynamic_Row_Table[[Funding Rate]:[Funding Rate]]*Dynamic_Row_Table[[Tenure (in months)]:[Tenure (in months)]]*$F$5*(1+$A20)/12) -(IF($A20<0,'Dynamic CM'!$G$5,'Dynamic CM'!$G$5*(($F$5*(1+$A20)/$F$5)^'Dynamic CM'!$H$5)) *VLOOKUP($D$5,EAD_Table[#All],MATCH("EAD",EAD_Table[#Headers],0),FALSE) *$F$5*(1+$A20))} -> 33.333433 | E20: {=($F$6*(1+$A20)*'User Segmentation'!$I$49) -Dynamic_Row_Table[[Fixed Cost]:[Fixed Cost]] -(Dynamic_Row_Table[[Funding Rate]:[Funding Rate]]*Dynamic_Row_Table[[Tenure (in months)]:[Tenure (in months)]]*$F$6*(1+$A20)/12) -(IF($A20<0,'Dynamic CM'!$G$6,'Dynamic CM'!$G$6*(($F$6*(1+$A20)/$F$6)^'Dynamic CM'!$H$6)) *VLOOKUP($D$6,EAD_Table[#All],MATCH("EAD",EAD_Table[#Headers],0),FALSE) *$F$6*(1+$A20))} -> 4.1562175 | Q20: 0.2 | R20: {=($F$3*(1+$Q20)*'User Segmentation'!$I$49) -Dynamic_Row_Table[[Fixed Cost]:[Fixed Cost]] -(Dynamic_Row_Table[[Funding Rate]:[Funding Rate]]*Dynamic_Row_Table[[Tenure (in months)]:[Tenure (in months)]]*$F$3*(1+$Q20)/12) -(IF($Q20<0,'Dynamic CM'!$G$3,'Dynamic CM'!$G$3*(($F$3*(1+$Q20)/$F$3)^'Dynamic CM'!$H$3)) *VLOOKUP($D$3,EAD_Table[#All],MATCH("EAD",EAD_Table[#Headers],0),FALSE) *$F$3*(1+$Q20))} -> -2.7602247 | S20: {=($F$4*(1+$Q20)*'User Segmentation'!$I$49) -Dynamic_Row_Table[[Fixed Cost]:[Fixed Cost]] -(Dynamic_Row_Table[[Funding Rate]:[Funding Rate]]*Dynamic_Row_Table[[Tenure (in months)]:[Tenure (in months)]]*$F$4*(1+$Q20)/12) -(IF($Q20<0,'Dynamic CM'!$G$4,'Dynamic CM'!$G$4*(($F$4*(1+$Q20)/$F$4)^'Dynamic CM'!$H$4)) *VLOOKUP($D$4,EAD_Table[#All],MATCH("EAD",EAD_Table[#Headers],0),FALSE) *$F$4*(1+$Q20))} -> 4.3547415 | T20: {=($F$5*(1+$Q20)*'User Segmentation'!$I$49) -Dynamic_Row_Table[[Fixed Cost]:[Fixed Cost]] -(Dynamic_Row_Table[[Funding Rate]:[Funding Rate]]*Dynamic_Row_Table[[Tenure (in months)]:[Tenure (in months)]]*$F$5*(1+$Q20)/12) -(IF($Q20<0,'Dynamic CM'!$G$5,'Dynamic CM'!$G$5*(($F$5*(1+$Q20)/$F$5)^'Dynamic CM'!$H$5)) *VLOOKUP($D$5,EAD_Table[#All],MATCH("EAD",EAD_Table[#Headers],0),FALSE) *$F$5*(1+$Q20))} -> 15.448906 | U20: {=($F$6*(1+$Q20)*'User Segmentation'!$I$49) -Dynamic_Row_Table[[Fixed Cost]:[Fixed Cost]] -(Dynamic_Row_Table[[Funding Rate]:[Funding Rate]]*Dynamic_Row_Table[[Tenure (in months)]:[Tenure (in months)]]*$F$6*(1+$Q20)/12) -(IF($Q20<0,'Dynamic CM'!$G$6,'Dynamic CM'!$G$6*(($F$6*(1+$Q20)/$F$6)^'Dynamic CM'!$H$6)) *VLOOKUP($D$6,EAD_Table[#All],MATCH("EAD",EAD_Table[#Headers],0),FALSE) *$F$6*(1+$Q20))} -> 1.8713743
A21: 2.25 | B21: {=($F$3*(1+$A21)*'User Segmentation'!$I$49) -Dynamic_Row_Table[[Fixed Cost]:[Fixed Cost]] -(Dynamic_Row_Table[[Funding Rate]:[Funding Rate]]*Dynamic_Row_Table[[Tenure (in months)]:[Tenure (in months)]]*$F$3*(1+$A21)/12) -(IF($A21<0,'Dynamic CM'!$G$3,'Dynamic CM'!$G$3*(($F$3*(1+$A21)/$F$3)^'Dynamic CM'!$H$3)) *VLOOKUP($D$3,EAD_Table[#All],MATCH("EAD",EAD_Table[#Headers],0),FALSE) *$F$3*(1+$A21))} -> -38.341492 | C21: {=($F$4*(1+$A21)*'User Segmentation'!$I$49) -Dynamic_Row_Table[[Fixed Cost]:[Fixed Cost]] -(Dynamic_Row_Table[[Funding Rate]:[Funding Rate]]*Dynamic_Row_Table[[Tenure (in months)]:[Tenure (in months)]]*$F$4*(1+$A21)/12) -(IF($A21<0,'Dynamic CM'!$G$4,'Dynamic CM'!$G$4*(($F$4*(1+$A21)/$F$4)^'Dynamic CM'!$H$4)) *VLOOKUP($D$4,EAD_Table[#All],MATCH("EAD",EAD_Table[#Headers],0),FALSE) *$F$4*(1+$A21))} -> 7.8117952 | D21: {=($F$5*(1+$A21)*'User Segmentation'!$I$49) -Dynamic_Row_Table[[Fixed Cost]:[Fixed Cost]] -(Dynamic_Row_Table[[Funding Rate]:[Funding Rate]]*Dynamic_Row_Table[[Tenure (in months)]:[Tenure (in months)]]*$F$5*(1+$A21)/12) -(IF($A21<0,'Dynamic CM'!$G$5,'Dynamic CM'!$G$5*(($F$5*(1+$A21)/$F$5)^'Dynamic CM'!$H$5)) *VLOOKUP($D$5,EAD_Table[#All],MATCH("EAD",EAD_Table[#Headers],0),FALSE) *$F$5*(1+$A21))} -> 34.84299 | E21: {=($F$6*(1+$A21)*'User Segmentation'!$I$49) -Dynamic_Row_Table[[Fixed Cost]:[Fixed Cost]] -(Dynamic_Row_Table[[Funding Rate]:[Funding Rate]]*Dynamic_Row_Table[[Tenure (in months)]:[Tenure (in months)]]*$F$6*(1+$A21)/12) -(IF($A21<0,'Dynamic CM'!$G$6,'Dynamic CM'!$G$6*(($F$6*(1+$A21)/$F$6)^'Dynamic CM'!$H$6)) *VLOOKUP($D$6,EAD_Table[#All],MATCH("EAD",EAD_Table[#Headers],0),FALSE) *$F$6*(1+$A21))} -> 3.8884473 | Q21: 0.3 | R21: {=($F$3*(1+$Q21)*'User Segmentation'!$I$49) -Dynamic_Row_Table[[Fixed Cost]:[Fixed Cost]] -(Dynamic_Row_Table[[Funding Rate]:[Funding Rate]]*Dynamic_Row_Table[[Tenure (in months)]:[Tenure (in months)]]*$F$3*(1+$Q21)/12) -(IF($Q21<0,'Dynamic CM'!$G$3,'Dynamic CM'!$G$3*(($F$3*(1+$Q21)/$F$3)^'Dynamic CM'!$H$3)) *VLOOKUP($D$3,EAD_Table[#All],MATCH("EAD",EAD_Table[#Headers],0),FALSE) *$F$3*(1+$Q21))} -> -3.1620954 | S21: {=($F$4*(1+$Q21)*'User Segmentation'!$I$49) -Dynamic_Row_Table[[Fixed Cost]:[Fixed Cost]] -(Dynamic_Row_Table[[Funding Rate]:[Funding Rate]]*Dynamic_Row_Table[[Tenure (in months)]:[Tenure (in months)]]*$F$4*(1+$Q21)/12) -(IF($Q21<0,'Dynamic CM'!$G$4,'Dynamic CM'!$G$4*(($F$4*(1+$Q21)/$F$4)^'Dynamic CM'!$H$4)) *VLOOKUP($D$4,EAD_Table[#All],MATCH("EAD",EAD_Table[#Headers],0),FALSE) *$F$4*(1+$Q21))} -> 4.8186771 | T21: {=($F$5*(1+$Q21)*'User Segmentation'!$I$49) -Dynamic_Row_Table[[Fixed Cost]:[Fixed Cost]] -(Dynamic_Row_Table[[Funding Rate]:[Funding Rate]]*Dynamic_Row_Table[[Tenure (in months)]:[Tenure (in months)]]*$F$5*(1+$Q21)/12) -(IF($Q21<0,'Dynamic CM'!$G$5,'Dynamic CM'!$G$5*(($F$5*(1+$Q21)/$F$5)^'Dynamic CM'!$H$5)) *VLOOKUP($D$5,EAD_Table[#All],MATCH("EAD",EAD_Table[#Headers],0),FALSE) *$F$5*(1+$Q21))} -> 16.758699 | U21: {=($F$6*(1+$Q21)*'User Segmentation'!$I$49) -Dynamic_Row_Table[[Fixed Cost]:[Fixed Cost]] -(Dynamic_Row_Table[[Funding Rate]:[Funding Rate]]*Dynamic_Row_Table[[Tenure (in months)]:[Tenure (in months)]]*$F$6*(1+$Q21)/12) -(IF($Q21<0,'Dynamic CM'!$G$6,'Dynamic CM'!$G$6*(($F$6*(1+$Q21)/$F$6)^'Dynamic CM'!$H$6)) *VLOOKUP($D$6,EAD_Table[#All],MATCH("EAD",EAD_Table[#Headers],0),FALSE) *$F$6*(1+$Q21))} -> 2.1741995
A22: 2.5 | B22: {=($F$3*(1+$A22)*'User Segmentation'!$I$49) -Dynamic_Row_Table[[Fixed Cost]:[Fixed Cost]] -(Dynamic_Row_Table[[Funding Rate]:[Funding Rate]]*Dynamic_Row_Table[[Tenure (in months)]:[Tenure (in months)]]*$F$3*(1+$A22)/12) -(IF($A22<0,'Dynamic CM'!$G$3,'Dynamic CM'!$G$3*(($F$3*(1+$A22)/$F$3)^'Dynamic CM'!$H$3)) *VLOOKUP($D$3,EAD_Table[#All],MATCH("EAD",EAD_Table[#Headers],0),FALSE) *$F$3*(1+$A22))} -> -47.932972 | C22: {=($F$4*(1+$A22)*'User Segmentation'!$I$49) -Dynamic_Row_Table[[Fixed Cost]:[Fixed Cost]] -(Dynamic_Row_Table[[Funding Rate]:[Funding Rate]]*Dynamic_Row_Table[[Tenure (in months)]:[Tenure (in months)]]*$F$4*(1+$A22)/12) -(IF($A22<0,'Dynamic CM'!$G$4,'Dynamic CM'!$G$4*(($F$4*(1+$A22)/$F$4)^'Dynamic CM'!$H$4)) *VLOOKUP($D$4,EAD_Table[#All],MATCH("EAD",EAD_Table[#Headers],0),FALSE) *$F$4*(1+$A22))} -> 7.2657137 | D22: {=($F$5*(1+$A22)*'User Segmentation'!$I$49) -Dynamic_Row_Table[[Fixed Cost]:[Fixed Cost]] -(Dynamic_Row_Table[[Funding Rate]:[Funding Rate]]*Dynamic_Row_Table[[Tenure (in months)]:[Tenure (in months)]]*$F$5*(1+$A22)/12) -(IF($A22<0,'Dynamic CM'!$G$5,'Dynamic CM'!$G$5*(($F$5*(1+$A22)/$F$5)^'Dynamic CM'!$H$5)) *VLOOKUP($D$5,EAD_Table[#All],MATCH("EAD",EAD_Table[#Headers],0),FALSE) *$F$5*(1+$A22))} -> 36.11001 | E22: {=($F$6*(1+$A22)*'User Segmentation'!$I$49) -Dynamic_Row_Table[[Fixed Cost]:[Fixed Cost]] -(Dynamic_Row_Table[[Funding Rate]:[Funding Rate]]*Dynamic_Row_Table[[Tenure (in months)]:[Tenure (in months)]]*$F$6*(1+$A22)/12) -(IF($A22<0,'Dynamic CM'!$G$6,'Dynamic CM'!$G$6*(($F$6*(1+$A22)/$F$6)^'Dynamic CM'!$H$6)) *VLOOKUP($D$6,EAD_Table[#All],MATCH("EAD",EAD_Table[#Headers],0),FALSE) *$F$6*(1+$A22))} -> 3.4645246 | Q22: 0.4 | R22: {=($F$3*(1+$Q22)*'User Segmentation'!$I$49) -Dynamic_Row_Table[[Fixed Cost]:[Fixed Cost]] -(Dynamic_Row_Table[[Funding Rate]:[Funding Rate]]*Dynamic_Row_Table[[Tenure (in months)]:[Tenure (in months)]]*$F$3*(1+$Q22)/12) -(IF($Q22<0,'Dynamic CM'!$G$3,'Dynamic CM'!$G$3*(($F$3*(1+$Q22)/$F$3)^'Dynamic CM'!$H$3)) *VLOOKUP($D$3,EAD_Table[#All],MATCH("EAD",EAD_Table[#Headers],0),FALSE) *$F$3*(1+$Q22))} -> -3.6610763 | S22: {=($F$4*(1+$Q22)*'User Segmentation'!$I$49) -Dynamic_Row_Table[[Fixed Cost]:[Fixed Cost]] -(Dynamic_Row_Table[[Funding Rate]:[Funding Rate]]*Dynamic_Row_Table[[Tenure (in months)]:[Tenure (in months)]]*$F$4*(1+$Q22)/12) -(IF($Q22<0,'Dynamic CM'!$G$4,'Dynamic CM'!$G$4*(($F$4*(1+$Q22)/$F$4)^'Dynamic CM'!$H$4)) *VLOOKUP($D$4,EAD_Table[#All],MATCH("EAD",EAD_Table[#Headers],0),FALSE) *$F$4*(1+$Q22))} -> 5.2556948 | T22: {=($F$5*(1+$Q22)*'User Segmentation'!$I$49) -Dynamic_Row_Table[[Fixed Cost]:[Fixed Cost]] -(Dynamic_Row_Table[[Funding Rate]:[Funding Rate]]*Dynamic_Row_Table[[Tenure (in months)]:[Tenure (in months)]]*$F$5*(1+$Q22)/12) -(IF($Q22<0,'Dynamic CM'!$G$5,'Dynamic CM'!$G$5*(($F$5*(1+$Q22)/$F$5)^'Dynamic CM'!$H$5)) *VLOOKUP($D$5,EAD_Table[#All],MATCH("EAD",EAD_Table[#Headers],0),FALSE) *$F$5*(1+$Q22))} -> 18.03213 | U22: {=($F$6*(1+$Q22)*'User Segmentation'!$I$49) -Dynamic_Row_Table[[Fixed Cost]:[Fixed Cost]] -(Dynamic_Row_Table[[Funding Rate]:[Funding Rate]]*Dynamic_Row_Table[[Tenure (in months)]:[Tenure (in months)]]*$F$6*(1+$Q22)/12) -(IF($Q22<0,'Dynamic CM'!$G$6,'Dynamic CM'!$G$6*(($F$6*(1+$Q22)/$F$6)^'Dynamic CM'!$H$6)) *VLOOKUP($D$6,EAD_Table[#All],MATCH("EAD",EAD_Table[#Headers],0),FALSE) *$F$6*(1+$Q22))} -> 2.4583897
A23: 2.75 | B23: {=($F$3*(1+$A23)*'User Segmentation'!$I$49) -Dynamic_Row_Table[[Fixed Cost]:[Fixed Cost]] -(Dynamic_Row_Table[[Funding Rate]:[Funding Rate]]*Dynamic_Row_Table[[Tenure (in months)]:[Tenure (in months)]]*$F$3*(1+$A23)/12) -(IF($A23<0,'Dynamic CM'!$G$3,'Dynamic CM'!$G$3*(($F$3*(1+$A23)/$F$3)^'Dynamic CM'!$H$3)) *VLOOKUP($D$3,EAD_Table[#All],MATCH("EAD",EAD_Table[#Headers],0),FALSE) *$F$3*(1+$A23))} -> -58.989859 | C23: {=($F$4*(1+$A23)*'User Segmentation'!$I$49) -Dynamic_Row_Table[[Fixed Cost]:[Fixed Cost]] -(Dynamic_Row_Table[[Funding Rate]:[Funding Rate]]*Dynamic_Row_Table[[Tenure (in months)]:[Tenure (in months)]]*$F$4*(1+$A23)/12) -(IF($A23<0,'Dynamic CM'!$G$4,'Dynamic CM'!$G$4*(($F$4*(1+$A23)/$F$4)^'Dynamic CM'!$H$4)) *VLOOKUP($D$4,EAD_Table[#All],MATCH("EAD",EAD_Table[#Headers],0),FALSE) *$F$4*(1+$A23))} -> 6.4886554 | D23: {=($F$5*(1+$A23)*'User Segmentation'!$I$49) -Dynamic_Row_Table[[Fixed Cost]:[Fixed Cost]] -(Dynamic_Row_Table[[Funding Rate]:[Funding Rate]]*Dynamic_Row_Table[[Tenure (in months)]:[Tenure (in months)]]*$F$5*(1+$A23)/12) -(IF($A23<0,'Dynamic CM'!$G$5,'Dynamic CM'!$G$5*(($F$5*(1+$A23)/$F$5)^'Dynamic CM'!$H$5)) *VLOOKUP($D$5,EAD_Table[#All],MATCH("EAD",EAD_Table[#Headers],0),FALSE) *$F$5*(1+$A23))} -> 37.133214 | E23: {=($F$6*(1+$A23)*'User Segmentation'!$I$49) -Dynamic_Row_Table[[Fixed Cost]:[Fixed Cost]] -(Dynamic_Row_Table[[Funding Rate]:[Funding Rate]]*Dynamic_Row_Table[[Tenure (in months)]:[Tenure (in months)]]*$F$6*(1+$A23)/12) -(IF($A23<0,'Dynamic CM'!$G$6,'Dynamic CM'!$G$6*(($F$6*(1+$A23)/$F$6)^'Dynamic CM'!$H$6)) *VLOOKUP($D$6,EAD_Table[#All],MATCH("EAD",EAD_Table[#Headers],0),FALSE) *$F$6*(1+$A23))} -> 2.8806997 | Q23: 0.5 | R23: {=($F$3*(1+$Q23)*'User Segmentation'!$I$49) -Dynamic_Row_Table[[Fixed Cost]:[Fixed Cost]] -(Dynamic_Row_Table[[Funding Rate]:[Funding Rate]]*Dynamic_Row_Table[[Tenure (in months)]:[Tenure (in months)]]*$F$3*(1+$Q23)/12) -(IF($Q23<0,'Dynamic CM'!$G$3,'Dynamic CM'!$G$3*(($F$3*(1+$Q23)/$F$3)^'Dynamic CM'!$H$3)) *VLOOKUP($D$3,EAD_Table[#All],MATCH("EAD",EAD_Table[#Headers],0),FALSE) *$F$3*(1+$Q23))} -> -4.263789 | S23: {=($F$4*(1+$Q23)*'User Segmentation'!$I$49) -Dynamic_Row_Table[[Fixed Cost]:[Fixed Cost]] -(Dynamic_Row_Table[[Funding Rate]:[Funding Rate]]*Dynamic_Row_Table[[Tenure (in months)]:[Tenure (in months)]]*$F$4*(1+$Q23)/12) -(IF($Q23<0,'Dynamic CM'!$G$4,'Dynamic CM'!$G$4*(($F$4*(1+$Q23)/$F$4)^'Dynamic CM'!$H$4)) *VLOOKUP($D$4,EAD_Table[#All],MATCH("EAD",EAD_Table[#Headers],0),FALSE) *$F$4*(1+$Q23))} -> 5.6651481 | T23: {=($F$5*(1+$Q23)*'User Segmentation'!$I$49) -Dynamic_Row_Table[[Fixed Cost]:[Fixed Cost]] -(Dynamic_Row_Table[[Funding Rate]:[Funding Rate]]*Dynamic_Row_Table[[Tenure (in months)]:[Tenure (in months)]]*$F$5*(1+$Q23)/12) -(IF($Q23<0,'Dynamic CM'!$G$5,'Dynamic CM'!$G$5*(($F$5*(1+$Q23)/$F$5)^'Dynamic CM'!$H$5)) *VLOOKUP($D$5,EAD_Table[#All],MATCH("EAD",EAD_Table[#Headers],0),FALSE) *$F$5*(1+$Q23))} -> 19.269007 | U23: {=($F$6*(1+$Q23)*'User Segmentation'!$I$49) -Dynamic_Row_Table[[Fixed Cost]:[Fixed Cost]] -(Dynamic_Row_Table[[Funding Rate]:[Funding Rate]]*Dynamic_Row_Table[[Tenure (in months)]:[Tenure (in months)]]*$F$6*(1+$Q23)/12) -(IF($Q23<0,'Dynamic CM'!$G$6,'Dynamic CM'!$G$6*(($F$6*(1+$Q23)/$F$6)^'Dynamic CM'!$H$6)) *VLOOKUP($D$6,EAD_Table[#All],MATCH("EAD",EAD_Table[#Headers],0),FALSE) *$F$6*(1+$Q23))} -> 2.7234976
A24: 3 | B24: {=($F$3*(1+$A24)*'User Segmentation'!$I$49) -Dynamic_Row_Table[[Fixed Cost]:[Fixed Cost]] -(Dynamic_Row_Table[[Funding Rate]:[Funding Rate]]*Dynamic_Row_Table[[Tenure (in months)]:[Tenure (in months)]]*$F$3*(1+$A24)/12) -(IF($A24<0,'Dynamic CM'!$G$3,'Dynamic CM'!$G$3*(($F$3*(1+$A24)/$F$3)^'Dynamic CM'!$H$3)) *VLOOKUP($D$3,EAD_Table[#All],MATCH("EAD",EAD_Table[#Headers],0),FALSE) *$F$3*(1+$A24))} -> -71.604964 | C24: {=($F$4*(1+$A24)*'User Segmentation'!$I$49) -Dynamic_Row_Table[[Fixed Cost]:[Fixed Cost]] -(Dynamic_Row_Table[[Funding Rate]:[Funding Rate]]*Dynamic_Row_Table[[Tenure (in months)]:[Tenure (in months)]]*$F$4*(1+$A24)/12) -(IF($A24<0,'Dynamic CM'!$G$4,'Dynamic CM'!$G$4*(($F$4*(1+$A24)/$F$4)^'Dynamic CM'!$H$4)) *VLOOKUP($D$4,EAD_Table[#All],MATCH("EAD",EAD_Table[#Headers],0),FALSE) *$F$4*(1+$A24))} -> 5.4754612 | D24: {=($F$5*(1+$A24)*'User Segmentation'!$I$49) -Dynamic_Row_Table[[Fixed Cost]:[Fixed Cost]] -(Dynamic_Row_Table[[Funding Rate]:[Funding Rate]]*Dynamic_Row_Table[[Tenure (in months)]:[Tenure (in months)]]*$F$5*(1+$A24)/12) -(IF($A24<0,'Dynamic CM'!$G$5,'Dynamic CM'!$G$5*(($F$5*(1+$A24)/$F$5)^'Dynamic CM'!$H$5)) *VLOOKUP($D$5,EAD_Table[#All],MATCH("EAD",EAD_Table[#Headers],0),FALSE) *$F$5*(1+$A24))} -> 37.911402 | E24: {=($F$6*(1+$A24)*'User Segmentation'!$I$49) -Dynamic_Row_Table[[Fixed Cost]:[Fixed Cost]] -(Dynamic_Row_Table[[Funding Rate]:[Funding Rate]]*Dynamic_Row_Table[[Tenure (in months)]:[Tenure (in months)]]*$F$6*(1+$A24)/12) -(IF($A24<0,'Dynamic CM'!$G$6,'Dynamic CM'!$G$6*(($F$6*(1+$A24)/$F$6)^'Dynamic CM'!$H$6)) *VLOOKUP($D$6,EAD_Table[#All],MATCH("EAD",EAD_Table[#Headers],0),FALSE) *$F$6*(1+$A24))} -> 2.1334013 | Q24: 0.6 | R24: {=($F$3*(1+$Q24)*'User Segmentation'!$I$49) -Dynamic_Row_Table[[Fixed Cost]:[Fixed Cost]] -(Dynamic_Row_Table[[Funding Rate]:[Funding Rate]]*Dynamic_Row_Table[[Tenure (in months)]:[Tenure (in months)]]*$F$3*(1+$Q24)/12) -(IF($Q24<0,'Dynamic CM'!$G$3,'Dynamic CM'!$G$3*(($F$3*(1+$Q24)/$F$3)^'Dynamic CM'!$H$3)) *VLOOKUP($D$3,EAD_Table[#All],MATCH("EAD",EAD_Table[#Headers],0),FALSE) *$F$3*(1+$Q24))} -> -4.9768032 | S24: {=($F$4*(1+$Q24)*'User Segmentation'!$I$49) -Dynamic_Row_Table[[Fixed Cost]:[Fixed Cost]] -(Dynamic_Row_Table[[Funding Rate]:[Funding Rate]]*Dynamic_Row_Table[[Tenure (in months)]:[Tenure (in months)]]*$F$4*(1+$Q24)/12) -(IF($Q24<0,'Dynamic CM'!$G$4,'Dynamic CM'!$G$4*(($F$4*(1+$Q24)/$F$4)^'Dynamic CM'!$H$4)) *VLOOKUP($D$4,EAD_Table[#All],MATCH("EAD",EAD_Table[#Headers],0),FALSE) *$F$4*(1+$Q24))} -> 6.0464214 | T24: {=($F$5*(1+$Q24)*'User Segmentation'!$I$49) -Dynamic_Row_Table[[Fixed Cost]:[Fixed Cost]] -(Dynamic_Row_Table[[Funding Rate]:[Funding Rate]]*Dynamic_Row_Table[[Tenure (in months)]:[Tenure (in months)]]*$F$5*(1+$Q24)/12) -(IF($Q24<0,'Dynamic CM'!$G$5,'Dynamic CM'!$G$5*(($F$5*(1+$Q24)/$F$5)^'Dynamic CM'!$H$5)) *VLOOKUP($D$5,EAD_Table[#All],MATCH("EAD",EAD_Table[#Headers],0),FALSE) *$F$5*(1+$Q24))} -> 20.469151 | U24: {=($F$6*(1+$Q24)*'User Segmentation'!$I$49) -Dynamic_Row_Table[[Fixed Cost]:[Fixed Cost]] -(Dynamic_Row_Table[[Funding Rate]:[Funding Rate]]*Dynamic_Row_Table[[Tenure (in months)]:[Tenure (in months)]]*$F$6*(1+$Q24)/12) -(IF($Q24<0,'Dynamic CM'!$G$6,'Dynamic CM'!$G$6*(($F$6*(1+$Q24)/$F$6)^'Dynamic CM'!$H$6)) *VLOOKUP($D$6,EAD_Table[#All],MATCH("EAD",EAD_Table[#Headers],0),FALSE) *$F$6*(1+$Q24))} -> 2.9690968
A25: 3.25 | B25: {=($F$3*(1+$A25)*'User Segmentation'!$I$49) -Dynamic_Row_Table[[Fixed Cost]:[Fixed Cost]] -(Dynamic_Row_Table[[Funding Rate]:[Funding Rate]]*Dynamic_Row_Table[[Tenure (in months)]:[Tenure (in months)]]*$F$3*(1+$A25)/12) -(IF($A25<0,'Dynamic CM'!$G$3,'Dynamic CM'!$G$3*(($F$3*(1+$A25)/$F$3)^'Dynamic CM'!$H$3)) *VLOOKUP($D$3,EAD_Table[#All],MATCH("EAD",EAD_Table[#Headers],0),FALSE) *$F$3*(1+$A25))} -> -85.870417 | C25: {=($F$4*(1+$A25)*'User Segmentation'!$I$49) -Dynamic_Row_Table[[Fixed Cost]:[Fixed Cost]] -(Dynamic_Row_Table[[Funding Rate]:[Funding Rate]]*Dynamic_Row_Table[[Tenure (in months)]:[Tenure (in months)]]*$F$4*(1+$A25)/12) -(IF($A25<0,'Dynamic CM'!$G$4,'Dynamic CM'!$G$4*(($F$4*(1+$A25)/$F$4)^'Dynamic CM'!$H$4)) *VLOOKUP($D$4,EAD_Table[#All],MATCH("EAD",EAD_Table[#Headers],0),FALSE) *$F$4*(1+$A25))} -> 4.2212014 | D25: {=($F$5*(1+$A25)*'User Segmentation'!$I$49) -Dynamic_Row_Table[[Fixed Cost]:[Fixed Cost]] -(Dynamic_Row_Table[[Funding Rate]:[Funding Rate]]*Dynamic_Row_Table[[Tenure (in months)]:[Tenure (in months)]]*$F$5*(1+$A25)/12) -(IF($A25<0,'Dynamic CM'!$G$5,'Dynamic CM'!$G$5*(($F$5*(1+$A25)/$F$5)^'Dynamic CM'!$H$5)) *VLOOKUP($D$5,EAD_Table[#All],MATCH("EAD",EAD_Table[#Headers],0),FALSE) *$F$5*(1+$A25))} -> 38.443449 | E25: {=($F$6*(1+$A25)*'User Segmentation'!$I$49) -Dynamic_Row_Table[[Fixed Cost]:[Fixed Cost]] -(Dynamic_Row_Table[[Funding Rate]:[Funding Rate]]*Dynamic_Row_Table[[Tenure (in months)]:[Tenure (in months)]]*$F$6*(1+$A25)/12) -(IF($A25<0,'Dynamic CM'!$G$6,'Dynamic CM'!$G$6*(($F$6*(1+$A25)/$F$6)^'Dynamic CM'!$H$6)) *VLOOKUP($D$6,EAD_Table[#All],MATCH("EAD",EAD_Table[#Headers],0),FALSE) *$F$6*(1+$A25))} -> 1.2192163 | Q25: 0.7 | R25: {=($F$3*(1+$Q25)*'User Segmentation'!$I$49) -Dynamic_Row_Table[[Fixed Cost]:[Fixed Cost]] -(Dynamic_Row_Table[[Funding Rate]:[Funding Rate]]*Dynamic_Row_Table[[Tenure (in months)]:[Tenure (in months)]]*$F$3*(1+$Q25)/12) -(IF($Q25<0,'Dynamic CM'!$G$3,'Dynamic CM'!$G$3*(($F$3*(1+$Q25)/$F$3)^'Dynamic CM'!$H$3)) *VLOOKUP($D$3,EAD_Table[#All],MATCH("EAD",EAD_Table[#Headers],0),FALSE) *$F$3*(1+$Q25))} -> -5.8066406 | S25: {=($F$4*(1+$Q25)*'User Segmentation'!$I$49) -Dynamic_Row_Table[[Fixed Cost]:[Fixed Cost]] -(Dynamic_Row_Table[[Funding Rate]:[Funding Rate]]*Dynamic_Row_Table[[Tenure (in months)]:[Tenure (in months)]]*$F$4*(1+$Q25)/12) -(IF($Q25<0,'Dynamic CM'!$G$4,'Dynamic CM'!$G$4*(($F$4*(1+$Q25)/$F$4)^'Dynamic CM'!$H$4)) *VLOOKUP($D$4,EAD_Table[#All],MATCH("EAD",EAD_Table[#Headers],0),FALSE) *$F$4*(1+$Q25))} -> 6.3989263 | T25: {=($F$5*(1+$Q25)*'User Segmentation'!$I$49) -Dynamic_Row_Table[[Fixed Cost]:[Fixed Cost]] -(Dynamic_Row_Table[[Funding Rate]:[Funding Rate]]*Dynamic_Row_Table[[Tenure (in months)]:[Tenure (in months)]]*$F$5*(1+$Q25)/12) -(IF($Q25<0,'Dynamic CM'!$G$5,'Dynamic CM'!$G$5*(($F$5*(1+$Q25)/$F$5)^'Dynamic CM'!$H$5)) *VLOOKUP($D$5,EAD_Table[#All],MATCH("EAD",EAD_Table[#Headers],0),FALSE) *$F$5*(1+$Q25))} -> 21.632393 | U25: {=($F$6*(1+$Q25)*'User Segmentation'!$I$49) -Dynamic_Row_Table[[Fixed Cost]:[Fixed Cost]] -(Dynamic_Row_Table[[Funding Rate]:[Funding Rate]]*Dynamic_Row_Table[[Tenure (in months)]:[Tenure (in months)]]*$F$6*(1+$Q25)/12) -(IF($Q25<0,'Dynamic CM'!$G$6,'Dynamic CM'!$G$6*(($F$6*(1+$Q25)/$F$6)^'Dynamic CM'!$H$6)) *VLOOKUP($D$6,EAD_Table[#All],MATCH("EAD",EAD_Table[#Headers],0),FALSE) *$F$6*(1+$Q25))} -> 3.1947801
A26: 3.5 | B26: {=($F$3*(1+$A26)*'User Segmentation'!$I$49) -Dynamic_Row_Table[[Fixed Cost]:[Fixed Cost]] -(Dynamic_Row_Table[[Funding Rate]:[Funding Rate]]*Dynamic_Row_Table[[Tenure (in months)]:[Tenure (in months)]]*$F$3*(1+$A26)/12) -(IF($A26<0,'Dynamic CM'!$G$3,'Dynamic CM'!$G$3*(($F$3*(1+$A26)/$F$3)^'Dynamic CM'!$H$3)) *VLOOKUP($D$3,EAD_Table[#All],MATCH("EAD",EAD_Table[#Headers],0),FALSE) *$F$3*(1+$A26))} -> -101.87772 | C26: {=($F$4*(1+$A26)*'User Segmentation'!$I$49) -Dynamic_Row_Table[[Fixed Cost]:[Fixed Cost]] -(Dynamic_Row_Table[[Funding Rate]:[Funding Rate]]*Dynamic_Row_Table[[Tenure (in months)]:[Tenure (in months)]]*$F$4*(1+$A26)/12) -(IF($A26<0,'Dynamic CM'!$G$4,'Dynamic CM'!$G$4*(($F$4*(1+$A26)/$F$4)^'Dynamic CM'!$H$4)) *VLOOKUP($D$4,EAD_Table[#All],MATCH("EAD",EAD_Table[#Headers],0),FALSE) *$F$4*(1+$A26))} -> 2.7211516 | D26: {=($F$5*(1+$A26)*'User Segmentation'!$I$49) -Dynamic_Row_Table[[Fixed Cost]:[Fixed Cost]] -(Dynamic_Row_Table[[Funding Rate]:[Funding Rate]]*Dynamic_Row_Table[[Tenure (in months)]:[Tenure (in months)]]*$F$5*(1+$A26)/12) -(IF($A26<0,'Dynamic CM'!$G$5,'Dynamic CM'!$G$5*(($F$5*(1+$A26)/$F$5)^'Dynamic CM'!$H$5)) *VLOOKUP($D$5,EAD_Table[#All],MATCH("EAD",EAD_Table[#Headers],0),FALSE) *$F$5*(1+$A26))} -> 38.728292 | E26: {=($F$6*(1+$A26)*'User Segmentation'!$I$49) -Dynamic_Row_Table[[Fixed Cost]:[Fixed Cost]] -(Dynamic_Row_Table[[Funding Rate]:[Funding Rate]]*Dynamic_Row_Table[[Tenure (in months)]:[Tenure (in months)]]*$F$6*(1+$A26)/12) -(IF($A26<0,'Dynamic CM'!$G$6,'Dynamic CM'!$G$6*(($F$6*(1+$A26)/$F$6)^'Dynamic CM'!$H$6)) *VLOOKUP($D$6,EAD_Table[#All],MATCH("EAD",EAD_Table[#Headers],0),FALSE) *$F$6*(1+$A26))} -> 0.13487426 | Q26: 0.8 | R26: {=($F$3*(1+$Q26)*'User Segmentation'!$I$49) -Dynamic_Row_Table[[Fixed Cost]:[Fixed Cost]] -(Dynamic_Row_Table[[Funding Rate]:[Funding Rate]]*Dynamic_Row_Table[[Tenure (in months)]:[Tenure (in months)]]*$F$3*(1+$Q26)/12) -(IF($Q26<0,'Dynamic CM'!$G$3,'Dynamic CM'!$G$3*(($F$3*(1+$Q26)/$F$3)^'Dynamic CM'!$H$3)) *VLOOKUP($D$3,EAD_Table[#All],MATCH("EAD",EAD_Table[#Headers],0),FALSE) *$F$3*(1+$Q26))} -> -6.7597781 | S26: {=($F$4*(1+$Q26)*'User Segmentation'!$I$49) -Dynamic_Row_Table[[Fixed Cost]:[Fixed Cost]] -(Dynamic_Row_Table[[Funding Rate]:[Funding Rate]]*Dynamic_Row_Table[[Tenure (in months)]:[Tenure (in months)]]*$F$4*(1+$Q26)/12) -(IF($Q26<0,'Dynamic CM'!$G$4,'Dynamic CM'!$G$4*(($F$4*(1+$Q26)/$F$4)^'Dynamic CM'!$H$4)) *VLOOKUP($D$4,EAD_Table[#All],MATCH("EAD",EAD_Table[#Headers],0),FALSE) *$F$4*(1+$Q26))} -> 6.7220992 | T26: {=($F$5*(1+$Q26)*'User Segmentation'!$I$49) -Dynamic_Row_Table[[Fixed Cost]:[Fixed Cost]] -(Dynamic_Row_Table[[Funding Rate]:[Funding Rate]]*Dynamic_Row_Table[[Tenure (in months)]:[Tenure (in months)]]*$F$5*(1+$Q26)/12) -(IF($Q26<0,'Dynamic CM'!$G$5,'Dynamic CM'!$G$5*(($F$5*(1+$Q26)/$F$5)^'Dynamic CM'!$H$5)) *VLOOKUP($D$5,EAD_Table[#All],MATCH("EAD",EAD_Table[#Headers],0),FALSE) *$F$5*(1+$Q26))} -> 22.758573 | U26: {=($F$6*(1+$Q26)*'User Segmentation'!$I$49) -Dynamic_Row_Table[[Fixed Cost]:[Fixed Cost]] -(Dynamic_Row_Table[[Funding Rate]:[Funding Rate]]*Dynamic_Row_Table[[Tenure (in months)]:[Tenure (in months)]]*$F$6*(1+$Q26)/12) -(IF($Q26<0,'Dynamic CM'!$G$6,'Dynamic CM'!$G$6*(($F$6*(1+$Q26)/$F$6)^'Dynamic CM'!$H$6)) *VLOOKUP($D$6,EAD_Table[#All],MATCH("EAD",EAD_Table[#Headers],0),FALSE) *$F$6*(1+$Q26))} -> 3.4001571
... A32: 5 | B32: {=($F$3*(1+$A32)*'User Segmentation'!$I$49) -Dynamic_Row_Table[[Fixed Cost]:[Fixed Cost]] -(Dynamic_Row_Table[[Funding Rate]:[Funding Rate]]*Dynamic_Row_Table[[Tenure (in months)]:[Tenure (in months)]]*$F$3*(1+$A32)/12) -(IF($A32<0,'Dynamic CM'!$G$3,'Dynamic CM'!$G$3*(($F$3*(1+$A32)/$F$3)^'Dynamic CM'!$H$3)) *VLOOKUP($D$3,EAD_Table[#All],MATCH("EAD",EAD_Table[#Headers],0),FALSE) *$F$3*(1+$A32))} -> -239.55403 | C32: {=($F$4*(1+$A32)*'User Segmentation'!$I$49) -Dynamic_Row_Table[[Fixed Cost]:[Fixed Cost]] -(Dynamic_Row_Table[[Funding Rate]:[Funding Rate]]*Dynamic_Row_Table[[Tenure (in months)]:[Tenure (in months)]]*$F$4*(1+$A32)/12) -(IF($A32<0,'Dynamic CM'!$G$4,'Dynamic CM'!$G$4*(($F$4*(1+$A32)/$F$4)^'Dynamic CM'!$H$4)) *VLOOKUP($D$4,EAD_Table[#All],MATCH("EAD",EAD_Table[#Headers],0),FALSE) *$F$4*(1+$A32))} -> -11.683878 | D32: {=($F$5*(1+$A32)*'User Segmentation'!$I$49) -Dynamic_Row_Table[[Fixed Cost]:[Fixed Cost]] -(Dynamic_Row_Table[[Funding Rate]:[Funding Rate]]*Dynamic_Row_Table[[Tenure (in months)]:[Tenure (in months)]]*$F$5*(1+$A32)/12) -(IF($A32<0,'Dynamic CM'!$G$5,'Dynamic CM'!$G$5*(($F$5*(1+$A32)/$F$5)^'Dynamic CM'!$H$5)) *VLOOKUP($D$5,EAD_Table[#All],MATCH("EAD",EAD_Table[#Headers],0),FALSE) *$F$5*(1+$A32))} -> 35.19304 | E32: {=($F$6*(1+$A32)*'User Segmentation'!$I$49) -Dynamic_Row_Table[[Fixed Cost]:[Fixed Cost]] -(Dynamic_Row_Table[[Funding Rate]:[Funding Rate]]*Dynamic_Row_Table[[Tenure (in months)]:[Tenure (in months)]]*$F$6*(1+$A32)/12) -(IF($A32<0,'Dynamic CM'!$G$6,'Dynamic CM'!$G$6*(($F$6*(1+$A32)/$F$6)^'Dynamic CM'!$H$6)) *VLOOKUP($D$6,EAD_Table[#All],MATCH("EAD",EAD_Table[#Headers],0),FALSE) *$F$6*(1+$A32))} -> -10.1128 | Q32: 1.4 | R32: {=($F$3*(1+$Q32)*'User Segmentation'!$I$49) -Dynamic_Row_Table[[Fixed Cost]:[Fixed Cost]] -(Dynamic_Row_Table[[Funding Rate]:[Funding Rate]]*Dynamic_Row_Table[[Tenure (in months)]:[Tenure (in months)]]*$F$3*(1+$Q32)/12) -(IF($Q32<0,'Dynamic CM'!$G$3,'Dynamic CM'!$G$3*(($F$3*(1+$Q32)/$F$3)^'Dynamic CM'!$H$3)) *VLOOKUP($D$3,EAD_Table[#All],MATCH("EAD",EAD_Table[#Headers],0),FALSE) *$F$3*(1+$Q32))} -> -15.425643 | S32: {=($F$4*(1+$Q32)*'User Segmentation'!$I$49) -Dynamic_Row_Table[[Fixed Cost]:[Fixed Cost]] -(Dynamic_Row_Table[[Funding Rate]:[Funding Rate]]*Dynamic_Row_Table[[Tenure (in months)]:[Tenure (in months)]]*$F$4*(1+$Q32)/12) -(IF($Q32<0,'Dynamic CM'!$G$4,'Dynamic CM'!$G$4*(($F$4*(1+$Q32)/$F$4)^'Dynamic CM'!$H$4)) *VLOOKUP($D$4,EAD_Table[#All],MATCH("EAD",EAD_Table[#Headers],0),FALSE) *$F$4*(1+$Q32))} -> 8.016146 | T32: {=($F$5*(1+$Q32)*'User Segmentation'!$I$49) -Dynamic_Row_Table[[Fixed Cost]:[Fixed Cost]] -(Dynamic_Row_Table[[Funding Rate]:[Funding Rate]]*Dynamic_Row_Table[[Tenure (in months)]:[Tenure (in months)]]*$F$5*(1+$Q32)/12) -(IF($Q32<0,'Dynamic CM'!$G$5,'Dynamic CM'!$G$5*(($F$5*(1+$Q32)/$F$5)^'Dynamic CM'!$H$5)) *VLOOKUP($D$5,EAD_Table[#All],MATCH("EAD",EAD_Table[#Headers],0),FALSE) *$F$5*(1+$Q32))} -> 28.729417 | U32: {=($F$6*(1+$Q32)*'User Segmentation'!$I$49) -Dynamic_Row_Table[[Fixed Cost]:[Fixed Cost]] -(Dynamic_Row_Table[[Funding Rate]:[Funding Rate]]*Dynamic_Row_Table[[Tenure (in months)]:[Tenure (in months)]]*$F$6*(1+$Q32)/12) -(IF($Q32<0,'Dynamic CM'!$G$6,'Dynamic CM'!$G$6*(($F$6*(1+$Q32)/$F$6)^'Dynamic CM'!$H$6)) *VLOOKUP($D$6,EAD_Table[#All],MATCH("EAD",EAD_Table[#Headers],0),FALSE) *$F$6*(1+$Q32))} -> 4.1859013
Q33: 1.5 | R33: {=($F$3*(1+$Q33)*'User Segmentation'!$I$49) -Dynamic_Row_Table[[Fixed Cost]:[Fixed Cost]] -(Dynamic_Row_Table[[Funding Rate]:[Funding Rate]]*Dynamic_Row_Table[[Tenure (in months)]:[Tenure (in months)]]*$F$3*(1+$Q33)/12) -(IF($Q33<0,'Dynamic CM'!$G$3,'Dynamic CM'!$G$3*(($F$3*(1+$Q33)/$F$3)^'Dynamic CM'!$H$3)) *VLOOKUP($D$3,EAD_Table[#All],MATCH("EAD",EAD_Table[#Headers],0),FALSE) *$F$3*(1+$Q33))} -> -17.420013 | S33: {=($F$4*(1+$Q33)*'User Segmentation'!$I$49) -Dynamic_Row_Table[[Fixed Cost]:[Fixed Cost]] -(Dynamic_Row_Table[[Funding Rate]:[Funding Rate]]*Dynamic_Row_Table[[Tenure (in months)]:[Tenure (in months)]]*$F$4*(1+$Q33)/12) -(IF($Q33<0,'Dynamic CM'!$G$4,'Dynamic CM'!$G$4*(($F$4*(1+$Q33)/$F$4)^'Dynamic CM'!$H$4)) *VLOOKUP($D$4,EAD_Table[#All],MATCH("EAD",EAD_Table[#Headers],0),FALSE) *$F$4*(1+$Q33))} -> 8.1198437 | T33: {=($F$5*(1+$Q33)*'User Segmentation'!$I$49) -Dynamic_Row_Table[[Fixed Cost]:[Fixed Cost]] -(Dynamic_Row_Table[[Funding Rate]:[Funding Rate]]*Dynamic_Row_Table[[Tenure (in months)]:[Tenure (in months)]]*$F$5*(1+$Q33)/12) -(IF($Q33<0,'Dynamic CM'!$G$5,'Dynamic CM'!$G$5*(($F$5*(1+$Q33)/$F$5)^'Dynamic CM'!$H$5)) *VLOOKUP($D$5,EAD_Table[#All],MATCH("EAD",EAD_Table[#Headers],0),FALSE) *$F$5*(1+$Q33))} -> 29.592325 | U33: {=($F$6*(1+$Q33)*'User Segmentation'!$I$49) -Dynamic_Row_Table[[Fixed Cost]:[Fixed Cost]] -(Dynamic_Row_Table[[Funding Rate]:[Funding Rate]]*Dynamic_Row_Table[[Tenure (in months)]:[Tenure (in months)]]*$F$6*(1+$Q33)/12) -(IF($Q33<0,'Dynamic CM'!$G$6,'Dynamic CM'!$G$6*(($F$6*(1+$Q33)/$F$6)^'Dynamic CM'!$H$6)) *VLOOKUP($D$6,EAD_Table[#All],MATCH("EAD",EAD_Table[#Headers],0),FALSE) *$F$6*(1+$Q33))} -> 4.2393387
A34: Peak CM | B34: Delta Peak | C34: Peak ATS | D34: Min Profitable Delta | E34: Max Profitable Delta | Q34: 1.6 | R34: {=($F$3*(1+$Q34)*'User Segmentation'!$I$49) -Dynamic_Row_Table[[Fixed Cost]:[Fixed Cost]] -(Dynamic_Row_Table[[Funding Rate]:[Funding Rate]]*Dynamic_Row_Table[[Tenure (in months)]:[Tenure (in months)]]*$F$3*(1+$Q34)/12) -(IF($Q34<0,'Dynamic CM'!$G$3,'Dynamic CM'!$G$3*(($F$3*(1+$Q34)/$F$3)^'Dynamic CM'!$H$3)) *VLOOKUP($D$3,EAD_Table[#All],MATCH("EAD",EAD_Table[#Headers],0),FALSE) *$F$3*(1+$Q34))} -> -19.588178 | S34: {=($F$4*(1+$Q34)*'User Segmentation'!$I$49) -Dynamic_Row_Table[[Fixed Cost]:[Fixed Cost]] -(Dynamic_Row_Table[[Funding Rate]:[Funding Rate]]*Dynamic_Row_Table[[Tenure (in months)]:[Tenure (in months)]]*$F$4*(1+$Q34)/12) -(IF($Q34<0,'Dynamic CM'!$G$4,'Dynamic CM'!$G$4*(($F$4*(1+$Q34)/$F$4)^'Dynamic CM'!$H$4)) *VLOOKUP($D$4,EAD_Table[#All],MATCH("EAD",EAD_Table[#Headers],0),FALSE) *$F$4*(1+$Q34))} -> 8.1903554 | T34: {=($F$5*(1+$Q34)*'User Segmentation'!$I$49) -Dynamic_Row_Table[[Fixed Cost]:[Fixed Cost]] -(Dynamic_Row_Table[[Funding Rate]:[Funding Rate]]*Dynamic_Row_Table[[Tenure (in months)]:[Tenure (in months)]]*$F$5*(1+$Q34)/12) -(IF($Q34<0,'Dynamic CM'!$G$5,'Dynamic CM'!$G$5*(($F$5*(1+$Q34)/$F$5)^'Dynamic CM'!$H$5)) *VLOOKUP($D$5,EAD_Table[#All],MATCH("EAD",EAD_Table[#Headers],0),FALSE) *$F$5*(1+$Q34))} -> 30.417142 | U34: {=($F$6*(1+$Q34)*'User Segmentation'!$I$49) -Dynamic_Row_Table[[Fixed Cost]:[Fixed Cost]] -(Dynamic_Row_Table[[Funding Rate]:[Funding Rate]]*Dynamic_Row_Table[[Tenure (in months)]:[Tenure (in months)]]*$F$6*(1+$Q34)/12) -(IF($Q34<0,'Dynamic CM'!$G$6,'Dynamic CM'!$G$6*(($F$6*(1+$Q34)/$F$6)^'Dynamic CM'!$H$6)) *VLOOKUP($D$6,EAD_Table[#All],MATCH("EAD",EAD_Table[#Headers],0),FALSE) *$F$6*(1+$Q34))} -> 4.2698018
A35: =MAX(U9:U169) -> 4.2770005 | B35: =INDEX(Q9:Q169, MATCH(MAX(U9:U169), U9:U169, 0)) -> 1.7 | C35: =(1+$B$35)*$F$6 -> 337.90179 | D35: {=IF(COUNTIF(U9:U169,">0")=0, "#NA", MIN(IF(U9:U169>0, Q9:Q169)) )} -> -0.2 | E35: {=IF(COUNTIF(U9:U169,">0")=0, "#NA", MAX(IF(U9:U169>0, Q9:Q169)) )} -> 3.5 | Q35: 1.7 | R35: {=($F$3*(1+$Q35)*'User Segmentation'!$I$49) -Dynamic_Row_Table[[Fixed Cost]:[Fixed Cost]] -(Dynamic_Row_Table[[Funding Rate]:[Funding Rate]]*Dynamic_Row_Table[[Tenure (in months)]:[Tenure (in months)]]*$F$3*(1+$Q35)/12) -(IF($Q35<0,'Dynamic CM'!$G$3,'Dynamic CM'!$G$3*(($F$3*(1+$Q35)/$F$3)^'Dynamic CM'!$H$3)) *VLOOKUP($D$3,EAD_Table[#All],MATCH("EAD",EAD_Table[#Headers],0),FALSE) *$F$3*(1+$Q35))} -> -21.936311 | S35: {=($F$4*(1+$Q35)*'User Segmentation'!$I$49) -Dynamic_Row_Table[[Fixed Cost]:[Fixed Cost]] -(Dynamic_Row_Table[[Funding Rate]:[Funding Rate]]*Dynamic_Row_Table[[Tenure (in months)]:[Tenure (in months)]]*$F$4*(1+$Q35)/12) -(IF($Q35<0,'Dynamic CM'!$G$4,'Dynamic CM'!$G$4*(($F$4*(1+$Q35)/$F$4)^'Dynamic CM'!$H$4)) *VLOOKUP($D$4,EAD_Table[#All],MATCH("EAD",EAD_Table[#Headers],0),FALSE) *$F$4*(1+$Q35))} -> 8.2272618 | T35: {=($F$5*(1+$Q35)*'User Segmentation'!$I$49) -Dynamic_Row_Table[[Fixed Cost]:[Fixed Cost]] -(Dynamic_Row_Table[[Funding Rate]:[Funding Rate]]*Dynamic_Row_Table[[Tenure (in months)]:[Tenure (in months)]]*$F$5*(1+$Q35)/12) -(IF($Q35<0,'Dynamic CM'!$G$5,'Dynamic CM'!$G$5*(($F$5*(1+$Q35)/$F$5)^'Dynamic CM'!$H$5)) *VLOOKUP($D$5,EAD_Table[#All],MATCH("EAD",EAD_Table[#Headers],0),FALSE) *$F$5*(1+$Q35))} -> 31.203762 | U35: {=($F$6*(1+$Q35)*'User Segmentation'!$I$49) -Dynamic_Row_Table[[Fixed Cost]:[Fixed Cost]] -(Dynamic_Row_Table[[Funding Rate]:[Funding Rate]]*Dynamic_Row_Table[[Tenure (in months)]:[Tenure (in months)]]*$F$6*(1+$Q35)/12) -(IF($Q35<0,'Dynamic CM'!$G$6,'Dynamic CM'!$G$6*(($F$6*(1+$Q35)/$F$6)^'Dynamic CM'!$H$6)) *VLOOKUP($D$6,EAD_Table[#All],MATCH("EAD",EAD_Table[#Headers],0),FALSE) *$F$6*(1+$Q35))} -> 4.2770005
D36: Min Profitable ATS | E36: Max Profitable ATS | Q36: 1.8 | R36: {=($F$3*(1+$Q36)*'User Segmentation'!$I$49) -Dynamic_Row_Table[[Fixed Cost]:[Fixed Cost]] -(Dynamic_Row_Table[[Funding Rate]:[Funding Rate]]*Dynamic_Row_Table[[Tenure (in months)]:[Tenure (in months)]]*$F$3*(1+$Q36)/12) -(IF($Q36<0,'Dynamic CM'!$G$3,'Dynamic CM'!$G$3*(($F$3*(1+$Q36)/$F$3)^'Dynamic CM'!$H$3)) *VLOOKUP($D$3,EAD_Table[#All],MATCH("EAD",EAD_Table[#Headers],0),FALSE) *$F$3*(1+$Q36))} -> -24.470561 | S36: {=($F$4*(1+$Q36)*'User Segmentation'!$I$49) -Dynamic_Row_Table[[Fixed Cost]:[Fixed Cost]] -(Dynamic_Row_Table[[Funding Rate]:[Funding Rate]]*Dynamic_Row_Table[[Tenure (in months)]:[Tenure (in months)]]*$F$4*(1+$Q36)/12) -(IF($Q36<0,'Dynamic CM'!$G$4,'Dynamic CM'!$G$4*(($F$4*(1+$Q36)/$F$4)^'Dynamic CM'!$H$4)) *VLOOKUP($D$4,EAD_Table[#All],MATCH("EAD",EAD_Table[#Headers],0),FALSE) *$F$4*(1+$Q36))} -> 8.2301546 | T36: {=($F$5*(1+$Q36)*'User Segmentation'!$I$49) -Dynamic_Row_Table[[Fixed Cost]:[Fixed Cost]] -(Dynamic_Row_Table[[Funding Rate]:[Funding Rate]]*Dynamic_Row_Table[[Tenure (in months)]:[Tenure (in months)]]*$F$5*(1+$Q36)/12) -(IF($Q36<0,'Dynamic CM'!$G$5,'Dynamic CM'!$G$5*(($F$5*(1+$Q36)/$F$5)^'Dynamic CM'!$H$5)) *VLOOKUP($D$5,EAD_Table[#All],MATCH("EAD",EAD_Table[#Headers],0),FALSE) *$F$5*(1+$Q36))} -> 31.952083 | U36: {=($F$6*(1+$Q36)*'User Segmentation'!$I$49) -Dynamic_Row_Table[[Fixed Cost]:[Fixed Cost]] -(Dynamic_Row_Table[[Funding Rate]:[Funding Rate]]*Dynamic_Row_Table[[Tenure (in months)]:[Tenure (in months)]]*$F$6*(1+$Q36)/12) -(IF($Q36<0,'Dynamic CM'!$G$6,'Dynamic CM'!$G$6*(($F$6*(1+$Q36)/$F$6)^'Dynamic CM'!$H$6)) *VLOOKUP($D$6,EAD_Table[#All],MATCH("EAD",EAD_Table[#Headers],0),FALSE) *$F$6*(1+$Q36))} -> 4.260652
D37: =IF(ISNUMBER(D$35),(1+D$35)*$F$6,"#NA") -> 100.11905 | E37: =IF(ISNUMBER(E$35),(1+E$35)*$F$6,"#NA") -> 563.16964 | Q37: 1.9 | R37: {=($F$3*(1+$Q37)*'User Segmentation'!$I$49) -Dynamic_Row_Table[[Fixed Cost]:[Fixed Cost]] -(Dynamic_Row_Table[[Funding Rate]:[Funding Rate]]*Dynamic_Row_Table[[Tenure (in months)]:[Tenure (in months)]]*$F$3*(1+$Q37)/12) -(IF($Q37<0,'Dynamic CM'!$G$3,'Dynamic CM'!$G$3*(($F$3*(1+$Q37)/$F$3)^'Dynamic CM'!$H$3)) *VLOOKUP($D$3,EAD_Table[#All],MATCH("EAD",EAD_Table[#Headers],0),FALSE) *$F$3*(1+$Q37))} -> -27.197051 | S37: {=($F$4*(1+$Q37)*'User Segmentation'!$I$49) -Dynamic_Row_Table[[Fixed Cost]:[Fixed Cost]] -(Dynamic_Row_Table[[Funding Rate]:[Funding Rate]]*Dynamic_Row_Table[[Tenure (in months)]:[Tenure (in months)]]*$F$4*(1+$Q37)/12) -(IF($Q37<0,'Dynamic CM'!$G$4,'Dynamic CM'!$G$4*(($F$4*(1+$Q37)/$F$4)^'Dynamic CM'!$H$4)) *VLOOKUP($D$4,EAD_Table[#All],MATCH("EAD",EAD_Table[#Headers],0),FALSE) *$F$4*(1+$Q37))} -> 8.1986357 | T37: {=($F$5*(1+$Q37)*'User Segmentation'!$I$49) -Dynamic_Row_Table[[Fixed Cost]:[Fixed Cost]] -(Dynamic_Row_Table[[Funding Rate]:[Funding Rate]]*Dynamic_Row_Table[[Tenure (in months)]:[Tenure (in months)]]*$F$5*(1+$Q37)/12) -(IF($Q37<0,'Dynamic CM'!$G$5,'Dynamic CM'!$G$5*(($F$5*(1+$Q37)/$F$5)^'Dynamic CM'!$H$5)) *VLOOKUP($D$5,EAD_Table[#All],MATCH("EAD",EAD_Table[#Headers],0),FALSE) *$F$5*(1+$Q37))} -> 32.662005 | U37: {=($F$6*(1+$Q37)*'User Segmentation'!$I$49) -Dynamic_Row_Table[[Fixed Cost]:[Fixed Cost]] -(Dynamic_Row_Table[[Funding Rate]:[Funding Rate]]*Dynamic_Row_Table[[Tenure (in months)]:[Tenure (in months)]]*$F$6*(1+$Q37)/12) -(IF($Q37<0,'Dynamic CM'!$G$6,'Dynamic CM'!$G$6*(($F$6*(1+$Q37)/$F$6)^'Dynamic CM'!$H$6)) *VLOOKUP($D$6,EAD_Table[#All],MATCH("EAD",EAD_Table[#Headers],0),FALSE) *$F$6*(1+$Q37))} -> 4.2204807
Q38: 2 | R38: {=($F$3*(1+$Q38)*'User Segmentation'!$I$49) -Dynamic_Row_Table[[Fixed Cost]:[Fixed Cost]] -(Dynamic_Row_Table[[Funding Rate]:[Funding Rate]]*Dynamic_Row_Table[[Tenure (in months)]:[Tenure (in months)]]*$F$3*(1+$Q38)/12) -(IF($Q38<0,'Dynamic CM'!$G$3,'Dynamic CM'!$G$3*(($F$3*(1+$Q38)/$F$3)^'Dynamic CM'!$H$3)) *VLOOKUP($D$3,EAD_Table[#All],MATCH("EAD",EAD_Table[#Headers],0),FALSE) *$F$3*(1+$Q38))} -> -30.121878 | S38: {=($F$4*(1+$Q38)*'User Segmentation'!$I$49) -Dynamic_Row_Table[[Fixed Cost]:[Fixed Cost]] -(Dynamic_Row_Table[[Funding Rate]:[Funding Rate]]*Dynamic_Row_Table[[Tenure (in months)]:[Tenure (in months)]]*$F$4*(1+$Q38)/12) -(IF($Q38<0,'Dynamic CM'!$G$4,'Dynamic CM'!$G$4*(($F$4*(1+$Q38)/$F$4)^'Dynamic CM'!$H$4)) *VLOOKUP($D$4,EAD_Table[#All],MATCH("EAD",EAD_Table[#Headers],0),FALSE) *$F$4*(1+$Q38))} -> 8.1323163 | T38: {=($F$5*(1+$Q38)*'User Segmentation'!$I$49) -Dynamic_Row_Table[[Fixed Cost]:[Fixed Cost]] -(Dynamic_Row_Table[[Funding Rate]:[Funding Rate]]*Dynamic_Row_Table[[Tenure (in months)]:[Tenure (in months)]]*$F$5*(1+$Q38)/12) -(IF($Q38<0,'Dynamic CM'!$G$5,'Dynamic CM'!$G$5*(($F$5*(1+$Q38)/$F$5)^'Dynamic CM'!$H$5)) *VLOOKUP($D$5,EAD_Table[#All],MATCH("EAD",EAD_Table[#Headers],0),FALSE) *$F$5*(1+$Q38))} -> 33.333433 | U38: {=($F$6*(1+$Q38)*'User Segmentation'!$I$49) -Dynamic_Row_Table[[Fixed Cost]:[Fixed Cost]] -(Dynamic_Row_Table[[Funding Rate]:[Funding Rate]]*Dynamic_Row_Table[[Tenure (in months)]:[Tenure (in months)]]*$F$6*(1+$Q38)/12) -(IF($Q38<0,'Dynamic CM'!$G$6,'Dynamic CM'!$G$6*(($F$6*(1+$Q38)/$F$6)^'Dynamic CM'!$H$6)) *VLOOKUP($D$6,EAD_Table[#All],MATCH("EAD",EAD_Table[#Headers],0),FALSE) *$F$6*(1+$Q38))} -> 4.1562175
Q39: 2.1 | R39: {=($F$3*(1+$Q39)*'User Segmentation'!$I$49) -Dynamic_Row_Table[[Fixed Cost]:[Fixed Cost]] -(Dynamic_Row_Table[[Funding Rate]:[Funding Rate]]*Dynamic_Row_Table[[Tenure (in months)]:[Tenure (in months)]]*$F$3*(1+$Q39)/12) -(IF($Q39<0,'Dynamic CM'!$G$3,'Dynamic CM'!$G$3*(($F$3*(1+$Q39)/$F$3)^'Dynamic CM'!$H$3)) *VLOOKUP($D$3,EAD_Table[#All],MATCH("EAD",EAD_Table[#Headers],0),FALSE) *$F$3*(1+$Q39))} -> -33.251119 | S39: {=($F$4*(1+$Q39)*'User Segmentation'!$I$49) -Dynamic_Row_Table[[Fixed Cost]:[Fixed Cost]] -(Dynamic_Row_Table[[Funding Rate]:[Funding Rate]]*Dynamic_Row_Table[[Tenure (in months)]:[Tenure (in months)]]*$F$4*(1+$Q39)/12) -(IF($Q39<0,'Dynamic CM'!$G$4,'Dynamic CM'!$G$4*(($F$4*(1+$Q39)/$F$4)^'Dynamic CM'!$H$4)) *VLOOKUP($D$4,EAD_Table[#All],MATCH("EAD",EAD_Table[#Headers],0),FALSE) *$F$4*(1+$Q39))} -> 8.0308168 | T39: {=($F$5*(1+$Q39)*'User Segmentation'!$I$49) -Dynamic_Row_Table[[Fixed Cost]:[Fixed Cost]] -(Dynamic_Row_Table[[Funding Rate]:[Funding Rate]]*Dynamic_Row_Table[[Tenure (in months)]:[Tenure (in months)]]*$F$5*(1+$Q39)/12) -(IF($Q39<0,'Dynamic CM'!$G$5,'Dynamic CM'!$G$5*(($F$5*(1+$Q39)/$F$5)^'Dynamic CM'!$H$5)) *VLOOKUP($D$5,EAD_Table[#All],MATCH("EAD",EAD_Table[#Headers],0),FALSE) *$F$5*(1+$Q39))} -> 33.966275 | U39: {=($F$6*(1+$Q39)*'User Segmentation'!$I$49) -Dynamic_Row_Table[[Fixed Cost]:[Fixed Cost]] -(Dynamic_Row_Table[[Funding Rate]:[Funding Rate]]*Dynamic_Row_Table[[Tenure (in months)]:[Tenure (in months)]]*$F$6*(1+$Q39)/12) -(IF($Q39<0,'Dynamic CM'!$G$6,'Dynamic CM'!$G$6*(($F$6*(1+$Q39)/$F$6)^'Dynamic CM'!$H$6)) *VLOOKUP($D$6,EAD_Table[#All],MATCH("EAD",EAD_Table[#Headers],0),FALSE) *$F$6*(1+$Q39))} -> 4.0675997
Q40: 2.2 | R40: {=($F$3*(1+$Q40)*'User Segmentation'!$I$49) -Dynamic_Row_Table[[Fixed Cost]:[Fixed Cost]] -(Dynamic_Row_Table[[Funding Rate]:[Funding Rate]]*Dynamic_Row_Table[[Tenure (in months)]:[Tenure (in months)]]*$F$3*(1+$Q40)/12) -(IF($Q40<0,'Dynamic CM'!$G$3,'Dynamic CM'!$G$3*(($F$3*(1+$Q40)/$F$3)^'Dynamic CM'!$H$3)) *VLOOKUP($D$3,EAD_Table[#All],MATCH("EAD",EAD_Table[#Headers],0),FALSE) *$F$3*(1+$Q40))} -> -36.590827 | S40: {=($F$4*(1+$Q40)*'User Segmentation'!$I$49) -Dynamic_Row_Table[[Fixed Cost]:[Fixed Cost]] -(Dynamic_Row_Table[[Funding Rate]:[Funding Rate]]*Dynamic_Row_Table[[Tenure (in months)]:[Tenure (in months)]]*$F$4*(1+$Q40)/12) -(IF($Q40<0,'Dynamic CM'!$G$4,'Dynamic CM'!$G$4*(($F$4*(1+$Q40)/$F$4)^'Dynamic CM'!$H$4)) *VLOOKUP($D$4,EAD_Table[#All],MATCH("EAD",EAD_Table[#Headers],0),FALSE) *$F$4*(1+$Q40))} -> 7.893766 | T40: {=($F$5*(1+$Q40)*'User Segmentation'!$I$49) -Dynamic_Row_Table[[Fixed Cost]:[Fixed Cost]] -(Dynamic_Row_Table[[Funding Rate]:[Funding Rate]]*Dynamic_Row_Table[[Tenure (in months)]:[Tenure (in months)]]*$F$5*(1+$Q40)/12) -(IF($Q40<0,'Dynamic CM'!$G$5,'Dynamic CM'!$G$5*(($F$5*(1+$Q40)/$F$5)^'Dynamic CM'!$H$5)) *VLOOKUP($D$5,EAD_Table[#All],MATCH("EAD",EAD_Table[#Headers],0),FALSE) *$F$5*(1+$Q40))} -> 34.560439 | U40: {=($F$6*(1+$Q40)*'User Segmentation'!$I$49) -Dynamic_Row_Table[[Fixed Cost]:[Fixed Cost]] -(Dynamic_Row_Table[[Funding Rate]:[Funding Rate]]*Dynamic_Row_Table[[Tenure (in months)]:[Tenure (in months)]]*$F$6*(1+$Q40)/12) -(IF($Q40<0,'Dynamic CM'!$G$6,'Dynamic CM'!$G$6*(($F$6*(1+$Q40)/$F$6)^'Dynamic CM'!$H$6)) *VLOOKUP($D$6,EAD_Table[#All],MATCH("EAD",EAD_Table[#Headers],0),FALSE) *$F$6*(1+$Q40))} -> 3.9543701
Q41: 2.3 | R41: {=($F$3*(1+$Q41)*'User Segmentation'!$I$49) -Dynamic_Row_Table[[Fixed Cost]:[Fixed Cost]] -(Dynamic_Row_Table[[Funding Rate]:[Funding Rate]]*Dynamic_Row_Table[[Tenure (in months)]:[Tenure (in months)]]*$F$3*(1+$Q41)/12) -(IF($Q41<0,'Dynamic CM'!$G$3,'Dynamic CM'!$G$3*(($F$3*(1+$Q41)/$F$3)^'Dynamic CM'!$H$3)) *VLOOKUP($D$3,EAD_Table[#All],MATCH("EAD",EAD_Table[#Headers],0),FALSE) *$F$3*(1+$Q41))} -> -40.147035 | S41: {=($F$4*(1+$Q41)*'User Segmentation'!$I$49) -Dynamic_Row_Table[[Fixed Cost]:[Fixed Cost]] -(Dynamic_Row_Table[[Funding Rate]:[Funding Rate]]*Dynamic_Row_Table[[Tenure (in months)]:[Tenure (in months)]]*$F$4*(1+$Q41)/12) -(IF($Q41<0,'Dynamic CM'!$G$4,'Dynamic CM'!$G$4*(($F$4*(1+$Q41)/$F$4)^'Dynamic CM'!$H$4)) *VLOOKUP($D$4,EAD_Table[#All],MATCH("EAD",EAD_Table[#Headers],0),FALSE) *$F$4*(1+$Q41))} -> 7.720801 | T41: {=($F$5*(1+$Q41)*'User Segmentation'!$I$49) -Dynamic_Row_Table[[Fixed Cost]:[Fixed Cost]] -(Dynamic_Row_Table[[Funding Rate]:[Funding Rate]]*Dynamic_Row_Table[[Tenure (in months)]:[Tenure (in months)]]*$F$5*(1+$Q41)/12) -(IF($Q41<0,'Dynamic CM'!$G$5,'Dynamic CM'!$G$5*(($F$5*(1+$Q41)/$F$5)^'Dynamic CM'!$H$5)) *VLOOKUP($D$5,EAD_Table[#All],MATCH("EAD",EAD_Table[#Headers],0),FALSE) *$F$5*(1+$Q41))} -> 35.115839 | U41: {=($F$6*(1+$Q41)*'User Segmentation'!$I$49) -Dynamic_Row_Table[[Fixed Cost]:[Fixed Cost]] -(Dynamic_Row_Table[[Funding Rate]:[Funding Rate]]*Dynamic_Row_Table[[Tenure (in months)]:[Tenure (in months)]]*$F$6*(1+$Q41)/12) -(IF($Q41<0,'Dynamic CM'!$G$6,'Dynamic CM'!$G$6*(($F$6*(1+$Q41)/$F$6)^'Dynamic CM'!$H$6)) *VLOOKUP($D$6,EAD_Table[#All],MATCH("EAD",EAD_Table[#Headers],0),FALSE) *$F$6*(1+$Q41))} -> 3.8162777
Q42: 2.4 | R42: {=($F$3*(1+$Q42)*'User Segmentation'!$I$49) -Dynamic_Row_Table[[Fixed Cost]:[Fixed Cost]] -(Dynamic_Row_Table[[Funding Rate]:[Funding Rate]]*Dynamic_Row_Table[[Tenure (in months)]:[Tenure (in months)]]*$F$3*(1+$Q42)/12) -(IF($Q42<0,'Dynamic CM'!$G$3,'Dynamic CM'!$G$3*(($F$3*(1+$Q42)/$F$3)^'Dynamic CM'!$H$3)) *VLOOKUP($D$3,EAD_Table[#All],MATCH("EAD",EAD_Table[#Headers],0),FALSE) *$F$3*(1+$Q42))} -> -43.925752 | S42: {=($F$4*(1+$Q42)*'User Segmentation'!$I$49) -Dynamic_Row_Table[[Fixed Cost]:[Fixed Cost]] -(Dynamic_Row_Table[[Funding Rate]:[Funding Rate]]*Dynamic_Row_Table[[Tenure (in months)]:[Tenure (in months)]]*$F$4*(1+$Q42)/12) -(IF($Q42<0,'Dynamic CM'!$G$4,'Dynamic CM'!$G$4*(($F$4*(1+$Q42)/$F$4)^'Dynamic CM'!$H$4)) *VLOOKUP($D$4,EAD_Table[#All],MATCH("EAD",EAD_Table[#Headers],0),FALSE) *$F$4*(1+$Q42))} -> 7.5115663 | T42: {=($F$5*(1+$Q42)*'User Segmentation'!$I$49) -Dynamic_Row_Table[[Fixed Cost]:[Fixed Cost]] -(Dynamic_Row_Table[[Funding Rate]:[Funding Rate]]*Dynamic_Row_Table[[Tenure (in months)]:[Tenure (in months)]]*$F$5*(1+$Q42)/12) -(IF($Q42<0,'Dynamic CM'!$G$5,'Dynamic CM'!$G$5*(($F$5*(1+$Q42)/$F$5)^'Dynamic CM'!$H$5)) *VLOOKUP($D$5,EAD_Table[#All],MATCH("EAD",EAD_Table[#Headers],0),FALSE) *$F$5*(1+$Q42))} -> 35.632391 | U42: {=($F$6*(1+$Q42)*'User Segmentation'!$I$49) -Dynamic_Row_Table[[Fixed Cost]:[Fixed Cost]] -(Dynamic_Row_Table[[Funding Rate]:[Funding Rate]]*Dynamic_Row_Table[[Tenure (in months)]:[Tenure (in months)]]*$F$6*(1+$Q42)/12) -(IF($Q42<0,'Dynamic CM'!$G$6,'Dynamic CM'!$G$6*(($F$6*(1+$Q42)/$F$6)^'Dynamic CM'!$H$6)) *VLOOKUP($D$6,EAD_Table[#All],MATCH("EAD",EAD_Table[#Headers],0),FALSE) *$F$6*(1+$Q42))} -> 3.6530762
Q43: 2.5 | R43: {=($F$3*(1+$Q43)*'User Segmentation'!$I$49) -Dynamic_Row_Table[[Fixed Cost]:[Fixed Cost]] -(Dynamic_Row_Table[[Funding Rate]:[Funding Rate]]*Dynamic_Row_Table[[Tenure (in months)]:[Tenure (in months)]]*$F$3*(1+$Q43)/12) -(IF($Q43<0,'Dynamic CM'!$G$3,'Dynamic CM'!$G$3*(($F$3*(1+$Q43)/$F$3)^'Dynamic CM'!$H$3)) *VLOOKUP($D$3,EAD_Table[#All],MATCH("EAD",EAD_Table[#Headers],0),FALSE) *$F$3*(1+$Q43))} -> -47.932972 | S43: {=($F$4*(1+$Q43)*'User Segmentation'!$I$49) -Dynamic_Row_Table[[Fixed Cost]:[Fixed Cost]] -(Dynamic_Row_Table[[Funding Rate]:[Funding Rate]]*Dynamic_Row_Table[[Tenure (in months)]:[Tenure (in months)]]*$F$4*(1+$Q43)/12) -(IF($Q43<0,'Dynamic CM'!$G$4,'Dynamic CM'!$G$4*(($F$4*(1+$Q43)/$F$4)^'Dynamic CM'!$H$4)) *VLOOKUP($D$4,EAD_Table[#All],MATCH("EAD",EAD_Table[#Headers],0),FALSE) *$F$4*(1+$Q43))} -> 7.2657137 | T43: {=($F$5*(1+$Q43)*'User Segmentation'!$I$49) -Dynamic_Row_Table[[Fixed Cost]:[Fixed Cost]] -(Dynamic_Row_Table[[Funding Rate]:[Funding Rate]]*Dynamic_Row_Table[[Tenure (in months)]:[Tenure (in months)]]*$F$5*(1+$Q43)/12) -(IF($Q43<0,'Dynamic CM'!$G$5,'Dynamic CM'!$G$5*(($F$5*(1+$Q43)/$F$5)^'Dynamic CM'!$H$5)) *VLOOKUP($D$5,EAD_Table[#All],MATCH("EAD",EAD_Table[#Headers],0),FALSE) *$F$5*(1+$Q43))} -> 36.11001 | U43: {=($F$6*(1+$Q43)*'User Segmentation'!$I$49) -Dynamic_Row_Table[[Fixed Cost]:[Fixed Cost]] -(Dynamic_Row_Table[[Funding Rate]:[Funding Rate]]*Dynamic_Row_Table[[Tenure (in months)]:[Tenure (in months)]]*$F$6*(1+$Q43)/12) -(IF($Q43<0,'Dynamic CM'!$G$6,'Dynamic CM'!$G$6*(($F$6*(1+$Q43)/$F$6)^'Dynamic CM'!$H$6)) *VLOOKUP($D$6,EAD_Table[#All],MATCH("EAD",EAD_Table[#Headers],0),FALSE) *$F$6*(1+$Q43))} -> 3.4645246
Q44: 2.6 | R44: {=($F$3*(1+$Q44)*'User Segmentation'!$I$49) -Dynamic_Row_Table[[Fixed Cost]:[Fixed Cost]] -(Dynamic_Row_Table[[Funding Rate]:[Funding Rate]]*Dynamic_Row_Table[[Tenure (in months)]:[Tenure (in months)]]*$F$3*(1+$Q44)/12) -(IF($Q44<0,'Dynamic CM'!$G$3,'Dynamic CM'!$G$3*(($F$3*(1+$Q44)/$F$3)^'Dynamic CM'!$H$3)) *VLOOKUP($D$3,EAD_Table[#All],MATCH("EAD",EAD_Table[#Headers],0),FALSE) *$F$3*(1+$Q44))} -> -52.174664 | S44: {=($F$4*(1+$Q44)*'User Segmentation'!$I$49) -Dynamic_Row_Table[[Fixed Cost]:[Fixed Cost]] -(Dynamic_Row_Table[[Funding Rate]:[Funding Rate]]*Dynamic_Row_Table[[Tenure (in months)]:[Tenure (in months)]]*$F$4*(1+$Q44)/12) -(IF($Q44<0,'Dynamic CM'!$G$4,'Dynamic CM'!$G$4*(($F$4*(1+$Q44)/$F$4)^'Dynamic CM'!$H$4)) *VLOOKUP($D$4,EAD_Table[#All],MATCH("EAD",EAD_Table[#Headers],0),FALSE) *$F$4*(1+$Q44))} -> 6.982902 | T44: {=($F$5*(1+$Q44)*'User Segmentation'!$I$49) -Dynamic_Row_Table[[Fixed Cost]:[Fixed Cost]] -(Dynamic_Row_Table[[Funding Rate]:[Funding Rate]]*Dynamic_Row_Table[[Tenure (in months)]:[Tenure (in months)]]*$F$5*(1+$Q44)/12) -(IF($Q44<0,'Dynamic CM'!$G$5,'Dynamic CM'!$G$5*(($F$5*(1+$Q44)/$F$5)^'Dynamic CM'!$H$5)) *VLOOKUP($D$5,EAD_Table[#All],MATCH("EAD",EAD_Table[#Headers],0),FALSE) *$F$5*(1+$Q44))} -> 36.548619 | U44: {=($F$6*(1+$Q44)*'User Segmentation'!$I$49) -Dynamic_Row_Table[[Fixed Cost]:[Fixed Cost]] -(Dynamic_Row_Table[[Funding Rate]:[Funding Rate]]*Dynamic_Row_Table[[Tenure (in months)]:[Tenure (in months)]]*$F$6*(1+$Q44)/12) -(IF($Q44<0,'Dynamic CM'!$G$6,'Dynamic CM'!$G$6*(($F$6*(1+$Q44)/$F$6)^'Dynamic CM'!$H$6)) *VLOOKUP($D$6,EAD_Table[#All],MATCH("EAD",EAD_Table[#Headers],0),FALSE) *$F$6*(1+$Q44))} -> 3.2503867
